Workbook

Sheet Inicio
B1: SISTEMA CONTABLE MULTI-CLIENTE — MYPE Chile
B2: Normativa: NIIF Pymes (BT N°82) · LIR D.L. 824 · D.L. 825 IVA · Sin Macros
B4: ¿CÓMO EMPEZAR? — Siga estos pasos en orden
B5: 1️⃣ | C5: → Clientes | D5: Registre sus clientes (RUT, razón social, giro). Use la hoja 'Nuevo Cliente' como formulario.
B6: 2️⃣ | C6: → Cuentas | D6: Revise el Plan de Cuentas. Ya viene precargado con ~95 cuentas estándar por cliente.
B7: 3️⃣ | C7: → Libro Diario | D7: Ingrese los asientos contables día a día. Cada asiento debe cuadrar (Debe = Haber).
B8: 4️⃣ | C8: → Libro Mayor | D8: Consulte los saldos por cuenta. Se calculan automáticamente desde el Libro Diario.
B9: 5️⃣ | C9: → Balance General | D9: Revise el Estado de Situación Financiera. Se genera automáticamente.
B10: 6️⃣ | C10: → Estado Resultados | D10: Revise las utilidades o pérdidas del período. Se genera automáticamente.
B11: 7️⃣ | C11: → Indicadores | D11: Consulte los KPIs financieros con semáforos (liquidez, deuda, rentabilidad).
B12: 8️⃣ | C12: → Flujo de Caja | D12: Analice la salud de caja: runway, burn rate, punto de equilibrio.
B14: CONSEJOS IMPORTANTES
B15: 💡 | C15: Las celdas con fondo AMARILLO son editables. Las demás se calculan automáticamente — no las modifique.
B16: 💡 | C16: Cada asiento en el Libro Diario DEBE cuadrar: la suma del Debe = suma del Haber (partida doble).
B17: 💡 | C17: Use los filtros de Cliente y Año en la parte superior de cada hoja para cambiar la vista.
B18: 💡 | C18: Los indicadores con 🟢🟡🔴 se comparan contra benchmarks SERCOTEC/CMF para MYPE chilenas.
B19: 💡 | C19: Para auditar el archivo, pídale a Claude: 'audita la contabilidad' o 'revisa el programa contable'.
B21: Sistema contable para MYPE Chile — NIIF Pymes · LIR · D.L. 825 IVA · Ley 20.720 · CMF · SERCOTEC · CORFO — v2.0 (2025)
B23: AUTORES
B24: Sandro A. Gómez Araya | C24: Software Craftsman | D24: furiolabs.cl
B25: Danilo J. Gómez Araya | C25: Contador Auditor
B26: Este proyecto es parte de las iniciativas de experimentación e innovación de furiolabs.cl
B28: ADVERTENCIA LEGAL
B29: Este template es una herramienta de apoyo para la gestión contable interna. No reemplaza la asesoría de un contador público autorizado ni la revisión por un auditor independiente. Las tasas de impuesto y referencias normativas están actualizadas a marzo de 2026 y deben verificarse ante cambios legislativos.
B30: El usuario es responsable de la correcta aplicación de la normativa tributaria a su situación particular. Para declaraciones al SII (F-29, F-22, etc.), los formularios deben completarse en sii.cl. El uso de este template no genera responsabilidad alguna para sus autores.

Sheet Marco Regulatorio
A1: MARCO REGULATORIO Y PRÁCTICAS CONTABLES
A2: Documento de referencia: normativa vigente aplicada en este sistema contable para MYPE Chile.
A4: 1. NORMA CONTABLE: NIIF para Pymes (IFRS for SMEs)
A5: Obligatoria en Chile desde 2013 para entidades sin obligación pública de rendir cuentas (Boletín Técnico N°82, Colegio de Contadores A.G.). La 3ª edición de NIIF Pymes es aplicable desde el 1 de enero de 2027 (IASB 2024).
A7: Nº | B7: Sección NIIF | C7: Tema | D7: Aplicación en este sistema | E7: Hoja(s) afectada(s) | F7: Notas
A8: 1 | B8: Sec. 2 | C8: Conceptos fundamentales | D8: Base de devengo (no caja); la partida doble rige todo el Libro Diario | E8: Libro Diario | F8: Cada asiento debe cuadrar: ΣDebe = ΣHaber
A9: 2 | B9: Sec. 3 | C9: Presentación de EEFF | D9: Sistema genera 4 EEFF: Balance, EERR, Flujo de Caja, + Indicadores | E9: Todas | F9: Falta hoja de Notas a los EEFF (recomendable para presentación formal)
A10: 3 | B10: Sec. 4 | C10: Estado de Situación Financiera | D10: Balance clasifica Corriente / No Corriente (plazo 12 meses) | E10: Balance General | F10: Activos: 1xxx / Pasivos: 2xxx / Patrimonio: 23xx
A11: 4 | B11: Sec. 5 | C11: Estado de Resultado Integral | D11: Formato por función del gasto con ingresos, costos y gastos operacionales | E11: Estado Resultados | F11: Incluye Margen Bruto, EBITDA, Resultado antes de impuesto
A12: 5 | B12: Sec. 7 | C12: Estado de Flujos de Efectivo | D12: Método indirecto, 3 secciones: Operación, Inversión, Financiamiento | E12: Flujo de Caja | F12: Cumple NIC 7 / NIIF Pymes Sec. 7
A13: 6 | B13: Sec. 10 | C13: Políticas Contables | D13: Consistencia: mismas fórmulas SUMPRODUCT aplicadas uniformemente | E13: Todas | F13: Las fórmulas no cambian entre períodos ni clientes
A14: 7 | B14: Sec. 17 | C14: Propiedad, Planta y Equipo | D14: Costo histórico menos depreciación acumulada; cuentas reguladoras 12xxxxx | E14: Balance General, Cuentas | F14: Depreciación acumulada = cuenta con saldo acreedor dentro de Activo
A15: 8 | B15: Sec. 22 | C15: Patrimonio | D15: Capital (2301001), Resultado del Ejercicio (2302001), Resultados Acumulados (2302101) | E15: Balance General | F15: Aportes de capital no constituyen renta (Art. 17 N°5 LIR)
A16: 9 | B16: Sec. 23 | C16: Ingresos | D16: Reconocimiento cuando es probable y medible; cuentas 4xxx | E16: Estado Resultados | F16: Ventas de bienes (4101001), servicios (4101002)
A17: 10 | B17: Sec. 27 | C17: Deterioro del Valor | D17: No automatizado en este template; requiere evaluación manual al cierre | E17: — | F17: Verificar indicadores de deterioro en Activos Fijos
A18: 11 | B18: Sec. 28 | C18: Beneficios a Empleados | D18: Provisión Vacaciones (2104001) incluida en plan de cuentas | E18: Cuentas, Balance | F18: Art. 67 Código del Trabajo; evaluar también IAS (Art. 163)
A19: 12 | B19: Sec. 29 | C19: Impuesto a las Ganancias | D19: Impuesto 1ª Categoría calculado en Estado de Resultados | E19: Estado Resultados | F19: Régimen Pro-Pyme 25% o General 27% (ver sección tributaria)
A21: 2. LEGISLACIÓN TRIBUTARIA CHILENA
A23: 2.1 Ley de la Renta (D.L. 824 / LIR)
A24: Nº | B24: Artículo | C24: Tema | D24: Aplicación en este sistema | E24: Hoja(s) afectada(s) | F24: Notas
A25: 1 | B25: Art. 14D | C25: Régimen Pro-Pyme | D25: Tasa de impuesto 12,5% Pro-Pyme 2025-2027 (Ley 21.755), 15% en 2028, 25% normal; o 27% General. El EERR calcula según régimen del cliente | E25: Estado Resultados | F25: Ingresos ≤ 75.000 UF anuales → Pro-Pyme. Ley 21.755: tasa 12,5% (2025-2027)
A26: 2 | B26: Art. 17 N°5 | C26: Aportes de capital | D26: No constituyen renta; se registran como Capital (2301001), no como ingreso | E26: Libro Diario, Balance | F26: Asiento: Debe Caja/Bancos — Haber Capital
A27: 3 | B27: Art. 29-33 | C27: Base imponible (RLI) | D27: EERR llega a Resultado antes de Impuesto; se aplican agregados/deducciones Art. 33 | E27: Estado Resultados | F27: Gastos rechazados se agregan a la RLI
A28: 4 | B28: Art. 31 N°1-7 | C28: Gastos deducibles | D28: Gastos registrados en cuentas 3xxx deben cumplir requisitos de deducibilidad | E28: Libro Diario, EERR | F28: Pagados, necesarios para el giro, acreditados
A29: 5 | B29: Art. 31 N°5 | C29: Depreciación normal | D29: Tablas SII (Res. Ex. N°43/2002); vida útil según tipo de activo | E29: Balance General | F29: Depreciación acelerada = 1/3 de vida útil normal
A30: 6 | B30: Art. 31 N°5 bis | C30: Depreciación instantánea | D30: 100% en un ejercicio para bienes nuevos adquiridos por Pro-Pyme (Ley 21.210) | E30: Balance General | F30: Solo aplica régimen Pro-Pyme (Art. 14D)
A31: 7 | B31: Art. 41 | C31: Corrección monetaria | D31: No implementada automáticamente; requiere ajuste manual de cierre | E31: — | F31: Actualización por IPC de activos y pasivos
A32: 8 | B32: Art. 42 N°2 | C32: Retención honorarios | D32: Tasa 2024: 13,75% (Ley 21.133 transitorio); sube a 17% en 2028 | E32: Estado Resultados | F32: Nota en celda de Asesorías y Honorarios
A33: 9 | B33: Art. 84 | C33: PPM | D33: Cuenta PPM (1107201) en plan de cuentas; se compensa contra impuesto anual | E33: Balance General, Cuentas | F33: Pagos provisionales mensuales
A35: 2.2 Impuesto al Valor Agregado (D.L. 825)
A36: Nº | B36: Artículo | C36: Tema | D36: Aplicación en este sistema | E36: Hoja(s) afectada(s) | F36: Notas
A37: 1 | B37: Art. 8 | C37: Hecho gravado | D37: Ventas y servicios afectos se registran en cuentas 4xxx con IVA separado | E37: Libro Diario | F37: IVA = 19% sobre base imponible
A38: 2 | B38: Art. 14 | C38: Tasa vigente: 19% | D38: Cálculos de IVA en el sistema usan 19% como tasa fija | E38: Libro Diario | F38: Vigente 2024-2025
A39: 3 | B39: Art. 23 | C39: Crédito Fiscal | D39: Cuenta 1107101 (IVA Crédito Fiscal) registra IVA pagado en compras | E39: Cuentas, Libro Diario | F39: Activo Corriente; se compensa contra Débito Fiscal
A40: 4 | B40: Art. 24 | C40: Débito Fiscal | D40: Cuenta 2105101 (IVA Débito Fiscal) registra IVA cobrado en ventas | E40: Cuentas, Libro Diario | F40: Pasivo Corriente; se paga en F-29 mensual
A42: 2.3 Legislación Laboral (Código del Trabajo)
A43: Nº | B43: Artículo | C43: Tema | D43: Aplicación en este sistema | E43: Hoja(s) afectada(s) | F43: Notas
A44: 1 | B44: Art. 44 | C44: Remuneración mínima | D44: Gasto remuneraciones (3103001); referencia: $500.000 (2025) | E44: Libro Diario, EERR | F44: Verificar monto vigente cada año
A45: 2 | B45: Art. 67 | C45: Feriado anual (vacaciones) | D45: Provisión Vacaciones (2104001) en plan de cuentas; pasivo corriente | E45: Cuentas, Balance | F45: Derecho irrenunciable; NIIF Pymes Sec. 28
A46: 3 | B46: Art. 163 | C46: Indemnización por años | D46: Cuenta 2104002 (Provisión IAS) disponible si la empresa tiene política de pago | E46: Cuentas | F46: No obligatoria salvo política interna de la empresa
A48: 3. PRÁCTICAS CONTABLES IMPLEMENTADAS EN ESTE TEMPLATE
A50: 3.1 Principios contables aplicados
A51: Nº | B51: Principio | C51: Cómo se aplica en este template | D51: Fundamento normativo
A52: 1 | B52: Partida Doble | C52: Todo registro en el Libro Diario tiene mínimo 2 líneas: un débito y un crédito de igual monto | E52: NIIF Marco Conceptual / Código de Comercio Art. 25
A53: 2 | B53: Base de Devengo | C53: Los ingresos y gastos se reconocen cuando se producen, no cuando se cobran/pagan | E53: NIIF Pymes Sec. 2
A54: 3 | B54: Moneda Funcional | C54: Todos los montos en Pesos Chilenos (CLP), sin decimales | E54: NIIF Pymes Sec. 30
A55: 4 | B55: Entidad Separada | C55: Cada cliente es una entidad independiente; los datos se filtran por ID de cliente | E55: NIIF Pymes Sec. 2
A56: 5 | B56: Empresa en Marcha | C56: Se asume continuidad operacional; los indicadores de Flujo de Caja alertan sobre riesgo | E56: NIIF Pymes Sec. 3.8 / Ley 20.720
A57: 6 | B57: Consistencia | C57: Las mismas fórmulas y criterios se aplican uniformemente a todos los clientes y períodos | E57: NIIF Pymes Sec. 10
A58: 7 | B58: Materialidad | C58: El sistema registra todas las transacciones; el umbral de materialidad lo define el contador | E58: NIIF Pymes Sec. 2.6
A59: 8 | B59: Prudencia | C59: Los indicadores con semáforo 🔴 alertan sobre situaciones financieras adversas | E59: NIIF Marco Conceptual
A61: 3.2 Estructura del Plan de Cuentas (PCGA Chile)
A62: Rango | B62: Tipo | C62: Naturaleza | D62: Saldo Normal | E62: Ejemplos | F62: Cuenta especial
A63: 1000000–1999999 | B63: ACTIVO | C63: Deudora | D63: Debe > Haber | E63: Caja (1101001), Bancos (1101002), CxC (1104001), PPE (1201001) | F63: Dep. Acumulada: saldo acreedor (cuenta reguladora)
A64: 2000000–2099999 | B64: PASIVO CORRIENTE | C64: Acreedora | D64: Haber > Debe | E64: Proveedores (2102001), Remuneraciones (2103001), IVA DF (2105101)
A65: 2100000–2299999 | B65: PASIVO NO CORRIENTE | C65: Acreedora | D65: Haber > Debe | E65: Deudas Bancarias LP (2201001), Préstamos LP (2201002)
A66: 2300000–2399999 | B66: PATRIMONIO | C66: Acreedora | D66: Haber > Debe | E66: Capital (2301001), Resultado Ejercicio (2302001), Acumulados (2302101)
A67: 3000000–3999999 | B67: GASTO / PÉRDIDA | C67: Deudora | D67: Debe > Haber | E67: Costo Ventas (3101001), Remuneraciones (3103001), Arriendos (3103002)
A68: 4000000–4999999 | B68: INGRESO / GANANCIA | C68: Acreedora | D68: Haber > Debe | E68: Ventas Bienes (4101001), Servicios (4101002), Otros Ingresos (4201001)
A70: 3.3 Motor de cálculo: fórmulas SUMPRODUCT
A71: Este template NO usa macros VBA. Todos los cálculos entre hojas se realizan mediante fórmulas SUMPRODUCT que filtran dinámicamente por ID de Cliente, Código de Cuenta y Año. Esto garantiza transparencia, auditabilidad y compatibilidad con cualquier versión de Excel.
A72: Patrón estándar: =SUMPRODUCT(('Libro Diario'!$A$10:$A$5000=cliente)*('Libro Diario'!$E$10:$E$5000=código)*(YEAR('Libro Diario'!$C$10:$C$5000)=año)*('Libro Diario'!$H$10:$H$5000))
A73: Las fórmulas usan rangos fijos ($A$10:$A$5000) para permitir hasta ~4.990 líneas de asientos por cliente sin modificar la estructura.
A75: 3.4 Convenciones de presentación
A76: Elemento | B76: Cómo se presenta | C76: Descripción
A77: Celdas editables | B77: Fondo amarillo (FFF8E1) | D77: El usuario solo debe modificar celdas con fondo amarillo
A78: Celdas calculadas | B78: Fondo blanco o azul claro | D78: No modificar: contienen fórmulas que se actualizan automáticamente
A79: Filtros de cliente/año | B79: Parte superior de cada hoja | D79: Dropdowns con validación de datos desde la hoja Clientes
A80: Semáforos (indicadores) | B80: 🟢 Bueno / 🟡 Precaución / 🔴 Crítico | D80: Umbrales basados en benchmarks SERCOTEC/CMF/CORFO para MYPE
A81: Notas normativas | B81: Celdas con fondo amarillo claro (FFFDE7) | D81: Citas de artículos y secciones de ley relevantes para cada sección
A82: Formato moneda | B82: CLP sin decimales, con separador de miles | D82: Formato: #,##0 o $#,##0 según contexto
A84: 4. INDICADORES FINANCIEROS — UMBRALES DE REFERENCIA
A85: Los umbrales utilizados en la hoja Indicadores y Flujo de Caja están basados en estándares SERCOTEC, CMF y CORFO para micro y pequeñas empresas chilenas. Pueden variar según sector.
A87: Indicador | B87: 🟢 Bueno | C87: 🟡 Precaución | D87: 🔴 Crítico | E87: Fuente | F87: Hoja
A88: Razón Corriente | B88: ≥ 1.5 | C88: 1.0 – 1.4 | D88: < 1.0 | E88: SERCOTEC | F88: Indicadores
A89: Razón Ácida (Prueba Ácida) | B89: ≥ 1.0 | C89: 0.7 – 0.9 | D89: < 0.7 | E89: SERCOTEC | F89: Indicadores
A90: Razón de Efectivo | B90: ≥ 0.3 | C90: 0.1 – 0.29 | D90: < 0.1 | E90: SERCOTEC | F90: Indicadores
A91: Endeudamiento (P/A) | B91: ≤ 0.5 | C91: 0.5 – 0.7 | D91: > 0.7 | E91: CMF | F91: Indicadores
A92: Deuda / Patrimonio (D/E) | B92: ≤ 1.0 | C92: 1.0 – 2.0 | D92: > 2.0 | E92: CMF | F92: Indicadores
A93: ROE | B93: ≥ 10% | C93: 5 – 10% | D93: < 5% | E93: CORFO | F93: Indicadores
A94: Margen Bruto | B94: ≥ 30% | C94: 15 – 30% | D94: < 15% | E94: SERCOTEC | F94: Indicadores
A95: Runway (meses) | B95: ≥ 3 | C95: 1 – 3 | D95: < 1 | E95: SERCOTEC | F95: Flujo de Caja
A96: Ciclo Conversión Efectivo | B96: ≤ 30 días | C96: 30 – 60 días | D96: > 60 días | E96: CMF | F96: Flujo de Caja
A97: DSCR (Cobertura deuda) | B97: ≥ 1.25 | C97: 1.0 – 1.24 | D97: < 1.0 | E97: Banca comercial | F97: Flujo de Caja
A99: 5. DECLARACIONES Y OBLIGACIONES SII
A100: Este template prepara la información contable necesaria para las siguientes declaraciones. La generación del formulario electrónico se realiza en el portal SII (sii.cl).
A102: Formulario | B102: Descripción | C102: Frecuencia | D102: Plazo | E102: Dato del template | F102: Hojas fuente
A103: F-29 | B103: IVA y Pagos Provisionales Mensuales | C103: Mensual | D103: Día 12 del mes siguiente | E103: IVA CF/DF, PPM, retenciones | F103: Libro Diario, Balance
A104: F-22 | B104: Declaración de Renta Anual | C104: Anual | D104: Abril (plazo máximo junio) | E104: Ingresos, gastos, RLI, impuesto | F104: Estado Resultados
A105: F-50 | B105: Retenciones de honorarios | C105: Mensual | D105: Día 12 del mes siguiente | E105: Retenciones Art. 42 N°2 | F105: Libro Diario
A106: DJ 1879 | B106: Retenciones honorarios anuales | C106: Anual | D106: Marzo | E106: Detalle anual retenciones | F106: Libro Diario
A107: DJ 1887 | B107: Sueldos y otras rentas | C107: Anual | D107: Marzo | E107: Detalle remuneraciones | F107: Libro Diario
A108: I001/I002 | B108: Balance de 8 Columnas SII | C108: Anual | D108: Junto con F-22 | E108: Saldos por cuenta | F108: Balance General, L. Mayor
A110: 6. REFERENCIAS LEGALES ADICIONALES
A112: Norma | B112: Descripción | C112: Relación con este template
A113: Ley 20.720 | B113: Ley de Insolvencia y Reestructuración | C113: Los indicadores de Flujo de Caja (Runway, Razón Corriente) ayudan a detectar estado de insolvencia tempranamente
A114: Código de Comercio Art. 25 | B114: Obligación de llevar libros contables | C114: El Libro Diario cumple la obligación legal de registrar operaciones cronológicamente
A115: Ley 20.780 / 21.210 | B115: Reforma Tributaria 2014/2020 | C115: Derogación del FUT, creación del RAI. Solo aplica RAI en este sistema
A116: Ley 21.133 | B116: Reforma honorarios | C116: Retención progresiva: 14,5% (2025) → 15,25% (2026) → 16% (2027) → 17% (2028+)
A117: Res. Ex. SII N°43/2002 | B117: Tablas de vida útil | C117: Referencia para depreciación de activos fijos en las notas del Balance General
...

Sheet Clientes
A1: REGISTRO DE CLIENTES
A2: 📝 Ingrese un cliente por fila. El ID (ej: CLI001) se usa en todas las demás hojas. Use la hoja 'Nuevo Cliente' como formulario de ingreso, o escriba directamente aquí.
A3: ID Cliente | B3: RUT | C3: Razón Social | D3: Giro | E3: Domicilio | F3: Comuna | G3: Representante Legal | H3: RUT Rep.Legal | I3: Teléfono | J3: E-mail
A4: CLI001 | B4: 76.000.000-0 | C4: ← Ingrese aquí su primer cliente

Sheet Nuevo Cliente
A1: FORMULARIO DE REGISTRO DE CLIENTE
A3: 📝 Complete los campos amarillos y luego copie la fila de Vista Previa (fila 20) a la hoja CLIENTES. Los campos con borde amarillo son editables.
A5: ID Cliente | F5: Ej: CLI004 — identificador único
A6: RUT | F6: Formato: 76.543.210-K
A7: Razón Social | F7: Nombre legal de la empresa
A8: Giro | F8: Actividad económica principal
A9: Domicilio | F9: Calle, número
A10: Comuna
A11: Representante Legal | F11: Nombre completo
A12: RUT Rep. Legal | F12: Formato: 12.345.678-9
A13: Teléfono | F13: Ej: (56-2) 2345 6789
A14: E-mail | F14: Correo de contacto
A16: ▶ Para agregar: copie la fila de datos ingresados y péguela en la hoja CLIENTES
A18: VISTA PREVIA — Fila a copiar en hoja CLIENTES
A19: ID Cliente | B19: RUT | C19: Razón Social | D19: Giro | E19: Domicilio | F19: Comuna
A20: =C5 -> 0 | B20: =C6 -> 0 | C20: =C7 -> 0 | D20: =C8 -> 0 | E20: =C9 -> 0 | F20: =C10 -> 0

Sheet Cuentas
A1: PLAN DE CUENTAS — MULTI-CLIENTE
A2: 📝 Cada cliente tiene su propio plan de cuentas (~95 cuentas estándar PCGA Chile). Puede agregar cuentas nuevas usando el formulario de la fila 4, o directamente en la tabla. Los códigos siguen: 1xxx=Activo, 2xxx=Pasivo, 3xxx=Gasto, 4xxx=Ingreso.
A3: AGREGAR NUEVA CUENTA
A4: Cliente: | C4: Código: | E4: Nombre Cuenta: | G4: Tipo:
A5: ↑ Complete los campos y copie manualmente la fila de datos en la tabla inferior. El Código debe ser único por cliente.
A7: ID Cliente | B7: Código Cuenta | C7: Nombre Cuenta | D7: Tipo | E7: Cód. Tipo | F7: Subtipo/Clasificación | G7: Activo en Uso | H7: Notas
A8: CLI001 | B8: 1101001 | C8: Caja | D8: ACTIVO | E8: =IF(D8="ACTIVO",1,IF(D8="PASIVO",2,IF(D8="PERDIDA",3,IF(D8="GANANCIA",4,0)))) -> 1 | G8: Sí
A9: CLI001 | B9: 1101002 | C9: Bancos | D9: ACTIVO | E9: =IF(D9="ACTIVO",1,IF(D9="PASIVO",2,IF(D9="PERDIDA",3,IF(D9="GANANCIA",4,0)))) -> 1 | G9: Sí
A10: CLI001 | B10: 1104001 | C10: Clientes Varios | D10: ACTIVO | E10: =IF(D10="ACTIVO",1,IF(D10="PASIVO",2,IF(D10="PERDIDA",3,IF(D10="GANANCIA",4,0)))) -> 1 | G10: Sí
A11: CLI001 | B11: 1106001 | C11: Retiros Acumulados-Ej. Anteriores. | D11: ACTIVO | E11: =IF(D11="ACTIVO",1,IF(D11="PASIVO",2,IF(D11="PERDIDA",3,IF(D11="GANANCIA",4,0)))) -> 1 | G11: Sí
A12: CLI001 | B12: 1106002 | C12: Cta. Cte. SOCIO | D12: ACTIVO | E12: =IF(D12="ACTIVO",1,IF(D12="PASIVO",2,IF(D12="PERDIDA",3,IF(D12="GANANCIA",4,0)))) -> 1 | G12: Sí
A13: CLI001 | B13: 1106003 | C13: Cta. Cte. SOCIO | D13: ACTIVO | E13: =IF(D13="ACTIVO",1,IF(D13="PASIVO",2,IF(D13="PERDIDA",3,IF(D13="GANANCIA",4,0)))) -> 1 | G13: Sí
A14: CLI001 | B14: 1106004 | C14: Cta. Cte. SOCIO | D14: ACTIVO | E14: =IF(D14="ACTIVO",1,IF(D14="PASIVO",2,IF(D14="PERDIDA",3,IF(D14="GANANCIA",4,0)))) -> 1 | G14: Sí
A15: CLI001 | B15: 1107001 | C15: Impuestos por Recuperar - Renta | D15: ACTIVO | E15: =IF(D15="ACTIVO",1,IF(D15="PASIVO",2,IF(D15="PERDIDA",3,IF(D15="GANANCIA",4,0)))) -> 1 | G15: Sí
A16: CLI001 | B16: 1107002 | C16: Impuestos por Recuperar - IVA | D16: ACTIVO | E16: =IF(D16="ACTIVO",1,IF(D16="PASIVO",2,IF(D16="PERDIDA",3,IF(D16="GANANCIA",4,0)))) -> 1 | G16: Sí
A17: CLI001 | B17: 1107003 | C17: Imposiciones por Recuperar | D17: ACTIVO | E17: =IF(D17="ACTIVO",1,IF(D17="PASIVO",2,IF(D17="PERDIDA",3,IF(D17="GANANCIA",4,0)))) -> 1 | G17: Sí
A18: CLI001 | B18: 1107101 | C18: IVA Crédito Fiscal 19% | D18: ACTIVO | E18: =IF(D18="ACTIVO",1,IF(D18="PASIVO",2,IF(D18="PERDIDA",3,IF(D18="GANANCIA",4,0)))) -> 1 | G18: Sí
A19: CLI001 | B19: 1107103 | C19: IVA Crédito Fiscal no Retenido 11% | D19: ACTIVO | E19: =IF(D19="ACTIVO",1,IF(D19="PASIVO",2,IF(D19="PERDIDA",3,IF(D19="GANANCIA",4,0)))) -> 1 | G19: Sí
... A292: CLI003 | B292: 4201102 | C292: Otros Ingresos | D292: GANANCIA | E292: =IF(D292="ACTIVO",1,IF(D292="PASIVO",2,IF(D292="PERDIDA",3,IF(D292="GANANCIA",4,0)))) -> 4 | G292: Sí
E293: =IF(D293="ACTIVO",1,IF(D293="PASIVO",2,IF(D293="PERDIDA",3,IF(D293="GANANCIA",4,0)))) -> 0
E294: =IF(D294="ACTIVO",1,IF(D294="PASIVO",2,IF(D294="PERDIDA",3,IF(D294="GANANCIA",4,0)))) -> 0
E295: =IF(D295="ACTIVO",1,IF(D295="PASIVO",2,IF(D295="PERDIDA",3,IF(D295="GANANCIA",4,0)))) -> 0
E296: =IF(D296="ACTIVO",1,IF(D296="PASIVO",2,IF(D296="PERDIDA",3,IF(D296="GANANCIA",4,0)))) -> 0
E297: =IF(D297="ACTIVO",1,IF(D297="PASIVO",2,IF(D297="PERDIDA",3,IF(D297="GANANCIA",4,0)))) -> 0
E298: =IF(D298="ACTIVO",1,IF(D298="PASIVO",2,IF(D298="PERDIDA",3,IF(D298="GANANCIA",4,0)))) -> 0
E299: =IF(D299="ACTIVO",1,IF(D299="PASIVO",2,IF(D299="PERDIDA",3,IF(D299="GANANCIA",4,0)))) -> 0
E300: =IF(D300="ACTIVO",1,IF(D300="PASIVO",2,IF(D300="PERDIDA",3,IF(D300="GANANCIA",4,0)))) -> 0
E301: =IF(D301="ACTIVO",1,IF(D301="PASIVO",2,IF(D301="PERDIDA",3,IF(D301="GANANCIA",4,0)))) -> 0
E302: =IF(D302="ACTIVO",1,IF(D302="PASIVO",2,IF(D302="PERDIDA",3,IF(D302="GANANCIA",4,0)))) -> 0
E303: =IF(D303="ACTIVO",1,IF(D303="PASIVO",2,IF(D303="PERDIDA",3,IF(D303="GANANCIA",4,0)))) -> 0
E304: =IF(D304="ACTIVO",1,IF(D304="PASIVO",2,IF(D304="PERDIDA",3,IF(D304="GANANCIA",4,0)))) -> 0
... E342: =IF(D342="ACTIVO",1,IF(D342="PASIVO",2,IF(D342="PERDIDA",3,IF(D342="GANANCIA",4,0)))) -> 0

Sheet Libro Diario
A1: LIBRO DIARIO — INGRESO DE ASIENTOS CONTABLES
A2: 📝 INSTRUCCIONES: (1) Seleccione Cliente en A5 (2) Ingrese Nº Asiento, Fecha, Código de Cuenta, Glosa, y montos en Debe o Haber (3) Cada asiento DEBE cuadrar: Σ Debe = Σ Haber (4) La fila 6 muestra si el asiento cuadra ✓ o no ✗
A3: INGRESAR NUEVO ASIENTO
A4: Cliente | B4: Nº Asiento | C4: Fecha | D4: Glosa General | E4: Cuenta (Cód.) | F4: Nombre Cuenta | G4: Detalle | H4: Debe (CLP) | I4: Haber (CLP) | J4: Tipo | K4: Sucursal
F5: =IFERROR(INDEX(Cuentas!$C$8:$C$500,MATCH(A5&"|"&E5,Cuentas!$A$8:$A$500&"|"&Cuentas!$B$8:$B$500,0)),"") -> 0
A6: TOTALES DEL ASIENTO INGRESADO → | H6: =SUMIF($A$10:$A$5000,A5,$H$10:$H$5000) -> 0 | I6: =SUMIF($A$10:$A$5000,A5,$I$10:$I$5000) -> 0 | J6: =IF(H6=I6,"✓ CUADRADO","✗ DESCUADRADO") -> ✓ CUADRADO
A8: FILTRO ACTIVO — Escriba un ID de cliente en B8 para filtrar (ej: CLI001), o "TODOS" para ver todos los asientos
A9: Cliente | B9: Nº Asiento | C9: Fecha | D9: Mes | E9: Código Cta. | F9: Nombre Cuenta | G9: Glosa / Detalle | H9: Debe (CLP) | I9: Haber (CLP) | J9: Tipo | K9: Sucursal
D10: =IF(C10="","",MONTH(C10)) | F10: =IFERROR(INDEX(Cuentas!$C$8:$C$500,MATCH(A10&"|"&E10,Cuentas!$A$8:$A$500&"|"&Cuentas!$B$8:$B$500,0)),"") -> 0 | G10: ← Ingrese su primer asiento aquí
D11: =IF(C11="","",MONTH(C11)) | F11: =IFERROR(INDEX(Cuentas!$C$8:$C$500,MATCH(A11&"|"&E11,Cuentas!$A$8:$A$500&"|"&Cuentas!$B$8:$B$500,0)),"") -> 0
D12: =IF(C12="","",MONTH(C12)) | F12: =IFERROR(INDEX(Cuentas!$C$8:$C$500,MATCH(A12&"|"&E12,Cuentas!$A$8:$A$500&"|"&Cuentas!$B$8:$B$500,0)),"") -> 0
D13: =IF(C13="","",MONTH(C13)) | F13: =IFERROR(INDEX(Cuentas!$C$8:$C$500,MATCH(A13&"|"&E13,Cuentas!$A$8:$A$500&"|"&Cuentas!$B$8:$B$500,0)),"") -> 0
D14: =IF(C14="","",MONTH(C14)) | F14: =IFERROR(INDEX(Cuentas!$C$8:$C$500,MATCH(A14&"|"&E14,Cuentas!$A$8:$A$500&"|"&Cuentas!$B$8:$B$500,0)),"") -> 0
D15: =IF(C15="","",MONTH(C15)) | F15: =IFERROR(INDEX(Cuentas!$C$8:$C$500,MATCH(A15&"|"&E15,Cuentas!$A$8:$A$500&"|"&Cuentas!$B$8:$B$500,0)),"") -> 0
D16: =IF(C16="","",MONTH(C16)) | F16: =IFERROR(INDEX(Cuentas!$C$8:$C$500,MATCH(A16&"|"&E16,Cuentas!$A$8:$A$500&"|"&Cuentas!$B$8:$B$500,0)),"") -> 0
D17: =IF(C17="","",MONTH(C17)) | F17: =IFERROR(INDEX(Cuentas!$C$8:$C$500,MATCH(A17&"|"&E17,Cuentas!$A$8:$A$500&"|"&Cuentas!$B$8:$B$500,0)),"") -> 0
D18: =IF(C18="","",MONTH(C18)) | F18: =IFERROR(INDEX(Cuentas!$C$8:$C$500,MATCH(A18&"|"&E18,Cuentas!$A$8:$A$500&"|"&Cuentas!$B$8:$B$500,0)),"") -> 0
D19: =IF(C19="","",MONTH(C19)) | F19: =IFERROR(INDEX(Cuentas!$C$8:$C$500,MATCH(A19&"|"&E19,Cuentas!$A$8:$A$500&"|"&Cuentas!$B$8:$B$500,0)),"") -> 0
D20: =IF(C20="","",MONTH(C20)) | F20: =IFERROR(INDEX(Cuentas!$C$8:$C$500,MATCH(A20&"|"&E20,Cuentas!$A$8:$A$500&"|"&Cuentas!$B$8:$B$500,0)),"") -> 0
D21: =IF(C21="","",MONTH(C21)) | F21: =IFERROR(INDEX(Cuentas!$C$8:$C$500,MATCH(A21&"|"&E21,Cuentas!$A$8:$A$500&"|"&Cuentas!$B$8:$B$500,0)),"") -> 0
D22: =IF(C22="","",MONTH(C22)) | F22: =IFERROR(INDEX(Cuentas!$C$8:$C$500,MATCH(A22&"|"&E22,Cuentas!$A$8:$A$500&"|"&Cuentas!$B$8:$B$500,0)),"") -> 0
... D517: =IF(C517="","",MONTH(C517)) | F517: =IFERROR(INDEX(Cuentas!$C$8:$C$500,MATCH(A517&"|"&E517,Cuentas!$A$8:$A$500&"|"&Cuentas!$B$8:$B$500,0)),"") -> 0

Sheet Libro Mayor
A1: LIBRO MAYOR — RESUMEN POR CUENTA
A2: 📊 Este resumen se calcula AUTOMÁTICAMENTE desde el Libro Diario. Cambie el Cliente y Año en los campos amarillos de arriba para consultar otro período. No modifique las celdas de datos — son fórmulas.
A3: FILTROS DE CONSULTA
A4: Cliente: | B4: CLI001 | D4: Período (Año): | E4: 2025 | F4: ← Escriba el ID de cliente y el año a consultar
A6: Código Cta. | B6: Nombre Cuenta | C6: Tipo | D6: Tratamiento | E6: Total Debe | F6: Total Haber | G6: Saldo Deudor | H6: Saldo Acreedor | I6: Saldo Final
A7: Las fórmulas calculan automáticamente desde Libro Diario filtrando por el Cliente y Período seleccionados arriba.
A8: 1101001 | B8: =IFERROR(INDEX(Cuentas!$C$8:$C$500,MATCH($B$4&"|"&A8,Cuentas!$A$8:$A$500&"|"&Cuentas!$B$8:$B$500,0)),"Caja") -> Caja | C8: =IFERROR(INDEX(Cuentas!$D$8:$D$500,MATCH($B$4&"|"&A8,Cuentas!$A$8:$A$500&"|"&Cuentas!$B$8:$B$500,0)),"ACTIVO") -> ACTIVO | D8: =IF(OR(C8="ACTIVO",C8="PERDIDA"),"Deudor","Acreedor") -> Deudor | E8: =SUMPRODUCT(('Libro Diario'!$A$10:$A$5000=$B$4)*('Libro Diario'!$E$10:$E$5000=A8)*(YEAR('Libro Diario'!$C$10:$C$5000)=$E$4)*('Libro Diario'!$H$10:$H$5000)) -> 0 | F8: =SUMPRODUCT(('Libro Diario'!$A$10:$A$5000=$B$4)*('Libro Diario'!$E$10:$E$5000=A8)*(YEAR('Libro Diario'!$C$10:$C$5000)=$E$4)*('Libro Diario'!$I$10:$I$5000)) -> 0 | G8: =IF(E8>F8,E8-F8,"") | H8: =IF(F8>E8,F8-E8,"") | I8: =IF(OR(C8="ACTIVO",C8="PERDIDA"),E8-F8,F8-E8) -> 0
A9: 1101002 | B9: =IFERROR(INDEX(Cuentas!$C$8:$C$500,MATCH($B$4&"|"&A9,Cuentas!$A$8:$A$500&"|"&Cuentas!$B$8:$B$500,0)),"Bancos") -> Bancos | C9: =IFERROR(INDEX(Cuentas!$D$8:$D$500,MATCH($B$4&"|"&A9,Cuentas!$A$8:$A$500&"|"&Cuentas!$B$8:$B$500,0)),"ACTIVO") -> ACTIVO | D9: =IF(OR(C9="ACTIVO",C9="PERDIDA"),"Deudor","Acreedor") -> Deudor | E9: =SUMPRODUCT(('Libro Diario'!$A$10:$A$5000=$B$4)*('Libro Diario'!$E$10:$E$5000=A9)*(YEAR('Libro Diario'!$C$10:$C$5000)=$E$4)*('Libro Diario'!$H$10:$H$5000)) -> 0 | F9: =SUMPRODUCT(('Libro Diario'!$A$10:$A$5000=$B$4)*('Libro Diario'!$E$10:$E$5000=A9)*(YEAR('Libro Diario'!$C$10:$C$5000)=$E$4)*('Libro Diario'!$I$10:$I$5000)) -> 0 | G9: =IF(E9>F9,E9-F9,"") | H9: =IF(F9>E9,F9-E9,"") | I9: =IF(OR(C9="ACTIVO",C9="PERDIDA"),E9-F9,F9-E9) -> 0
A10: 1104001 | B10: =IFERROR(INDEX(Cuentas!$C$8:$C$500,MATCH($B$4&"|"&A10,Cuentas!$A$8:$A$500&"|"&Cuentas!$B$8:$B$500,0)),"Clientes Varios") -> Clientes Varios | C10: =IFERROR(INDEX(Cuentas!$D$8:$D$500,MATCH($B$4&"|"&A10,Cuentas!$A$8:$A$500&"|"&Cuentas!$B$8:$B$500,0)),"ACTIVO") -> ACTIVO | D10: =IF(OR(C10="ACTIVO",C10="PERDIDA"),"Deudor","Acreedor") -> Deudor | E10: =SUMPRODUCT(('Libro Diario'!$A$10:$A$5000=$B$4)*('Libro Diario'!$E$10:$E$5000=A10)*(YEAR('Libro Diario'!$C$10:$C$5000)=$E$4)*('Libro Diario'!$H$10:$H$5000)) -> 0 | F10: =SUMPRODUCT(('Libro Diario'!$A$10:$A$5000=$B$4)*('Libro Diario'!$E$10:$E$5000=A10)*(YEAR('Libro Diario'!$C$10:$C$5000)=$E$4)*('Libro Diario'!$I$10:$I$5000)) -> 0 | G10: =IF(E10>F10,E10-F10,"") | H10: =IF(F10>E10,F10-E10,"") | I10: =IF(OR(C10="ACTIVO",C10="PERDIDA"),E10-F10,F10-E10) -> 0
A11: 1106001 | B11: =IFERROR(INDEX(Cuentas!$C$8:$C$500,MATCH($B$4&"|"&A11,Cuentas!$A$8:$A$500&"|"&Cuentas!$B$8:$B$500,0)),"Retiros Acumulados-Ej. Anteriores.") -> Retiros Acumulados-Ej. Anteriores. | C11: =IFERROR(INDEX(Cuentas!$D$8:$D$500,MATCH($B$4&"|"&A11,Cuentas!$A$8:$A$500&"|"&Cuentas!$B$8:$B$500,0)),"ACTIVO") -> ACTIVO | D11: =IF(OR(C11="ACTIVO",C11="PERDIDA"),"Deudor","Acreedor") -> Deudor | E11: =SUMPRODUCT(('Libro Diario'!$A$10:$A$5000=$B$4)*('Libro Diario'!$E$10:$E$5000=A11)*(YEAR('Libro Diario'!$C$10:$C$5000)=$E$4)*('Libro Diario'!$H$10:$H$5000)) -> 0 | F11: =SUMPRODUCT(('Libro Diario'!$A$10:$A$5000=$B$4)*('Libro Diario'!$E$10:$E$5000=A11)*(YEAR('Libro Diario'!$C$10:$C$5000)=$E$4)*('Libro Diario'!$I$10:$I$5000)) -> 0 | G11: =IF(E11>F11,E11-F11,"") | H11: =IF(F11>E11,F11-E11,"") | I11: =IF(OR(C11="ACTIVO",C11="PERDIDA"),E11-F11,F11-E11) -> 0
A12: 1106002 | B12: =IFERROR(INDEX(Cuentas!$C$8:$C$500,MATCH($B$4&"|"&A12,Cuentas!$A$8:$A$500&"|"&Cuentas!$B$8:$B$500,0)),"Cta. Cte. SOCIO") -> Cta. Cte. SOCIO | C12: =IFERROR(INDEX(Cuentas!$D$8:$D$500,MATCH($B$4&"|"&A12,Cuentas!$A$8:$A$500&"|"&Cuentas!$B$8:$B$500,0)),"ACTIVO") -> ACTIVO | D12: =IF(OR(C12="ACTIVO",C12="PERDIDA"),"Deudor","Acreedor") -> Deudor | E12: =SUMPRODUCT(('Libro Diario'!$A$10:$A$5000=$B$4)*('Libro Diario'!$E$10:$E$5000=A12)*(YEAR('Libro Diario'!$C$10:$C$5000)=$E$4)*('Libro Diario'!$H$10:$H$5000)) -> 0 | F12: =SUMPRODUCT(('Libro Diario'!$A$10:$A$5000=$B$4)*('Libro Diario'!$E$10:$E$5000=A12)*(YEAR('Libro Diario'!$C$10:$C$5000)=$E$4)*('Libro Diario'!$I$10:$I$5000)) -> 0 | G12: =IF(E12>F12,E12-F12,"") | H12: =IF(F12>E12,F12-E12,"") | I12: =IF(OR(C12="ACTIVO",C12="PERDIDA"),E12-F12,F12-E12) -> 0
A13: 1106003 | B13: =IFERROR(INDEX(Cuentas!$C$8:$C$500,MATCH($B$4&"|"&A13,Cuentas!$A$8:$A$500&"|"&Cuentas!$B$8:$B$500,0)),"Cta. Cte. SOCIO") -> Cta. Cte. SOCIO | C13: =IFERROR(INDEX(Cuentas!$D$8:$D$500,MATCH($B$4&"|"&A13,Cuentas!$A$8:$A$500&"|"&Cuentas!$B$8:$B$500,0)),"ACTIVO") -> ACTIVO | D13: =IF(OR(C13="ACTIVO",C13="PERDIDA"),"Deudor","Acreedor") -> Deudor | E13: =SUMPRODUCT(('Libro Diario'!$A$10:$A$5000=$B$4)*('Libro Diario'!$E$10:$E$5000=A13)*(YEAR('Libro Diario'!$C$10:$C$5000)=$E$4)*('Libro Diario'!$H$10:$H$5000)) -> 0 | F13: =SUMPRODUCT(('Libro Diario'!$A$10:$A$5000=$B$4)*('Libro Diario'!$E$10:$E$5000=A13)*(YEAR('Libro Diario'!$C$10:$C$5000)=$E$4)*('Libro Diario'!$I$10:$I$5000)) -> 0 | G13: =IF(E13>F13,E13-F13,"") | H13: =IF(F13>E13,F13-E13,"") | I13: =IF(OR(C13="ACTIVO",C13="PERDIDA"),E13-F13,F13-E13) -> 0
A14: 1106004 | B14: =IFERROR(INDEX(Cuentas!$C$8:$C$500,MATCH($B$4&"|"&A14,Cuentas!$A$8:$A$500&"|"&Cuentas!$B$8:$B$500,0)),"Cta. Cte. SOCIO") -> Cta. Cte. SOCIO | C14: =IFERROR(INDEX(Cuentas!$D$8:$D$500,MATCH($B$4&"|"&A14,Cuentas!$A$8:$A$500&"|"&Cuentas!$B$8:$B$500,0)),"ACTIVO") -> ACTIVO | D14: =IF(OR(C14="ACTIVO",C14="PERDIDA"),"Deudor","Acreedor") -> Deudor | E14: =SUMPRODUCT(('Libro Diario'!$A$10:$A$5000=$B$4)*('Libro Diario'!$E$10:$E$5000=A14)*(YEAR('Libro Diario'!$C$10:$C$5000)=$E$4)*('Libro Diario'!$H$10:$H$5000)) -> 0 | F14: =SUMPRODUCT(('Libro Diario'!$A$10:$A$5000=$B$4)*('Libro Diario'!$E$10:$E$5000=A14)*(YEAR('Libro Diario'!$C$10:$C$5000)=$E$4)*('Libro Diario'!$I$10:$I$5000)) -> 0 | G14: =IF(E14>F14,E14-F14,"") | H14: =IF(F14>E14,F14-E14,"") | I14: =IF(OR(C14="ACTIVO",C14="PERDIDA"),E14-F14,F14-E14) -> 0
A15: 1107001 | B15: =IFERROR(INDEX(Cuentas!$C$8:$C$500,MATCH($B$4&"|"&A15,Cuentas!$A$8:$A$500&"|"&Cuentas!$B$8:$B$500,0)),"Impuestos por Recuperar - Renta") -> Impuestos por Recuperar - Renta | C15: =IFERROR(INDEX(Cuentas!$D$8:$D$500,MATCH($B$4&"|"&A15,Cuentas!$A$8:$A$500&"|"&Cuentas!$B$8:$B$500,0)),"ACTIVO") -> ACTIVO | D15: =IF(OR(C15="ACTIVO",C15="PERDIDA"),"Deudor","Acreedor") -> Deudor | E15: =SUMPRODUCT(('Libro Diario'!$A$10:$A$5000=$B$4)*('Libro Diario'!$E$10:$E$5000=A15)*(YEAR('Libro Diario'!$C$10:$C$5000)=$E$4)*('Libro Diario'!$H$10:$H$5000)) -> 0 | F15: =SUMPRODUCT(('Libro Diario'!$A$10:$A$5000=$B$4)*('Libro Diario'!$E$10:$E$5000=A15)*(YEAR('Libro Diario'!$C$10:$C$5000)=$E$4)*('Libro Diario'!$I$10:$I$5000)) -> 0 | G15: =IF(E15>F15,E15-F15,"") | H15: =IF(F15>E15,F15-E15,"") | I15: =IF(OR(C15="ACTIVO",C15="PERDIDA"),E15-F15,F15-E15) -> 0
A16: 1107002 | B16: =IFERROR(INDEX(Cuentas!$C$8:$C$500,MATCH($B$4&"|"&A16,Cuentas!$A$8:$A$500&"|"&Cuentas!$B$8:$B$500,0)),"Impuestos por Recuperar - IVA") -> Impuestos por Recuperar - IVA | C16: =IFERROR(INDEX(Cuentas!$D$8:$D$500,MATCH($B$4&"|"&A16,Cuentas!$A$8:$A$500&"|"&Cuentas!$B$8:$B$500,0)),"ACTIVO") -> ACTIVO | D16: =IF(OR(C16="ACTIVO",C16="PERDIDA"),"Deudor","Acreedor") -> Deudor | E16: =SUMPRODUCT(('Libro Diario'!$A$10:$A$5000=$B$4)*('Libro Diario'!$E$10:$E$5000=A16)*(YEAR('Libro Diario'!$C$10:$C$5000)=$E$4)*('Libro Diario'!$H$10:$H$5000)) -> 0 | F16: =SUMPRODUCT(('Libro Diario'!$A$10:$A$5000=$B$4)*('Libro Diario'!$E$10:$E$5000=A16)*(YEAR('Libro Diario'!$C$10:$C$5000)=$E$4)*('Libro Diario'!$I$10:$I$5000)) -> 0 | G16: =IF(E16>F16,E16-F16,"") | H16: =IF(F16>E16,F16-E16,"") | I16: =IF(OR(C16="ACTIVO",C16="PERDIDA"),E16-F16,F16-E16) -> 0
A17: 1107003 | B17: =IFERROR(INDEX(Cuentas!$C$8:$C$500,MATCH($B$4&"|"&A17,Cuentas!$A$8:$A$500&"|"&Cuentas!$B$8:$B$500,0)),"Imposiciones por Recuperar") -> Imposiciones por Recuperar | C17: =IFERROR(INDEX(Cuentas!$D$8:$D$500,MATCH($B$4&"|"&A17,Cuentas!$A$8:$A$500&"|"&Cuentas!$B$8:$B$500,0)),"ACTIVO") -> ACTIVO | D17: =IF(OR(C17="ACTIVO",C17="PERDIDA"),"Deudor","Acreedor") -> Deudor | E17: =SUMPRODUCT(('Libro Diario'!$A$10:$A$5000=$B$4)*('Libro Diario'!$E$10:$E$5000=A17)*(YEAR('Libro Diario'!$C$10:$C$5000)=$E$4)*('Libro Diario'!$H$10:$H$5000)) -> 0 | F17: =SUMPRODUCT(('Libro Diario'!$A$10:$A$5000=$B$4)*('Libro Diario'!$E$10:$E$5000=A17)*(YEAR('Libro Diario'!$C$10:$C$5000)=$E$4)*('Libro Diario'!$I$10:$I$5000)) -> 0 | G17: =IF(E17>F17,E17-F17,"") | H17: =IF(F17>E17,F17-E17,"") | I17: =IF(OR(C17="ACTIVO",C17="PERDIDA"),E17-F17,F17-E17) -> 0
A18: 1107101 | B18: =IFERROR(INDEX(Cuentas!$C$8:$C$500,MATCH($B$4&"|"&A18,Cuentas!$A$8:$A$500&"|"&Cuentas!$B$8:$B$500,0)),"IVA Crédito Fiscal 19%") -> IVA Crédito Fiscal 19% | C18: =IFERROR(INDEX(Cuentas!$D$8:$D$500,MATCH($B$4&"|"&A18,Cuentas!$A$8:$A$500&"|"&Cuentas!$B$8:$B$500,0)),"ACTIVO") -> ACTIVO | D18: =IF(OR(C18="ACTIVO",C18="PERDIDA"),"Deudor","Acreedor") -> Deudor | E18: =SUMPRODUCT(('Libro Diario'!$A$10:$A$5000=$B$4)*('Libro Diario'!$E$10:$E$5000=A18)*(YEAR('Libro Diario'!$C$10:$C$5000)=$E$4)*('Libro Diario'!$H$10:$H$5000)) -> 0 | F18: =SUMPRODUCT(('Libro Diario'!$A$10:$A$5000=$B$4)*('Libro Diario'!$E$10:$E$5000=A18)*(YEAR('Libro Diario'!$C$10:$C$5000)=$E$4)*('Libro Diario'!$I$10:$I$5000)) -> 0 | G18: =IF(E18>F18,E18-F18,"") | H18: =IF(F18>E18,F18-E18,"") | I18: =IF(OR(C18="ACTIVO",C18="PERDIDA"),E18-F18,F18-E18) -> 0
A19: 1107103 | B19: =IFERROR(INDEX(Cuentas!$C$8:$C$500,MATCH($B$4&"|"&A19,Cuentas!$A$8:$A$500&"|"&Cuentas!$B$8:$B$500,0)),"IVA Crédito Fiscal no Retenido 11%") -> IVA Crédito Fiscal no Retenido 11% | C19: =IFERROR(INDEX(Cuentas!$D$8:$D$500,MATCH($B$4&"|"&A19,Cuentas!$A$8:$A$500&"|"&Cuentas!$B$8:$B$500,0)),"ACTIVO") -> ACTIVO | D19: =IF(OR(C19="ACTIVO",C19="PERDIDA"),"Deudor","Acreedor") -> Deudor | E19: =SUMPRODUCT(('Libro Diario'!$A$10:$A$5000=$B$4)*('Libro Diario'!$E$10:$E$5000=A19)*(YEAR('Libro Diario'!$C$10:$C$5000)=$E$4)*('Libro Diario'!$H$10:$H$5000)) -> 0 | F19: =SUMPRODUCT(('Libro Diario'!$A$10:$A$5000=$B$4)*('Libro Diario'!$E$10:$E$5000=A19)*(YEAR('Libro Diario'!$C$10:$C$5000)=$E$4)*('Libro Diario'!$I$10:$I$5000)) -> 0 | G19: =IF(E19>F19,E19-F19,"") | H19: =IF(F19>E19,F19-E19,"") | I19: =IF(OR(C19="ACTIVO",C19="PERDIDA"),E19-F19,F19-E19) -> 0
A20: 1107201 | B20: =IFERROR(INDEX(Cuentas!$C$8:$C$500,MATCH($B$4&"|"&A20,Cuentas!$A$8:$A$500&"|"&Cuentas!$B$8:$B$500,0)),"P.P.M.") -> P.P.M. | C20: =IFERROR(INDEX(Cuentas!$D$8:$D$500,MATCH($B$4&"|"&A20,Cuentas!$A$8:$A$500&"|"&Cuentas!$B$8:$B$500,0)),"ACTIVO") -> ACTIVO | D20: =IF(OR(C20="ACTIVO",C20="PERDIDA"),"Deudor","Acreedor") -> Deudor | E20: =SUMPRODUCT(('Libro Diario'!$A$10:$A$5000=$B$4)*('Libro Diario'!$E$10:$E$5000=A20)*(YEAR('Libro Diario'!$C$10:$C$5000)=$E$4)*('Libro Diario'!$H$10:$H$5000)) -> 0 | F20: =SUMPRODUCT(('Libro Diario'!$A$10:$A$5000=$B$4)*('Libro Diario'!$E$10:$E$5000=A20)*(YEAR('Libro Diario'!$C$10:$C$5000)=$E$4)*('Libro Diario'!$I$10:$I$5000)) -> 0 | G20: =IF(E20>F20,E20-F20,"") | H20: =IF(F20>E20,F20-E20,"") | I20: =IF(OR(C20="ACTIVO",C20="PERDIDA"),E20-F20,F20-E20) -> 0
A21: 1107301 | B21: =IFERROR(INDEX(Cuentas!$C$8:$C$500,MATCH($B$4&"|"&A21,Cuentas!$A$8:$A$500&"|"&Cuentas!$B$8:$B$500,0)),"Credito Diessel Transporte Carga") -> Credito Diessel Transporte Carga | C21: =IFERROR(INDEX(Cuentas!$D$8:$D$500,MATCH($B$4&"|"&A21,Cuentas!$A$8:$A$500&"|"&Cuentas!$B$8:$B$500,0)),"ACTIVO") -> ACTIVO | D21: =IF(OR(C21="ACTIVO",C21="PERDIDA"),"Deudor","Acreedor") -> Deudor | E21: =SUMPRODUCT(('Libro Diario'!$A$10:$A$5000=$B$4)*('Libro Diario'!$E$10:$E$5000=A21)*(YEAR('Libro Diario'!$C$10:$C$5000)=$E$4)*('Libro Diario'!$H$10:$H$5000)) -> 0 | F21: =SUMPRODUCT(('Libro Diario'!$A$10:$A$5000=$B$4)*('Libro Diario'!$E$10:$E$5000=A21)*(YEAR('Libro Diario'!$C$10:$C$5000)=$E$4)*('Libro Diario'!$I$10:$I$5000)) -> 0 | G21: =IF(E21>F21,E21-F21,"") | H21: =IF(F21>E21,F21-E21,"") | I21: =IF(OR(C21="ACTIVO",C21="PERDIDA"),E21-F21,F21-E21) -> 0
A22: 1107302 | B22: =IFERROR(INDEX(Cuentas!$C$8:$C$500,MATCH($B$4&"|"&A22,Cuentas!$A$8:$A$500&"|"&Cuentas!$B$8:$B$500,0)),"Art. 33 bis (4%) Activo Fijo") -> Art. 33 bis (4%) Activo Fijo | C22: =IFERROR(INDEX(Cuentas!$D$8:$D$500,MATCH($B$4&"|"&A22,Cuentas!$A$8:$A$500&"|"&Cuentas!$B$8:$B$500,0)),"ACTIVO") -> ACTIVO | D22: =IF(OR(C22="ACTIVO",C22="PERDIDA"),"Deudor","Acreedor") -> Deudor | E22: =SUMPRODUCT(('Libro Diario'!$A$10:$A$5000=$B$4)*('Libro Diario'!$E$10:$E$5000=A22)*(YEAR('Libro Diario'!$C$10:$C$5000)=$E$4)*('Libro Diario'!$H$10:$H$5000)) -> 0 | F22: =SUMPRODUCT(('Libro Diario'!$A$10:$A$5000=$B$4)*('Libro Diario'!$E$10:$E$5000=A22)*(YEAR('Libro Diario'!$C$10:$C$5000)=$E$4)*('Libro Diario'!$I$10:$I$5000)) -> 0 | G22: =IF(E22>F22,E22-F22,"") | H22: =IF(F22>E22,F22-E22,"") | I22: =IF(OR(C22="ACTIVO",C22="PERDIDA"),E22-F22,F22-E22) -> 0
A23: 1107401 | B23: =IFERROR(INDEX(Cuentas!$C$8:$C$500,MATCH($B$4&"|"&A23,Cuentas!$A$8:$A$500&"|"&Cuentas!$B$8:$B$500,0)),"Contribuciones Bienes Raices- Credito") -> Contribuciones Bienes Raices- Credito | C23: =IFERROR(INDEX(Cuentas!$D$8:$D$500,MATCH($B$4&"|"&A23,Cuentas!$A$8:$A$500&"|"&Cuentas!$B$8:$B$500,0)),"ACTIVO") -> ACTIVO | D23: =IF(OR(C23="ACTIVO",C23="PERDIDA"),"Deudor","Acreedor") -> Deudor | E23: =SUMPRODUCT(('Libro Diario'!$A$10:$A$5000=$B$4)*('Libro Diario'!$E$10:$E$5000=A23)*(YEAR('Libro Diario'!$C$10:$C$5000)=$E$4)*('Libro Diario'!$H$10:$H$5000)) -> 0 | F23: =SUMPRODUCT(('Libro Diario'!$A$10:$A$5000=$B$4)*('Libro Diario'!$E$10:$E$5000=A23)*(YEAR('Libro Diario'!$C$10:$C$5000)=$E$4)*('Libro Diario'!$I$10:$I$5000)) -> 0 | G23: =IF(E23>F23,E23-F23,"") | H23: =IF(F23>E23,F23-E23,"") | I23: =IF(OR(C23="ACTIVO",C23="PERDIDA"),E23-F23,F23-E23) -> 0
A24: 1107402 | B24: =IFERROR(INDEX(Cuentas!$C$8:$C$500,MATCH($B$4&"|"&A24,Cuentas!$A$8:$A$500&"|"&Cuentas!$B$8:$B$500,0)),"Pagos Provisionales por Utilidades Absorbidas") -> Pagos Provisionales por Utilidades Absorbidas | C24: =IFERROR(INDEX(Cuentas!$D$8:$D$500,MATCH($B$4&"|"&A24,Cuentas!$A$8:$A$500&"|"&Cuentas!$B$8:$B$500,0)),"ACTIVO") -> ACTIVO | D24: =IF(OR(C24="ACTIVO",C24="PERDIDA"),"Deudor","Acreedor") -> Deudor | E24: =SUMPRODUCT(('Libro Diario'!$A$10:$A$5000=$B$4)*('Libro Diario'!$E$10:$E$5000=A24)*(YEAR('Libro Diario'!$C$10:$C$5000)=$E$4)*('Libro Diario'!$H$10:$H$5000)) -> 0 | F24: =SUMPRODUCT(('Libro Diario'!$A$10:$A$5000=$B$4)*('Libro Diario'!$E$10:$E$5000=A24)*(YEAR('Libro Diario'!$C$10:$C$5000)=$E$4)*('Libro Diario'!$I$10:$I$5000)) -> 0 | G24: =IF(E24>F24,E24-F24,"") | H24: =IF(F24>E24,F24-E24,"") | I24: =IF(OR(C24="ACTIVO",C24="PERDIDA"),E24-F24,F24-E24) -> 0
A25: 1107404 | B25: =IFERROR(INDEX(Cuentas!$C$8:$C$500,MATCH($B$4&"|"&A25,Cuentas!$A$8:$A$500&"|"&Cuentas!$B$8:$B$500,0)),"Credito Sence") -> Credito Sence | C25: =IFERROR(INDEX(Cuentas!$D$8:$D$500,MATCH($B$4&"|"&A25,Cuentas!$A$8:$A$500&"|"&Cuentas!$B$8:$B$500,0)),"ACTIVO") -> ACTIVO | D25: =IF(OR(C25="ACTIVO",C25="PERDIDA"),"Deudor","Acreedor") -> Deudor | E25: =SUMPRODUCT(('Libro Diario'!$A$10:$A$5000=$B$4)*('Libro Diario'!$E$10:$E$5000=A25)*(YEAR('Libro Diario'!$C$10:$C$5000)=$E$4)*('Libro Diario'!$H$10:$H$5000)) -> 0 | F25: =SUMPRODUCT(('Libro Diario'!$A$10:$A$5000=$B$4)*('Libro Diario'!$E$10:$E$5000=A25)*(YEAR('Libro Diario'!$C$10:$C$5000)=$E$4)*('Libro Diario'!$I$10:$I$5000)) -> 0 | G25: =IF(E25>F25,E25-F25,"") | H25: =IF(F25>E25,F25-E25,"") | I25: =IF(OR(C25="ACTIVO",C25="PERDIDA"),E25-F25,F25-E25) -> 0
A26: 1108001 | B26: =IFERROR(INDEX(Cuentas!$C$8:$C$500,MATCH($B$4&"|"&A26,Cuentas!$A$8:$A$500&"|"&Cuentas!$B$8:$B$500,0)),"Mercaderías") -> Mercaderías | C26: =IFERROR(INDEX(Cuentas!$D$8:$D$500,MATCH($B$4&"|"&A26,Cuentas!$A$8:$A$500&"|"&Cuentas!$B$8:$B$500,0)),"ACTIVO") -> ACTIVO | D26: =IF(OR(C26="ACTIVO",C26="PERDIDA"),"Deudor","Acreedor") -> Deudor | E26: =SUMPRODUCT(('Libro Diario'!$A$10:$A$5000=$B$4)*('Libro Diario'!$E$10:$E$5000=A26)*(YEAR('Libro Diario'!$C$10:$C$5000)=$E$4)*('Libro Diario'!$H$10:$H$5000)) -> 0 | F26: =SUMPRODUCT(('Libro Diario'!$A$10:$A$5000=$B$4)*('Libro Diario'!$E$10:$E$5000=A26)*(YEAR('Libro Diario'!$C$10:$C$5000)=$E$4)*('Libro Diario'!$I$10:$I$5000)) -> 0 | G26: =IF(E26>F26,E26-F26,"") | H26: =IF(F26>E26,F26-E26,"") | I26: =IF(OR(C26="ACTIVO",C26="PERDIDA"),E26-F26,F26-E26) -> 0
A27: 1108002 | B27: =IFERROR(INDEX(Cuentas!$C$8:$C$500,MATCH($B$4&"|"&A27,Cuentas!$A$8:$A$500&"|"&Cuentas!$B$8:$B$500,0)),"Materia Prima e Insumos") -> Materia Prima e Insumos | C27: =IFERROR(INDEX(Cuentas!$D$8:$D$500,MATCH($B$4&"|"&A27,Cuentas!$A$8:$A$500&"|"&Cuentas!$B$8:$B$500,0)),"ACTIVO") -> ACTIVO | D27: =IF(OR(C27="ACTIVO",C27="PERDIDA"),"Deudor","Acreedor") -> Deudor | E27: =SUMPRODUCT(('Libro Diario'!$A$10:$A$5000=$B$4)*('Libro Diario'!$E$10:$E$5000=A27)*(YEAR('Libro Diario'!$C$10:$C$5000)=$E$4)*('Libro Diario'!$H$10:$H$5000)) -> 0 | F27: =SUMPRODUCT(('Libro Diario'!$A$10:$A$5000=$B$4)*('Libro Diario'!$E$10:$E$5000=A27)*(YEAR('Libro Diario'!$C$10:$C$5000)=$E$4)*('Libro Diario'!$I$10:$I$5000)) -> 0 | G27: =IF(E27>F27,E27-F27,"") | H27: =IF(F27>E27,F27-E27,"") | I27: =IF(OR(C27="ACTIVO",C27="PERDIDA"),E27-F27,F27-E27) -> 0
A28: 1110001 | B28: =IFERROR(INDEX(Cuentas!$C$8:$C$500,MATCH($B$4&"|"&A28,Cuentas!$A$8:$A$500&"|"&Cuentas!$B$8:$B$500,0)),"Intereses diferidos Corto Plazo") -> Intereses diferidos Corto Plazo | C28: =IFERROR(INDEX(Cuentas!$D$8:$D$500,MATCH($B$4&"|"&A28,Cuentas!$A$8:$A$500&"|"&Cuentas!$B$8:$B$500,0)),"ACTIVO") -> ACTIVO | D28: =IF(OR(C28="ACTIVO",C28="PERDIDA"),"Deudor","Acreedor") -> Deudor | E28: =SUMPRODUCT(('Libro Diario'!$A$10:$A$5000=$B$4)*('Libro Diario'!$E$10:$E$5000=A28)*(YEAR('Libro Diario'!$C$10:$C$5000)=$E$4)*('Libro Diario'!$H$10:$H$5000)) -> 0 | F28: =SUMPRODUCT(('Libro Diario'!$A$10:$A$5000=$B$4)*('Libro Diario'!$E$10:$E$5000=A28)*(YEAR('Libro Diario'!$C$10:$C$5000)=$E$4)*('Libro Diario'!$I$10:$I$5000)) -> 0 | G28: =IF(E28>F28,E28-F28,"") | H28: =IF(F28>E28,F28-E28,"") | I28: =IF(OR(C28="ACTIVO",C28="PERDIDA"),E28-F28,F28-E28) -> 0
A29: 1201001 | B29: =IFERROR(INDEX(Cuentas!$C$8:$C$500,MATCH($B$4&"|"&A29,Cuentas!$A$8:$A$500&"|"&Cuentas!$B$8:$B$500,0)),"Vehiculos de Carga") -> Vehiculos de Carga | C29: =IFERROR(INDEX(Cuentas!$D$8:$D$500,MATCH($B$4&"|"&A29,Cuentas!$A$8:$A$500&"|"&Cuentas!$B$8:$B$500,0)),"ACTIVO") -> ACTIVO | D29: =IF(OR(C29="ACTIVO",C29="PERDIDA"),"Deudor","Acreedor") -> Deudor | E29: =SUMPRODUCT(('Libro Diario'!$A$10:$A$5000=$B$4)*('Libro Diario'!$E$10:$E$5000=A29)*(YEAR('Libro Diario'!$C$10:$C$5000)=$E$4)*('Libro Diario'!$H$10:$H$5000)) -> 0 | F29: =SUMPRODUCT(('Libro Diario'!$A$10:$A$5000=$B$4)*('Libro Diario'!$E$10:$E$5000=A29)*(YEAR('Libro Diario'!$C$10:$C$5000)=$E$4)*('Libro Diario'!$I$10:$I$5000)) -> 0 | G29: =IF(E29>F29,E29-F29,"") | H29: =IF(F29>E29,F29-E29,"") | I29: =IF(OR(C29="ACTIVO",C29="PERDIDA"),E29-F29,F29-E29) -> 0
A30: 1201002 | B30: =IFERROR(INDEX(Cuentas!$C$8:$C$500,MATCH($B$4&"|"&A30,Cuentas!$A$8:$A$500&"|"&Cuentas!$B$8:$B$500,0)),"Dep.Acum.Vehiculos de Carga") -> Dep.Acum.Vehiculos de Carga | C30: =IFERROR(INDEX(Cuentas!$D$8:$D$500,MATCH($B$4&"|"&A30,Cuentas!$A$8:$A$500&"|"&Cuentas!$B$8:$B$500,0)),"PASIVO") -> PASIVO | D30: =IF(OR(C30="ACTIVO",C30="PERDIDA"),"Deudor","Acreedor") -> Acreedor | E30: =SUMPRODUCT(('Libro Diario'!$A$10:$A$5000=$B$4)*('Libro Diario'!$E$10:$E$5000=A30)*(YEAR('Libro Diario'!$C$10:$C$5000)=$E$4)*('Libro Diario'!$H$10:$H$5000)) -> 0 | F30: =SUMPRODUCT(('Libro Diario'!$A$10:$A$5000=$B$4)*('Libro Diario'!$E$10:$E$5000=A30)*(YEAR('Libro Diario'!$C$10:$C$5000)=$E$4)*('Libro Diario'!$I$10:$I$5000)) -> 0 | G30: =IF(E30>F30,E30-F30,"") | H30: =IF(F30>E30,F30-E30,"") | I30: =IF(OR(C30="ACTIVO",C30="PERDIDA"),E30-F30,F30-E30) -> 0
A31: 1201003 | B31: =IFERROR(INDEX(Cuentas!$C$8:$C$500,MATCH($B$4&"|"&A31,Cuentas!$A$8:$A$500&"|"&Cuentas!$B$8:$B$500,0)),"Otros Vehiculos de Trabajo") -> Otros Vehiculos de Trabajo | C31: =IFERROR(INDEX(Cuentas!$D$8:$D$500,MATCH($B$4&"|"&A31,Cuentas!$A$8:$A$500&"|"&Cuentas!$B$8:$B$500,0)),"ACTIVO") -> ACTIVO | D31: =IF(OR(C31="ACTIVO",C31="PERDIDA"),"Deudor","Acreedor") -> Deudor | E31: =SUMPRODUCT(('Libro Diario'!$A$10:$A$5000=$B$4)*('Libro Diario'!$E$10:$E$5000=A31)*(YEAR('Libro Diario'!$C$10:$C$5000)=$E$4)*('Libro Diario'!$H$10:$H$5000)) -> 0 | F31: =SUMPRODUCT(('Libro Diario'!$A$10:$A$5000=$B$4)*('Libro Diario'!$E$10:$E$5000=A31)*(YEAR('Libro Diario'!$C$10:$C$5000)=$E$4)*('Libro Diario'!$I$10:$I$5000)) -> 0 | G31: =IF(E31>F31,E31-F31,"") | H31: =IF(F31>E31,F31-E31,"") | I31: =IF(OR(C31="ACTIVO",C31="PERDIDA"),E31-F31,F31-E31) -> 0
A32: 1201004 | B32: =IFERROR(INDEX(Cuentas!$C$8:$C$500,MATCH($B$4&"|"&A32,Cuentas!$A$8:$A$500&"|"&Cuentas!$B$8:$B$500,0)),"Dep. Acum. Vehículos") -> Dep. Acum. Vehículos | C32: =IFERROR(INDEX(Cuentas!$D$8:$D$500,MATCH($B$4&"|"&A32,Cuentas!$A$8:$A$500&"|"&Cuentas!$B$8:$B$500,0)),"PASIVO") -> PASIVO | D32: =IF(OR(C32="ACTIVO",C32="PERDIDA"),"Deudor","Acreedor") -> Acreedor | E32: =SUMPRODUCT(('Libro Diario'!$A$10:$A$5000=$B$4)*('Libro Diario'!$E$10:$E$5000=A32)*(YEAR('Libro Diario'!$C$10:$C$5000)=$E$4)*('Libro Diario'!$H$10:$H$5000)) -> 0 | F32: =SUMPRODUCT(('Libro Diario'!$A$10:$A$5000=$B$4)*('Libro Diario'!$E$10:$E$5000=A32)*(YEAR('Libro Diario'!$C$10:$C$5000)=$E$4)*('Libro Diario'!$I$10:$I$5000)) -> 0 | G32: =IF(E32>F32,E32-F32,"") | H32: =IF(F32>E32,F32-E32,"") | I32: =IF(OR(C32="ACTIVO",C32="PERDIDA"),E32-F32,F32-E32) -> 0
A33: 1201005 | B33: =IFERROR(INDEX(Cuentas!$C$8:$C$500,MATCH($B$4&"|"&A33,Cuentas!$A$8:$A$500&"|"&Cuentas!$B$8:$B$500,0)),"Remolques , carros") -> Remolques , carros | C33: =IFERROR(INDEX(Cuentas!$D$8:$D$500,MATCH($B$4&"|"&A33,Cuentas!$A$8:$A$500&"|"&Cuentas!$B$8:$B$500,0)),"ACTIVO") -> ACTIVO | D33: =IF(OR(C33="ACTIVO",C33="PERDIDA"),"Deudor","Acreedor") -> Deudor | E33: =SUMPRODUCT(('Libro Diario'!$A$10:$A$5000=$B$4)*('Libro Diario'!$E$10:$E$5000=A33)*(YEAR('Libro Diario'!$C$10:$C$5000)=$E$4)*('Libro Diario'!$H$10:$H$5000)) -> 0 | F33: =SUMPRODUCT(('Libro Diario'!$A$10:$A$5000=$B$4)*('Libro Diario'!$E$10:$E$5000=A33)*(YEAR('Libro Diario'!$C$10:$C$5000)=$E$4)*('Libro Diario'!$I$10:$I$5000)) -> 0 | G33: =IF(E33>F33,E33-F33,"") | H33: =IF(F33>E33,F33-E33,"") | I33: =IF(OR(C33="ACTIVO",C33="PERDIDA"),E33-F33,F33-E33) -> 0
A34: 1201006 | B34: =IFERROR(INDEX(Cuentas!$C$8:$C$500,MATCH($B$4&"|"&A34,Cuentas!$A$8:$A$500&"|"&Cuentas!$B$8:$B$500,0)),"Dep.Acum.Remolques, carros") -> Dep.Acum.Remolques, carros | C34: =IFERROR(INDEX(Cuentas!$D$8:$D$500,MATCH($B$4&"|"&A34,Cuentas!$A$8:$A$500&"|"&Cuentas!$B$8:$B$500,0)),"PASIVO") -> PASIVO | D34: =IF(OR(C34="ACTIVO",C34="PERDIDA"),"Deudor","Acreedor") -> Acreedor | E34: =SUMPRODUCT(('Libro Diario'!$A$10:$A$5000=$B$4)*('Libro Diario'!$E$10:$E$5000=A34)*(YEAR('Libro Diario'!$C$10:$C$5000)=$E$4)*('Libro Diario'!$H$10:$H$5000)) -> 0 | F34: =SUMPRODUCT(('Libro Diario'!$A$10:$A$5000=$B$4)*('Libro Diario'!$E$10:$E$5000=A34)*(YEAR('Libro Diario'!$C$10:$C$5000)=$E$4)*('Libro Diario'!$I$10:$I$5000)) -> 0 | G34: =IF(E34>F34,E34-F34,"") | H34: =IF(F34>E34,F34-E34,"") | I34: =IF(OR(C34="ACTIVO",C34="PERDIDA"),E34-F34,F34-E34) -> 0
A35: 1201007 | B35: =IFERROR(INDEX(Cuentas!$C$8:$C$500,MATCH($B$4&"|"&A35,Cuentas!$A$8:$A$500&"|"&Cuentas!$B$8:$B$500,0)),"Vehiculos") -> Vehiculos | C35: =IFERROR(INDEX(Cuentas!$D$8:$D$500,MATCH($B$4&"|"&A35,Cuentas!$A$8:$A$500&"|"&Cuentas!$B$8:$B$500,0)),"ACTIVO") -> ACTIVO | D35: =IF(OR(C35="ACTIVO",C35="PERDIDA"),"Deudor","Acreedor") -> Deudor | E35: =SUMPRODUCT(('Libro Diario'!$A$10:$A$5000=$B$4)*('Libro Diario'!$E$10:$E$5000=A35)*(YEAR('Libro Diario'!$C$10:$C$5000)=$E$4)*('Libro Diario'!$H$10:$H$5000)) -> 0 | F35: =SUMPRODUCT(('Libro Diario'!$A$10:$A$5000=$B$4)*('Libro Diario'!$E$10:$E$5000=A35)*(YEAR('Libro Diario'!$C$10:$C$5000)=$E$4)*('Libro Diario'!$I$10:$I$5000)) -> 0 | G35: =IF(E35>F35,E35-F35,"") | H35: =IF(F35>E35,F35-E35,"") | I35: =IF(OR(C35="ACTIVO",C35="PERDIDA"),E35-F35,F35-E35) -> 0
A36: 1201008 | B36: =IFERROR(INDEX(Cuentas!$C$8:$C$500,MATCH($B$4&"|"&A36,Cuentas!$A$8:$A$500&"|"&Cuentas!$B$8:$B$500,0)),"Vehiculos en Leasing") -> Vehiculos en Leasing | C36: =IFERROR(INDEX(Cuentas!$D$8:$D$500,MATCH($B$4&"|"&A36,Cuentas!$A$8:$A$500&"|"&Cuentas!$B$8:$B$500,0)),"ACTIVO") -> ACTIVO | D36: =IF(OR(C36="ACTIVO",C36="PERDIDA"),"Deudor","Acreedor") -> Deudor | E36: =SUMPRODUCT(('Libro Diario'!$A$10:$A$5000=$B$4)*('Libro Diario'!$E$10:$E$5000=A36)*(YEAR('Libro Diario'!$C$10:$C$5000)=$E$4)*('Libro Diario'!$H$10:$H$5000)) -> 0 | F36: =SUMPRODUCT(('Libro Diario'!$A$10:$A$5000=$B$4)*('Libro Diario'!$E$10:$E$5000=A36)*(YEAR('Libro Diario'!$C$10:$C$5000)=$E$4)*('Libro Diario'!$I$10:$I$5000)) -> 0 | G36: =IF(E36>F36,E36-F36,"") | H36: =IF(F36>E36,F36-E36,"") | I36: =IF(OR(C36="ACTIVO",C36="PERDIDA"),E36-F36,F36-E36) -> 0
A37: 1201010 | B37: =IFERROR(INDEX(Cuentas!$C$8:$C$500,MATCH($B$4&"|"&A37,Cuentas!$A$8:$A$500&"|"&Cuentas!$B$8:$B$500,0)),"Dif.Valor Comercial Vehiculos") -> Dif.Valor Comercial Vehiculos | C37: =IFERROR(INDEX(Cuentas!$D$8:$D$500,MATCH($B$4&"|"&A37,Cuentas!$A$8:$A$500&"|"&Cuentas!$B$8:$B$500,0)),"ACTIVO") -> ACTIVO | D37: =IF(OR(C37="ACTIVO",C37="PERDIDA"),"Deudor","Acreedor") -> Deudor | E37: =SUMPRODUCT(('Libro Diario'!$A$10:$A$5000=$B$4)*('Libro Diario'!$E$10:$E$5000=A37)*(YEAR('Libro Diario'!$C$10:$C$5000)=$E$4)*('Libro Diario'!$H$10:$H$5000)) -> 0 | F37: =SUMPRODUCT(('Libro Diario'!$A$10:$A$5000=$B$4)*('Libro Diario'!$E$10:$E$5000=A37)*(YEAR('Libro Diario'!$C$10:$C$5000)=$E$4)*('Libro Diario'!$I$10:$I$5000)) -> 0 | G37: =IF(E37>F37,E37-F37,"") | H37: =IF(F37>E37,F37-E37,"") | I37: =IF(OR(C37="ACTIVO",C37="PERDIDA"),E37-F37,F37-E37) -> 0
A38: 1202001 | B38: =IFERROR(INDEX(Cuentas!$C$8:$C$500,MATCH($B$4&"|"&A38,Cuentas!$A$8:$A$500&"|"&Cuentas!$B$8:$B$500,0)),"Gruas") -> Gruas | C38: =IFERROR(INDEX(Cuentas!$D$8:$D$500,MATCH($B$4&"|"&A38,Cuentas!$A$8:$A$500&"|"&Cuentas!$B$8:$B$500,0)),"ACTIVO") -> ACTIVO | D38: =IF(OR(C38="ACTIVO",C38="PERDIDA"),"Deudor","Acreedor") -> Deudor | E38: =SUMPRODUCT(('Libro Diario'!$A$10:$A$5000=$B$4)*('Libro Diario'!$E$10:$E$5000=A38)*(YEAR('Libro Diario'!$C$10:$C$5000)=$E$4)*('Libro Diario'!$H$10:$H$5000)) -> 0 | F38: =SUMPRODUCT(('Libro Diario'!$A$10:$A$5000=$B$4)*('Libro Diario'!$E$10:$E$5000=A38)*(YEAR('Libro Diario'!$C$10:$C$5000)=$E$4)*('Libro Diario'!$I$10:$I$5000)) -> 0 | G38: =IF(E38>F38,E38-F38,"") | H38: =IF(F38>E38,F38-E38,"") | I38: =IF(OR(C38="ACTIVO",C38="PERDIDA"),E38-F38,F38-E38) -> 0
A39: 1202003 | B39: =IFERROR(INDEX(Cuentas!$C$8:$C$500,MATCH($B$4&"|"&A39,Cuentas!$A$8:$A$500&"|"&Cuentas!$B$8:$B$500,0)),"Tractores") -> Tractores | C39: =IFERROR(INDEX(Cuentas!$D$8:$D$500,MATCH($B$4&"|"&A39,Cuentas!$A$8:$A$500&"|"&Cuentas!$B$8:$B$500,0)),"ACTIVO") -> ACTIVO | D39: =IF(OR(C39="ACTIVO",C39="PERDIDA"),"Deudor","Acreedor") -> Deudor | E39: =SUMPRODUCT(('Libro Diario'!$A$10:$A$5000=$B$4)*('Libro Diario'!$E$10:$E$5000=A39)*(YEAR('Libro Diario'!$C$10:$C$5000)=$E$4)*('Libro Diario'!$H$10:$H$5000)) -> 0 | F39: =SUMPRODUCT(('Libro Diario'!$A$10:$A$5000=$B$4)*('Libro Diario'!$E$10:$E$5000=A39)*(YEAR('Libro Diario'!$C$10:$C$5000)=$E$4)*('Libro Diario'!$I$10:$I$5000)) -> 0 | G39: =IF(E39>F39,E39-F39,"") | H39: =IF(F39>E39,F39-E39,"") | I39: =IF(OR(C39="ACTIVO",C39="PERDIDA"),E39-F39,F39-E39) -> 0
A40: 1202004 | B40: =IFERROR(INDEX(Cuentas!$C$8:$C$500,MATCH($B$4&"|"&A40,Cuentas!$A$8:$A$500&"|"&Cuentas!$B$8:$B$500,0)),"Maquinas y equipos") -> Maquinas y equipos | C40: =IFERROR(INDEX(Cuentas!$D$8:$D$500,MATCH($B$4&"|"&A40,Cuentas!$A$8:$A$500&"|"&Cuentas!$B$8:$B$500,0)),"ACTIVO") -> ACTIVO | D40: =IF(OR(C40="ACTIVO",C40="PERDIDA"),"Deudor","Acreedor") -> Deudor | E40: =SUMPRODUCT(('Libro Diario'!$A$10:$A$5000=$B$4)*('Libro Diario'!$E$10:$E$5000=A40)*(YEAR('Libro Diario'!$C$10:$C$5000)=$E$4)*('Libro Diario'!$H$10:$H$5000)) -> 0 | F40: =SUMPRODUCT(('Libro Diario'!$A$10:$A$5000=$B$4)*('Libro Diario'!$E$10:$E$5000=A40)*(YEAR('Libro Diario'!$C$10:$C$5000)=$E$4)*('Libro Diario'!$I$10:$I$5000)) -> 0 | G40: =IF(E40>F40,E40-F40,"") | H40: =IF(F40>E40,F40-E40,"") | I40: =IF(OR(C40="ACTIVO",C40="PERDIDA"),E40-F40,F40-E40) -> 0
A41: 1202005 | B41: =IFERROR(INDEX(Cuentas!$C$8:$C$500,MATCH($B$4&"|"&A41,Cuentas!$A$8:$A$500&"|"&Cuentas!$B$8:$B$500,0)),"Equipos Computacionales y relacionados") -> Equipos Computacionales y relacionados | C41: =IFERROR(INDEX(Cuentas!$D$8:$D$500,MATCH($B$4&"|"&A41,Cuentas!$A$8:$A$500&"|"&Cuentas!$B$8:$B$500,0)),"ACTIVO") -> ACTIVO | D41: =IF(OR(C41="ACTIVO",C41="PERDIDA"),"Deudor","Acreedor") -> Deudor | E41: =SUMPRODUCT(('Libro Diario'!$A$10:$A$5000=$B$4)*('Libro Diario'!$E$10:$E$5000=A41)*(YEAR('Libro Diario'!$C$10:$C$5000)=$E$4)*('Libro Diario'!$H$10:$H$5000)) -> 0 | F41: =SUMPRODUCT(('Libro Diario'!$A$10:$A$5000=$B$4)*('Libro Diario'!$E$10:$E$5000=A41)*(YEAR('Libro Diario'!$C$10:$C$5000)=$E$4)*('Libro Diario'!$I$10:$I$5000)) -> 0 | G41: =IF(E41>F41,E41-F41,"") | H41: =IF(F41>E41,F41-E41,"") | I41: =IF(OR(C41="ACTIVO",C41="PERDIDA"),E41-F41,F41-E41) -> 0
A42: 1202006 | B42: =IFERROR(INDEX(Cuentas!$C$8:$C$500,MATCH($B$4&"|"&A42,Cuentas!$A$8:$A$500&"|"&Cuentas!$B$8:$B$500,0)),"Dep.Acum.Maquinas y Equipos") -> Dep.Acum.Maquinas y Equipos | C42: =IFERROR(INDEX(Cuentas!$D$8:$D$500,MATCH($B$4&"|"&A42,Cuentas!$A$8:$A$500&"|"&Cuentas!$B$8:$B$500,0)),"PASIVO") -> PASIVO | D42: =IF(OR(C42="ACTIVO",C42="PERDIDA"),"Deudor","Acreedor") -> Acreedor | E42: =SUMPRODUCT(('Libro Diario'!$A$10:$A$5000=$B$4)*('Libro Diario'!$E$10:$E$5000=A42)*(YEAR('Libro Diario'!$C$10:$C$5000)=$E$4)*('Libro Diario'!$H$10:$H$5000)) -> 0 | F42: =SUMPRODUCT(('Libro Diario'!$A$10:$A$5000=$B$4)*('Libro Diario'!$E$10:$E$5000=A42)*(YEAR('Libro Diario'!$C$10:$C$5000)=$E$4)*('Libro Diario'!$I$10:$I$5000)) -> 0 | G42: =IF(E42>F42,E42-F42,"") | H42: =IF(F42>E42,F42-E42,"") | I42: =IF(OR(C42="ACTIVO",C42="PERDIDA"),E42-F42,F42-E42) -> 0
A43: 1202007 | B43: =IFERROR(INDEX(Cuentas!$C$8:$C$500,MATCH($B$4&"|"&A43,Cuentas!$A$8:$A$500&"|"&Cuentas!$B$8:$B$500,0)),"Maquinarias y Equipos en Leasing") -> Maquinarias y Equipos en Leasing | C43: =IFERROR(INDEX(Cuentas!$D$8:$D$500,MATCH($B$4&"|"&A43,Cuentas!$A$8:$A$500&"|"&Cuentas!$B$8:$B$500,0)),"ACTIVO") -> ACTIVO | D43: =IF(OR(C43="ACTIVO",C43="PERDIDA"),"Deudor","Acreedor") -> Deudor | E43: =SUMPRODUCT(('Libro Diario'!$A$10:$A$5000=$B$4)*('Libro Diario'!$E$10:$E$5000=A43)*(YEAR('Libro Diario'!$C$10:$C$5000)=$E$4)*('Libro Diario'!$H$10:$H$5000)) -> 0 | F43: =SUMPRODUCT(('Libro Diario'!$A$10:$A$5000=$B$4)*('Libro Diario'!$E$10:$E$5000=A43)*(YEAR('Libro Diario'!$C$10:$C$5000)=$E$4)*('Libro Diario'!$I$10:$I$5000)) -> 0 | G43: =IF(E43>F43,E43-F43,"") | H43: =IF(F43>E43,F43-E43,"") | I43: =IF(OR(C43="ACTIVO",C43="PERDIDA"),E43-F43,F43-E43) -> 0
A44: 1203001 | B44: =IFERROR(INDEX(Cuentas!$C$8:$C$500,MATCH($B$4&"|"&A44,Cuentas!$A$8:$A$500&"|"&Cuentas!$B$8:$B$500,0)),"Terrenos") -> Terrenos | C44: =IFERROR(INDEX(Cuentas!$D$8:$D$500,MATCH($B$4&"|"&A44,Cuentas!$A$8:$A$500&"|"&Cuentas!$B$8:$B$500,0)),"ACTIVO") -> ACTIVO | D44: =IF(OR(C44="ACTIVO",C44="PERDIDA"),"Deudor","Acreedor") -> Deudor | E44: =SUMPRODUCT(('Libro Diario'!$A$10:$A$5000=$B$4)*('Libro Diario'!$E$10:$E$5000=A44)*(YEAR('Libro Diario'!$C$10:$C$5000)=$E$4)*('Libro Diario'!$H$10:$H$5000)) -> 0 | F44: =SUMPRODUCT(('Libro Diario'!$A$10:$A$5000=$B$4)*('Libro Diario'!$E$10:$E$5000=A44)*(YEAR('Libro Diario'!$C$10:$C$5000)=$E$4)*('Libro Diario'!$I$10:$I$5000)) -> 0 | G44: =IF(E44>F44,E44-F44,"") | H44: =IF(F44>E44,F44-E44,"") | I44: =IF(OR(C44="ACTIVO",C44="PERDIDA"),E44-F44,F44-E44) -> 0
A45: 1203002 | B45: =IFERROR(INDEX(Cuentas!$C$8:$C$500,MATCH($B$4&"|"&A45,Cuentas!$A$8:$A$500&"|"&Cuentas!$B$8:$B$500,0)),"Construcciones") -> Construcciones | C45: =IFERROR(INDEX(Cuentas!$D$8:$D$500,MATCH($B$4&"|"&A45,Cuentas!$A$8:$A$500&"|"&Cuentas!$B$8:$B$500,0)),"ACTIVO") -> ACTIVO | D45: =IF(OR(C45="ACTIVO",C45="PERDIDA"),"Deudor","Acreedor") -> Deudor | E45: =SUMPRODUCT(('Libro Diario'!$A$10:$A$5000=$B$4)*('Libro Diario'!$E$10:$E$5000=A45)*(YEAR('Libro Diario'!$C$10:$C$5000)=$E$4)*('Libro Diario'!$H$10:$H$5000)) -> 0 | F45: =SUMPRODUCT(('Libro Diario'!$A$10:$A$5000=$B$4)*('Libro Diario'!$E$10:$E$5000=A45)*(YEAR('Libro Diario'!$C$10:$C$5000)=$E$4)*('Libro Diario'!$I$10:$I$5000)) -> 0 | G45: =IF(E45>F45,E45-F45,"") | H45: =IF(F45>E45,F45-E45,"") | I45: =IF(OR(C45="ACTIVO",C45="PERDIDA"),E45-F45,F45-E45) -> 0
A46: 1203003 | B46: =IFERROR(INDEX(Cuentas!$C$8:$C$500,MATCH($B$4&"|"&A46,Cuentas!$A$8:$A$500&"|"&Cuentas!$B$8:$B$500,0)),"Dep. Acum. Construcciones") -> Dep. Acum. Construcciones | C46: =IFERROR(INDEX(Cuentas!$D$8:$D$500,MATCH($B$4&"|"&A46,Cuentas!$A$8:$A$500&"|"&Cuentas!$B$8:$B$500,0)),"PASIVO") -> PASIVO | D46: =IF(OR(C46="ACTIVO",C46="PERDIDA"),"Deudor","Acreedor") -> Acreedor | E46: =SUMPRODUCT(('Libro Diario'!$A$10:$A$5000=$B$4)*('Libro Diario'!$E$10:$E$5000=A46)*(YEAR('Libro Diario'!$C$10:$C$5000)=$E$4)*('Libro Diario'!$H$10:$H$5000)) -> 0 | F46: =SUMPRODUCT(('Libro Diario'!$A$10:$A$5000=$B$4)*('Libro Diario'!$E$10:$E$5000=A46)*(YEAR('Libro Diario'!$C$10:$C$5000)=$E$4)*('Libro Diario'!$I$10:$I$5000)) -> 0 | G46: =IF(E46>F46,E46-F46,"") | H46: =IF(F46>E46,F46-E46,"") | I46: =IF(OR(C46="ACTIVO",C46="PERDIDA"),E46-F46,F46-E46) -> 0
A47: 1204001 | B47: =IFERROR(INDEX(Cuentas!$C$8:$C$500,MATCH($B$4&"|"&A47,Cuentas!$A$8:$A$500&"|"&Cuentas!$B$8:$B$500,0)),"Muebles , Utiles e Instalaciones") -> Muebles , Utiles e Instalaciones | C47: =IFERROR(INDEX(Cuentas!$D$8:$D$500,MATCH($B$4&"|"&A47,Cuentas!$A$8:$A$500&"|"&Cuentas!$B$8:$B$500,0)),"ACTIVO") -> ACTIVO | D47: =IF(OR(C47="ACTIVO",C47="PERDIDA"),"Deudor","Acreedor") -> Deudor | E47: =SUMPRODUCT(('Libro Diario'!$A$10:$A$5000=$B$4)*('Libro Diario'!$E$10:$E$5000=A47)*(YEAR('Libro Diario'!$C$10:$C$5000)=$E$4)*('Libro Diario'!$H$10:$H$5000)) -> 0 | F47: =SUMPRODUCT(('Libro Diario'!$A$10:$A$5000=$B$4)*('Libro Diario'!$E$10:$E$5000=A47)*(YEAR('Libro Diario'!$C$10:$C$5000)=$E$4)*('Libro Diario'!$I$10:$I$5000)) -> 0 | G47: =IF(E47>F47,E47-F47,"") | H47: =IF(F47>E47,F47-E47,"") | I47: =IF(OR(C47="ACTIVO",C47="PERDIDA"),E47-F47,F47-E47) -> 0
A48: 1204009 | B48: =IFERROR(INDEX(Cuentas!$C$8:$C$500,MATCH($B$4&"|"&A48,Cuentas!$A$8:$A$500&"|"&Cuentas!$B$8:$B$500,0)),"Dep. Acum. Muebles, Útiles e Instalaciones") -> Dep. Acum. Muebles, Útiles e Instalaciones | C48: =IFERROR(INDEX(Cuentas!$D$8:$D$500,MATCH($B$4&"|"&A48,Cuentas!$A$8:$A$500&"|"&Cuentas!$B$8:$B$500,0)),"PASIVO") -> PASIVO | D48: =IF(OR(C48="ACTIVO",C48="PERDIDA"),"Deudor","Acreedor") -> Acreedor | E48: =SUMPRODUCT(('Libro Diario'!$A$10:$A$5000=$B$4)*('Libro Diario'!$E$10:$E$5000=A48)*(YEAR('Libro Diario'!$C$10:$C$5000)=$E$4)*('Libro Diario'!$H$10:$H$5000)) -> 0 | F48: =SUMPRODUCT(('Libro Diario'!$A$10:$A$5000=$B$4)*('Libro Diario'!$E$10:$E$5000=A48)*(YEAR('Libro Diario'!$C$10:$C$5000)=$E$4)*('Libro Diario'!$I$10:$I$5000)) -> 0 | G48: =IF(E48>F48,E48-F48,"") | H48: =IF(F48>E48,F48-E48,"") | I48: =IF(OR(C48="ACTIVO",C48="PERDIDA"),E48-F48,F48-E48) -> 0
A49: 1205001 | B49: =IFERROR(INDEX(Cuentas!$C$8:$C$500,MATCH($B$4&"|"&A49,Cuentas!$A$8:$A$500&"|"&Cuentas!$B$8:$B$500,0)),"Repuestos e Insumos") -> Repuestos e Insumos | C49: =IFERROR(INDEX(Cuentas!$D$8:$D$500,MATCH($B$4&"|"&A49,Cuentas!$A$8:$A$500&"|"&Cuentas!$B$8:$B$500,0)),"ACTIVO") -> ACTIVO | D49: =IF(OR(C49="ACTIVO",C49="PERDIDA"),"Deudor","Acreedor") -> Deudor | E49: =SUMPRODUCT(('Libro Diario'!$A$10:$A$5000=$B$4)*('Libro Diario'!$E$10:$E$5000=A49)*(YEAR('Libro Diario'!$C$10:$C$5000)=$E$4)*('Libro Diario'!$H$10:$H$5000)) -> 0 | F49: =SUMPRODUCT(('Libro Diario'!$A$10:$A$5000=$B$4)*('Libro Diario'!$E$10:$E$5000=A49)*(YEAR('Libro Diario'!$C$10:$C$5000)=$E$4)*('Libro Diario'!$I$10:$I$5000)) -> 0 | G49: =IF(E49>F49,E49-F49,"") | H49: =IF(F49>E49,F49-E49,"") | I49: =IF(OR(C49="ACTIVO",C49="PERDIDA"),E49-F49,F49-E49) -> 0
A50: 1301001 | B50: =IFERROR(INDEX(Cuentas!$C$8:$C$500,MATCH($B$4&"|"&A50,Cuentas!$A$8:$A$500&"|"&Cuentas!$B$8:$B$500,0)),"Intereses Diferidos Largo Plazo") -> Intereses Diferidos Largo Plazo | C50: =IFERROR(INDEX(Cuentas!$D$8:$D$500,MATCH($B$4&"|"&A50,Cuentas!$A$8:$A$500&"|"&Cuentas!$B$8:$B$500,0)),"ACTIVO") -> ACTIVO | D50: =IF(OR(C50="ACTIVO",C50="PERDIDA"),"Deudor","Acreedor") -> Deudor | E50: =SUMPRODUCT(('Libro Diario'!$A$10:$A$5000=$B$4)*('Libro Diario'!$E$10:$E$5000=A50)*(YEAR('Libro Diario'!$C$10:$C$5000)=$E$4)*('Libro Diario'!$H$10:$H$5000)) -> 0 | F50: =SUMPRODUCT(('Libro Diario'!$A$10:$A$5000=$B$4)*('Libro Diario'!$E$10:$E$5000=A50)*(YEAR('Libro Diario'!$C$10:$C$5000)=$E$4)*('Libro Diario'!$I$10:$I$5000)) -> 0 | G50: =IF(E50>F50,E50-F50,"") | H50: =IF(F50>E50,F50-E50,"") | I50: =IF(OR(C50="ACTIVO",C50="PERDIDA"),E50-F50,F50-E50) -> 0
A51: 1303001 | B51: =IFERROR(INDEX(Cuentas!$C$8:$C$500,MATCH($B$4&"|"&A51,Cuentas!$A$8:$A$500&"|"&Cuentas!$B$8:$B$500,0)),"Derechos Soc. Forestal Los Cipreces Ltda.") -> Derechos Soc. Forestal Los Cipreces Ltda. | C51: =IFERROR(INDEX(Cuentas!$D$8:$D$500,MATCH($B$4&"|"&A51,Cuentas!$A$8:$A$500&"|"&Cuentas!$B$8:$B$500,0)),"ACTIVO") -> ACTIVO | D51: =IF(OR(C51="ACTIVO",C51="PERDIDA"),"Deudor","Acreedor") -> Deudor | E51: =SUMPRODUCT(('Libro Diario'!$A$10:$A$5000=$B$4)*('Libro Diario'!$E$10:$E$5000=A51)*(YEAR('Libro Diario'!$C$10:$C$5000)=$E$4)*('Libro Diario'!$H$10:$H$5000)) -> 0 | F51: =SUMPRODUCT(('Libro Diario'!$A$10:$A$5000=$B$4)*('Libro Diario'!$E$10:$E$5000=A51)*(YEAR('Libro Diario'!$C$10:$C$5000)=$E$4)*('Libro Diario'!$I$10:$I$5000)) -> 0 | G51: =IF(E51>F51,E51-F51,"") | H51: =IF(F51>E51,F51-E51,"") | I51: =IF(OR(C51="ACTIVO",C51="PERDIDA"),E51-F51,F51-E51) -> 0
A52: 2102001 | B52: =IFERROR(INDEX(Cuentas!$C$8:$C$500,MATCH($B$4&"|"&A52,Cuentas!$A$8:$A$500&"|"&Cuentas!$B$8:$B$500,0)),"Proveedores") -> Proveedores | C52: =IFERROR(INDEX(Cuentas!$D$8:$D$500,MATCH($B$4&"|"&A52,Cuentas!$A$8:$A$500&"|"&Cuentas!$B$8:$B$500,0)),"PASIVO") -> PASIVO | D52: =IF(OR(C52="ACTIVO",C52="PERDIDA"),"Deudor","Acreedor") -> Acreedor | E52: =SUMPRODUCT(('Libro Diario'!$A$10:$A$5000=$B$4)*('Libro Diario'!$E$10:$E$5000=A52)*(YEAR('Libro Diario'!$C$10:$C$5000)=$E$4)*('Libro Diario'!$H$10:$H$5000)) -> 0 | F52: =SUMPRODUCT(('Libro Diario'!$A$10:$A$5000=$B$4)*('Libro Diario'!$E$10:$E$5000=A52)*(YEAR('Libro Diario'!$C$10:$C$5000)=$E$4)*('Libro Diario'!$I$10:$I$5000)) -> 0 | G52: =IF(E52>F52,E52-F52,"") | H52: =IF(F52>E52,F52-E52,"") | I52: =IF(OR(C52="ACTIVO",C52="PERDIDA"),E52-F52,F52-E52) -> 0
A53: 2103001 | B53: =IFERROR(INDEX(Cuentas!$C$8:$C$500,MATCH($B$4&"|"&A53,Cuentas!$A$8:$A$500&"|"&Cuentas!$B$8:$B$500,0)),"Documentos por Pagar-Vehiculos") -> Documentos por Pagar-Vehiculos | C53: =IFERROR(INDEX(Cuentas!$D$8:$D$500,MATCH($B$4&"|"&A53,Cuentas!$A$8:$A$500&"|"&Cuentas!$B$8:$B$500,0)),"PASIVO") -> PASIVO | D53: =IF(OR(C53="ACTIVO",C53="PERDIDA"),"Deudor","Acreedor") -> Acreedor | E53: =SUMPRODUCT(('Libro Diario'!$A$10:$A$5000=$B$4)*('Libro Diario'!$E$10:$E$5000=A53)*(YEAR('Libro Diario'!$C$10:$C$5000)=$E$4)*('Libro Diario'!$H$10:$H$5000)) -> 0 | F53: =SUMPRODUCT(('Libro Diario'!$A$10:$A$5000=$B$4)*('Libro Diario'!$E$10:$E$5000=A53)*(YEAR('Libro Diario'!$C$10:$C$5000)=$E$4)*('Libro Diario'!$I$10:$I$5000)) -> 0 | G53: =IF(E53>F53,E53-F53,"") | H53: =IF(F53>E53,F53-E53,"") | I53: =IF(OR(C53="ACTIVO",C53="PERDIDA"),E53-F53,F53-E53) -> 0
A54: 2104001 | B54: =IFERROR(INDEX(Cuentas!$C$8:$C$500,MATCH($B$4&"|"&A54,Cuentas!$A$8:$A$500&"|"&Cuentas!$B$8:$B$500,0)),"Acreedores Varios") -> Provisión Vacaciones | C54: =IFERROR(INDEX(Cuentas!$D$8:$D$500,MATCH($B$4&"|"&A54,Cuentas!$A$8:$A$500&"|"&Cuentas!$B$8:$B$500,0)),"PASIVO") -> PASIVO | D54: =IF(OR(C54="ACTIVO",C54="PERDIDA"),"Deudor","Acreedor") -> Acreedor | E54: =SUMPRODUCT(('Libro Diario'!$A$10:$A$5000=$B$4)*('Libro Diario'!$E$10:$E$5000=A54)*(YEAR('Libro Diario'!$C$10:$C$5000)=$E$4)*('Libro Diario'!$H$10:$H$5000)) -> 0 | F54: =SUMPRODUCT(('Libro Diario'!$A$10:$A$5000=$B$4)*('Libro Diario'!$E$10:$E$5000=A54)*(YEAR('Libro Diario'!$C$10:$C$5000)=$E$4)*('Libro Diario'!$I$10:$I$5000)) -> 0 | G54: =IF(E54>F54,E54-F54,"") | H54: =IF(F54>E54,F54-E54,"") | I54: =IF(OR(C54="ACTIVO",C54="PERDIDA"),E54-F54,F54-E54) -> 0
A55: 2104003 | B55: =IFERROR(INDEX(Cuentas!$C$8:$C$500,MATCH($B$4&"|"&A55,Cuentas!$A$8:$A$500&"|"&Cuentas!$B$8:$B$500,0)),"Doctos. Por Pagar") -> Doctos. Por Pagar | C55: =IFERROR(INDEX(Cuentas!$D$8:$D$500,MATCH($B$4&"|"&A55,Cuentas!$A$8:$A$500&"|"&Cuentas!$B$8:$B$500,0)),"PASIVO") -> PASIVO | D55: =IF(OR(C55="ACTIVO",C55="PERDIDA"),"Deudor","Acreedor") -> Acreedor | E55: =SUMPRODUCT(('Libro Diario'!$A$10:$A$5000=$B$4)*('Libro Diario'!$E$10:$E$5000=A55)*(YEAR('Libro Diario'!$C$10:$C$5000)=$E$4)*('Libro Diario'!$H$10:$H$5000)) -> 0 | F55: =SUMPRODUCT(('Libro Diario'!$A$10:$A$5000=$B$4)*('Libro Diario'!$E$10:$E$5000=A55)*(YEAR('Libro Diario'!$C$10:$C$5000)=$E$4)*('Libro Diario'!$I$10:$I$5000)) -> 0 | G55: =IF(E55>F55,E55-F55,"") | H55: =IF(F55>E55,F55-E55,"") | I55: =IF(OR(C55="ACTIVO",C55="PERDIDA"),E55-F55,F55-E55) -> 0
A56: 2105003 | B56: =IFERROR(INDEX(Cuentas!$C$8:$C$500,MATCH($B$4&"|"&A56,Cuentas!$A$8:$A$500&"|"&Cuentas!$B$8:$B$500,0)),"Impuesto Único a los trabajadores") -> Impuesto Único a los trabajadores | C56: =IFERROR(INDEX(Cuentas!$D$8:$D$500,MATCH($B$4&"|"&A56,Cuentas!$A$8:$A$500&"|"&Cuentas!$B$8:$B$500,0)),"PASIVO") -> PASIVO | D56: =IF(OR(C56="ACTIVO",C56="PERDIDA"),"Deudor","Acreedor") -> Acreedor | E56: =SUMPRODUCT(('Libro Diario'!$A$10:$A$5000=$B$4)*('Libro Diario'!$E$10:$E$5000=A56)*(YEAR('Libro Diario'!$C$10:$C$5000)=$E$4)*('Libro Diario'!$H$10:$H$5000)) -> 0 | F56: =SUMPRODUCT(('Libro Diario'!$A$10:$A$5000=$B$4)*('Libro Diario'!$E$10:$E$5000=A56)*(YEAR('Libro Diario'!$C$10:$C$5000)=$E$4)*('Libro Diario'!$I$10:$I$5000)) -> 0 | G56: =IF(E56>F56,E56-F56,"") | H56: =IF(F56>E56,F56-E56,"") | I56: =IF(OR(C56="ACTIVO",C56="PERDIDA"),E56-F56,F56-E56) -> 0
A57: 2105004 | B57: =IFERROR(INDEX(Cuentas!$C$8:$C$500,MATCH($B$4&"|"&A57,Cuentas!$A$8:$A$500&"|"&Cuentas!$B$8:$B$500,0)),"PPM por Pagar") -> PPM por Pagar | C57: =IFERROR(INDEX(Cuentas!$D$8:$D$500,MATCH($B$4&"|"&A57,Cuentas!$A$8:$A$500&"|"&Cuentas!$B$8:$B$500,0)),"PASIVO") -> PASIVO | D57: =IF(OR(C57="ACTIVO",C57="PERDIDA"),"Deudor","Acreedor") -> Acreedor | E57: =SUMPRODUCT(('Libro Diario'!$A$10:$A$5000=$B$4)*('Libro Diario'!$E$10:$E$5000=A57)*(YEAR('Libro Diario'!$C$10:$C$5000)=$E$4)*('Libro Diario'!$H$10:$H$5000)) -> 0 | F57: =SUMPRODUCT(('Libro Diario'!$A$10:$A$5000=$B$4)*('Libro Diario'!$E$10:$E$5000=A57)*(YEAR('Libro Diario'!$C$10:$C$5000)=$E$4)*('Libro Diario'!$I$10:$I$5000)) -> 0 | G57: =IF(E57>F57,E57-F57,"") | H57: =IF(F57>E57,F57-E57,"") | I57: =IF(OR(C57="ACTIVO",C57="PERDIDA"),E57-F57,F57-E57) -> 0
A58: 2105005 | B58: =IFERROR(INDEX(Cuentas!$C$8:$C$500,MATCH($B$4&"|"&A58,Cuentas!$A$8:$A$500&"|"&Cuentas!$B$8:$B$500,0)),"Provision Impto. Renta") -> Provision Impto. Renta | C58: =IFERROR(INDEX(Cuentas!$D$8:$D$500,MATCH($B$4&"|"&A58,Cuentas!$A$8:$A$500&"|"&Cuentas!$B$8:$B$500,0)),"PASIVO") -> PASIVO | D58: =IF(OR(C58="ACTIVO",C58="PERDIDA"),"Deudor","Acreedor") -> Acreedor | E58: =SUMPRODUCT(('Libro Diario'!$A$10:$A$5000=$B$4)*('Libro Diario'!$E$10:$E$5000=A58)*(YEAR('Libro Diario'!$C$10:$C$5000)=$E$4)*('Libro Diario'!$H$10:$H$5000)) -> 0 | F58: =SUMPRODUCT(('Libro Diario'!$A$10:$A$5000=$B$4)*('Libro Diario'!$E$10:$E$5000=A58)*(YEAR('Libro Diario'!$C$10:$C$5000)=$E$4)*('Libro Diario'!$I$10:$I$5000)) -> 0 | G58: =IF(E58>F58,E58-F58,"") | H58: =IF(F58>E58,F58-E58,"") | I58: =IF(OR(C58="ACTIVO",C58="PERDIDA"),E58-F58,F58-E58) -> 0
A59: 2105006 | B59: =IFERROR(INDEX(Cuentas!$C$8:$C$500,MATCH($B$4&"|"&A59,Cuentas!$A$8:$A$500&"|"&Cuentas!$B$8:$B$500,0)),"Contribuciones por Pagar") -> Contribuciones por Pagar | C59: =IFERROR(INDEX(Cuentas!$D$8:$D$500,MATCH($B$4&"|"&A59,Cuentas!$A$8:$A$500&"|"&Cuentas!$B$8:$B$500,0)),"PASIVO") -> PASIVO | D59: =IF(OR(C59="ACTIVO",C59="PERDIDA"),"Deudor","Acreedor") -> Acreedor | E59: =SUMPRODUCT(('Libro Diario'!$A$10:$A$5000=$B$4)*('Libro Diario'!$E$10:$E$5000=A59)*(YEAR('Libro Diario'!$C$10:$C$5000)=$E$4)*('Libro Diario'!$H$10:$H$5000)) -> 0 | F59: =SUMPRODUCT(('Libro Diario'!$A$10:$A$5000=$B$4)*('Libro Diario'!$E$10:$E$5000=A59)*(YEAR('Libro Diario'!$C$10:$C$5000)=$E$4)*('Libro Diario'!$I$10:$I$5000)) -> 0 | G59: =IF(E59>F59,E59-F59,"") | H59: =IF(F59>E59,F59-E59,"") | I59: =IF(OR(C59="ACTIVO",C59="PERDIDA"),E59-F59,F59-E59) -> 0
A60: 2105101 | B60: =IFERROR(INDEX(Cuentas!$C$8:$C$500,MATCH($B$4&"|"&A60,Cuentas!$A$8:$A$500&"|"&Cuentas!$B$8:$B$500,0)),"IVA Débito Fiscal 19%") -> IVA Débito Fiscal 19% | C60: =IFERROR(INDEX(Cuentas!$D$8:$D$500,MATCH($B$4&"|"&A60,Cuentas!$A$8:$A$500&"|"&Cuentas!$B$8:$B$500,0)),"PASIVO") -> PASIVO | D60: =IF(OR(C60="ACTIVO",C60="PERDIDA"),"Deudor","Acreedor") -> Acreedor | E60: =SUMPRODUCT(('Libro Diario'!$A$10:$A$5000=$B$4)*('Libro Diario'!$E$10:$E$5000=A60)*(YEAR('Libro Diario'!$C$10:$C$5000)=$E$4)*('Libro Diario'!$H$10:$H$5000)) -> 0 | F60: =SUMPRODUCT(('Libro Diario'!$A$10:$A$5000=$B$4)*('Libro Diario'!$E$10:$E$5000=A60)*(YEAR('Libro Diario'!$C$10:$C$5000)=$E$4)*('Libro Diario'!$I$10:$I$5000)) -> 0 | G60: =IF(E60>F60,E60-F60,"") | H60: =IF(F60>E60,F60-E60,"") | I60: =IF(OR(C60="ACTIVO",C60="PERDIDA"),E60-F60,F60-E60) -> 0
A61: 2105102 | B61: =IFERROR(INDEX(Cuentas!$C$8:$C$500,MATCH($B$4&"|"&A61,Cuentas!$A$8:$A$500&"|"&Cuentas!$B$8:$B$500,0)),"IVA Debito Fiscal no Ret 11%") -> IVA Debito Fiscal no Ret 11% | C61: =IFERROR(INDEX(Cuentas!$D$8:$D$500,MATCH($B$4&"|"&A61,Cuentas!$A$8:$A$500&"|"&Cuentas!$B$8:$B$500,0)),"PASIVO") -> PASIVO | D61: =IF(OR(C61="ACTIVO",C61="PERDIDA"),"Deudor","Acreedor") -> Acreedor | E61: =SUMPRODUCT(('Libro Diario'!$A$10:$A$5000=$B$4)*('Libro Diario'!$E$10:$E$5000=A61)*(YEAR('Libro Diario'!$C$10:$C$5000)=$E$4)*('Libro Diario'!$H$10:$H$5000)) -> 0 | F61: =SUMPRODUCT(('Libro Diario'!$A$10:$A$5000=$B$4)*('Libro Diario'!$E$10:$E$5000=A61)*(YEAR('Libro Diario'!$C$10:$C$5000)=$E$4)*('Libro Diario'!$I$10:$I$5000)) -> 0 | G61: =IF(E61>F61,E61-F61,"") | H61: =IF(F61>E61,F61-E61,"") | I61: =IF(OR(C61="ACTIVO",C61="PERDIDA"),E61-F61,F61-E61) -> 0
A62: 2105201 | B62: =IFERROR(INDEX(Cuentas!$C$8:$C$500,MATCH($B$4&"|"&A62,Cuentas!$A$8:$A$500&"|"&Cuentas!$B$8:$B$500,0)),"Retencion 2ª Categoria (10 %)") -> Retencion 2ª Categoria (10 %) | C62: =IFERROR(INDEX(Cuentas!$D$8:$D$500,MATCH($B$4&"|"&A62,Cuentas!$A$8:$A$500&"|"&Cuentas!$B$8:$B$500,0)),"PASIVO") -> PASIVO | D62: =IF(OR(C62="ACTIVO",C62="PERDIDA"),"Deudor","Acreedor") -> Acreedor | E62: =SUMPRODUCT(('Libro Diario'!$A$10:$A$5000=$B$4)*('Libro Diario'!$E$10:$E$5000=A62)*(YEAR('Libro Diario'!$C$10:$C$5000)=$E$4)*('Libro Diario'!$H$10:$H$5000)) -> 0 | F62: =SUMPRODUCT(('Libro Diario'!$A$10:$A$5000=$B$4)*('Libro Diario'!$E$10:$E$5000=A62)*(YEAR('Libro Diario'!$C$10:$C$5000)=$E$4)*('Libro Diario'!$I$10:$I$5000)) -> 0 | G62: =IF(E62>F62,E62-F62,"") | H62: =IF(F62>E62,F62-E62,"") | I62: =IF(OR(C62="ACTIVO",C62="PERDIDA"),E62-F62,F62-E62) -> 0
A63: 2105401 | B63: =IFERROR(INDEX(Cuentas!$C$8:$C$500,MATCH($B$4&"|"&A63,Cuentas!$A$8:$A$500&"|"&Cuentas!$B$8:$B$500,0)),"IVA Compras Retenido a Terceros") -> IVA Compras Retenido a Terceros | C63: =IFERROR(INDEX(Cuentas!$D$8:$D$500,MATCH($B$4&"|"&A63,Cuentas!$A$8:$A$500&"|"&Cuentas!$B$8:$B$500,0)),"PASIVO") -> PASIVO | D63: =IF(OR(C63="ACTIVO",C63="PERDIDA"),"Deudor","Acreedor") -> Acreedor | E63: =SUMPRODUCT(('Libro Diario'!$A$10:$A$5000=$B$4)*('Libro Diario'!$E$10:$E$5000=A63)*(YEAR('Libro Diario'!$C$10:$C$5000)=$E$4)*('Libro Diario'!$H$10:$H$5000)) -> 0 | F63: =SUMPRODUCT(('Libro Diario'!$A$10:$A$5000=$B$4)*('Libro Diario'!$E$10:$E$5000=A63)*(YEAR('Libro Diario'!$C$10:$C$5000)=$E$4)*('Libro Diario'!$I$10:$I$5000)) -> 0 | G63: =IF(E63>F63,E63-F63,"") | H63: =IF(F63>E63,F63-E63,"") | I63: =IF(OR(C63="ACTIVO",C63="PERDIDA"),E63-F63,F63-E63) -> 0
A64: 2106001 | B64: =IFERROR(INDEX(Cuentas!$C$8:$C$500,MATCH($B$4&"|"&A64,Cuentas!$A$8:$A$500&"|"&Cuentas!$B$8:$B$500,0)),"Sueldos por Pagar") -> Sueldos por Pagar | C64: =IFERROR(INDEX(Cuentas!$D$8:$D$500,MATCH($B$4&"|"&A64,Cuentas!$A$8:$A$500&"|"&Cuentas!$B$8:$B$500,0)),"PASIVO") -> PASIVO | D64: =IF(OR(C64="ACTIVO",C64="PERDIDA"),"Deudor","Acreedor") -> Acreedor | E64: =SUMPRODUCT(('Libro Diario'!$A$10:$A$5000=$B$4)*('Libro Diario'!$E$10:$E$5000=A64)*(YEAR('Libro Diario'!$C$10:$C$5000)=$E$4)*('Libro Diario'!$H$10:$H$5000)) -> 0 | F64: =SUMPRODUCT(('Libro Diario'!$A$10:$A$5000=$B$4)*('Libro Diario'!$E$10:$E$5000=A64)*(YEAR('Libro Diario'!$C$10:$C$5000)=$E$4)*('Libro Diario'!$I$10:$I$5000)) -> 0 | G64: =IF(E64>F64,E64-F64,"") | H64: =IF(F64>E64,F64-E64,"") | I64: =IF(OR(C64="ACTIVO",C64="PERDIDA"),E64-F64,F64-E64) -> 0
A65: 2106002 | B65: =IFERROR(INDEX(Cuentas!$C$8:$C$500,MATCH($B$4&"|"&A65,Cuentas!$A$8:$A$500&"|"&Cuentas!$B$8:$B$500,0)),"Honorarios por Pagar") -> Honorarios por Pagar | C65: =IFERROR(INDEX(Cuentas!$D$8:$D$500,MATCH($B$4&"|"&A65,Cuentas!$A$8:$A$500&"|"&Cuentas!$B$8:$B$500,0)),"PASIVO") -> PASIVO | D65: =IF(OR(C65="ACTIVO",C65="PERDIDA"),"Deudor","Acreedor") -> Acreedor | E65: =SUMPRODUCT(('Libro Diario'!$A$10:$A$5000=$B$4)*('Libro Diario'!$E$10:$E$5000=A65)*(YEAR('Libro Diario'!$C$10:$C$5000)=$E$4)*('Libro Diario'!$H$10:$H$5000)) -> 0 | F65: =SUMPRODUCT(('Libro Diario'!$A$10:$A$5000=$B$4)*('Libro Diario'!$E$10:$E$5000=A65)*(YEAR('Libro Diario'!$C$10:$C$5000)=$E$4)*('Libro Diario'!$I$10:$I$5000)) -> 0 | G65: =IF(E65>F65,E65-F65,"") | H65: =IF(F65>E65,F65-E65,"") | I65: =IF(OR(C65="ACTIVO",C65="PERDIDA"),E65-F65,F65-E65) -> 0
A66: 2107001 | B66: =IFERROR(INDEX(Cuentas!$C$8:$C$500,MATCH($B$4&"|"&A66,Cuentas!$A$8:$A$500&"|"&Cuentas!$B$8:$B$500,0)),"Instituciones de Prevision") -> Instituciones de Prevision | C66: =IFERROR(INDEX(Cuentas!$D$8:$D$500,MATCH($B$4&"|"&A66,Cuentas!$A$8:$A$500&"|"&Cuentas!$B$8:$B$500,0)),"PASIVO") -> PASIVO | D66: =IF(OR(C66="ACTIVO",C66="PERDIDA"),"Deudor","Acreedor") -> Acreedor | E66: =SUMPRODUCT(('Libro Diario'!$A$10:$A$5000=$B$4)*('Libro Diario'!$E$10:$E$5000=A66)*(YEAR('Libro Diario'!$C$10:$C$5000)=$E$4)*('Libro Diario'!$H$10:$H$5000)) -> 0 | F66: =SUMPRODUCT(('Libro Diario'!$A$10:$A$5000=$B$4)*('Libro Diario'!$E$10:$E$5000=A66)*(YEAR('Libro Diario'!$C$10:$C$5000)=$E$4)*('Libro Diario'!$I$10:$I$5000)) -> 0 | G66: =IF(E66>F66,E66-F66,"") | H66: =IF(F66>E66,F66-E66,"") | I66: =IF(OR(C66="ACTIVO",C66="PERDIDA"),E66-F66,F66-E66) -> 0
A67: 2108001 | B67: =IFERROR(INDEX(Cuentas!$C$8:$C$500,MATCH($B$4&"|"&A67,Cuentas!$A$8:$A$500&"|"&Cuentas!$B$8:$B$500,0)),"Préstamos de Socios") -> Préstamos de Socios | C67: =IFERROR(INDEX(Cuentas!$D$8:$D$500,MATCH($B$4&"|"&A67,Cuentas!$A$8:$A$500&"|"&Cuentas!$B$8:$B$500,0)),"PASIVO") -> PASIVO | D67: =IF(OR(C67="ACTIVO",C67="PERDIDA"),"Deudor","Acreedor") -> Acreedor | E67: =SUMPRODUCT(('Libro Diario'!$A$10:$A$5000=$B$4)*('Libro Diario'!$E$10:$E$5000=A67)*(YEAR('Libro Diario'!$C$10:$C$5000)=$E$4)*('Libro Diario'!$H$10:$H$5000)) -> 0 | F67: =SUMPRODUCT(('Libro Diario'!$A$10:$A$5000=$B$4)*('Libro Diario'!$E$10:$E$5000=A67)*(YEAR('Libro Diario'!$C$10:$C$5000)=$E$4)*('Libro Diario'!$I$10:$I$5000)) -> 0 | G67: =IF(E67>F67,E67-F67,"") | H67: =IF(F67>E67,F67-E67,"") | I67: =IF(OR(C67="ACTIVO",C67="PERDIDA"),E67-F67,F67-E67) -> 0
A68: 2108003 | B68: =IFERROR(INDEX(Cuentas!$C$8:$C$500,MATCH($B$4&"|"&A68,Cuentas!$A$8:$A$500&"|"&Cuentas!$B$8:$B$500,0)),"Acreedores Varios") -> Acreedores Varios | C68: =IFERROR(INDEX(Cuentas!$D$8:$D$500,MATCH($B$4&"|"&A68,Cuentas!$A$8:$A$500&"|"&Cuentas!$B$8:$B$500,0)),"PASIVO") -> PASIVO | D68: =IF(OR(C68="ACTIVO",C68="PERDIDA"),"Deudor","Acreedor") -> Acreedor | E68: =SUMPRODUCT(('Libro Diario'!$A$10:$A$5000=$B$4)*('Libro Diario'!$E$10:$E$5000=A68)*(YEAR('Libro Diario'!$C$10:$C$5000)=$E$4)*('Libro Diario'!$H$10:$H$5000)) -> 0 | F68: =SUMPRODUCT(('Libro Diario'!$A$10:$A$5000=$B$4)*('Libro Diario'!$E$10:$E$5000=A68)*(YEAR('Libro Diario'!$C$10:$C$5000)=$E$4)*('Libro Diario'!$I$10:$I$5000)) -> 0 | G68: =IF(E68>F68,E68-F68,"") | H68: =IF(F68>E68,F68-E68,"") | I68: =IF(OR(C68="ACTIVO",C68="PERDIDA"),E68-F68,F68-E68) -> 0
A69: 2201001 | B69: =IFERROR(INDEX(Cuentas!$C$8:$C$500,MATCH($B$4&"|"&A69,Cuentas!$A$8:$A$500&"|"&Cuentas!$B$8:$B$500,0)),"Prestamos Banco Largo Plazo") -> Prestamos Banco Largo Plazo | C69: =IFERROR(INDEX(Cuentas!$D$8:$D$500,MATCH($B$4&"|"&A69,Cuentas!$A$8:$A$500&"|"&Cuentas!$B$8:$B$500,0)),"PASIVO") -> PASIVO | D69: =IF(OR(C69="ACTIVO",C69="PERDIDA"),"Deudor","Acreedor") -> Acreedor | E69: =SUMPRODUCT(('Libro Diario'!$A$10:$A$5000=$B$4)*('Libro Diario'!$E$10:$E$5000=A69)*(YEAR('Libro Diario'!$C$10:$C$5000)=$E$4)*('Libro Diario'!$H$10:$H$5000)) -> 0 | F69: =SUMPRODUCT(('Libro Diario'!$A$10:$A$5000=$B$4)*('Libro Diario'!$E$10:$E$5000=A69)*(YEAR('Libro Diario'!$C$10:$C$5000)=$E$4)*('Libro Diario'!$I$10:$I$5000)) -> 0 | G69: =IF(E69>F69,E69-F69,"") | H69: =IF(F69>E69,F69-E69,"") | I69: =IF(OR(C69="ACTIVO",C69="PERDIDA"),E69-F69,F69-E69) -> 0
A70: 2201002 | B70: =IFERROR(INDEX(Cuentas!$C$8:$C$500,MATCH($B$4&"|"&A70,Cuentas!$A$8:$A$500&"|"&Cuentas!$B$8:$B$500,0)),"Acreedores Leasing Largo Plazo") -> Acreedores Leasing Largo Plazo | C70: =IFERROR(INDEX(Cuentas!$D$8:$D$500,MATCH($B$4&"|"&A70,Cuentas!$A$8:$A$500&"|"&Cuentas!$B$8:$B$500,0)),"PASIVO") -> PASIVO | D70: =IF(OR(C70="ACTIVO",C70="PERDIDA"),"Deudor","Acreedor") -> Acreedor | E70: =SUMPRODUCT(('Libro Diario'!$A$10:$A$5000=$B$4)*('Libro Diario'!$E$10:$E$5000=A70)*(YEAR('Libro Diario'!$C$10:$C$5000)=$E$4)*('Libro Diario'!$H$10:$H$5000)) -> 0 | F70: =SUMPRODUCT(('Libro Diario'!$A$10:$A$5000=$B$4)*('Libro Diario'!$E$10:$E$5000=A70)*(YEAR('Libro Diario'!$C$10:$C$5000)=$E$4)*('Libro Diario'!$I$10:$I$5000)) -> 0 | G70: =IF(E70>F70,E70-F70,"") | H70: =IF(F70>E70,F70-E70,"") | I70: =IF(OR(C70="ACTIVO",C70="PERDIDA"),E70-F70,F70-E70) -> 0
A71: 2301001 | B71: =IFERROR(INDEX(Cuentas!$C$8:$C$500,MATCH($B$4&"|"&A71,Cuentas!$A$8:$A$500&"|"&Cuentas!$B$8:$B$500,0)),"Capital") -> Capital | C71: =IFERROR(INDEX(Cuentas!$D$8:$D$500,MATCH($B$4&"|"&A71,Cuentas!$A$8:$A$500&"|"&Cuentas!$B$8:$B$500,0)),"PASIVO") -> PASIVO | D71: =IF(OR(C71="ACTIVO",C71="PERDIDA"),"Deudor","Acreedor") -> Acreedor | E71: =SUMPRODUCT(('Libro Diario'!$A$10:$A$5000=$B$4)*('Libro Diario'!$E$10:$E$5000=A71)*(YEAR('Libro Diario'!$C$10:$C$5000)=$E$4)*('Libro Diario'!$H$10:$H$5000)) -> 0 | F71: =SUMPRODUCT(('Libro Diario'!$A$10:$A$5000=$B$4)*('Libro Diario'!$E$10:$E$5000=A71)*(YEAR('Libro Diario'!$C$10:$C$5000)=$E$4)*('Libro Diario'!$I$10:$I$5000)) -> 0 | G71: =IF(E71>F71,E71-F71,"") | H71: =IF(F71>E71,F71-E71,"") | I71: =IF(OR(C71="ACTIVO",C71="PERDIDA"),E71-F71,F71-E71) -> 0
A72: 2302001 | B72: =IFERROR(INDEX(Cuentas!$C$8:$C$500,MATCH($B$4&"|"&A72,Cuentas!$A$8:$A$500&"|"&Cuentas!$B$8:$B$500,0)),"Revalorización Capital Propio") -> Revalorización Capital Propio | C72: =IFERROR(INDEX(Cuentas!$D$8:$D$500,MATCH($B$4&"|"&A72,Cuentas!$A$8:$A$500&"|"&Cuentas!$B$8:$B$500,0)),"PASIVO") -> PASIVO | D72: =IF(OR(C72="ACTIVO",C72="PERDIDA"),"Deudor","Acreedor") -> Acreedor | E72: =SUMPRODUCT(('Libro Diario'!$A$10:$A$5000=$B$4)*('Libro Diario'!$E$10:$E$5000=A72)*(YEAR('Libro Diario'!$C$10:$C$5000)=$E$4)*('Libro Diario'!$H$10:$H$5000)) -> 0 | F72: =SUMPRODUCT(('Libro Diario'!$A$10:$A$5000=$B$4)*('Libro Diario'!$E$10:$E$5000=A72)*(YEAR('Libro Diario'!$C$10:$C$5000)=$E$4)*('Libro Diario'!$I$10:$I$5000)) -> 0 | G72: =IF(E72>F72,E72-F72,"") | H72: =IF(F72>E72,F72-E72,"") | I72: =IF(OR(C72="ACTIVO",C72="PERDIDA"),E72-F72,F72-E72) -> 0
A73: 2302101 | B73: =IFERROR(INDEX(Cuentas!$C$8:$C$500,MATCH($B$4&"|"&A73,Cuentas!$A$8:$A$500&"|"&Cuentas!$B$8:$B$500,0)),"Resultado Ej. Anteriores") -> Resultado Ej. Anteriores | C73: =IFERROR(INDEX(Cuentas!$D$8:$D$500,MATCH($B$4&"|"&A73,Cuentas!$A$8:$A$500&"|"&Cuentas!$B$8:$B$500,0)),"PASIVO") -> PASIVO | D73: =IF(OR(C73="ACTIVO",C73="PERDIDA"),"Deudor","Acreedor") -> Acreedor | E73: =SUMPRODUCT(('Libro Diario'!$A$10:$A$5000=$B$4)*('Libro Diario'!$E$10:$E$5000=A73)*(YEAR('Libro Diario'!$C$10:$C$5000)=$E$4)*('Libro Diario'!$H$10:$H$5000)) -> 0 | F73: =SUMPRODUCT(('Libro Diario'!$A$10:$A$5000=$B$4)*('Libro Diario'!$E$10:$E$5000=A73)*(YEAR('Libro Diario'!$C$10:$C$5000)=$E$4)*('Libro Diario'!$I$10:$I$5000)) -> 0 | G73: =IF(E73>F73,E73-F73,"") | H73: =IF(F73>E73,F73-E73,"") | I73: =IF(OR(C73="ACTIVO",C73="PERDIDA"),E73-F73,F73-E73) -> 0
A74: 2302201 | B74: =IFERROR(INDEX(Cuentas!$C$8:$C$500,MATCH($B$4&"|"&A74,Cuentas!$A$8:$A$500&"|"&Cuentas!$B$8:$B$500,0)),"Resultado del Ejercicio") -> Resultado del Ejercicio | C74: =IFERROR(INDEX(Cuentas!$D$8:$D$500,MATCH($B$4&"|"&A74,Cuentas!$A$8:$A$500&"|"&Cuentas!$B$8:$B$500,0)),"PASIVO") -> PASIVO | D74: =IF(OR(C74="ACTIVO",C74="PERDIDA"),"Deudor","Acreedor") -> Acreedor | E74: =SUMPRODUCT(('Libro Diario'!$A$10:$A$5000=$B$4)*('Libro Diario'!$E$10:$E$5000=A74)*(YEAR('Libro Diario'!$C$10:$C$5000)=$E$4)*('Libro Diario'!$H$10:$H$5000)) -> 0 | F74: =SUMPRODUCT(('Libro Diario'!$A$10:$A$5000=$B$4)*('Libro Diario'!$E$10:$E$5000=A74)*(YEAR('Libro Diario'!$C$10:$C$5000)=$E$4)*('Libro Diario'!$I$10:$I$5000)) -> 0 | G74: =IF(E74>F74,E74-F74,"") | H74: =IF(F74>E74,F74-E74,"") | I74: =IF(OR(C74="ACTIVO",C74="PERDIDA"),E74-F74,F74-E74) -> 0
A75: 3101001 | B75: =IFERROR(INDEX(Cuentas!$C$8:$C$500,MATCH($B$4&"|"&A75,Cuentas!$A$8:$A$500&"|"&Cuentas!$B$8:$B$500,0)),"Costo de Ventas") -> Costo de Ventas | C75: =IFERROR(INDEX(Cuentas!$D$8:$D$500,MATCH($B$4&"|"&A75,Cuentas!$A$8:$A$500&"|"&Cuentas!$B$8:$B$500,0)),"PERDIDA") -> PERDIDA | D75: =IF(OR(C75="ACTIVO",C75="PERDIDA"),"Deudor","Acreedor") -> Deudor | E75: =SUMPRODUCT(('Libro Diario'!$A$10:$A$5000=$B$4)*('Libro Diario'!$E$10:$E$5000=A75)*(YEAR('Libro Diario'!$C$10:$C$5000)=$E$4)*('Libro Diario'!$H$10:$H$5000)) -> 0 | F75: =SUMPRODUCT(('Libro Diario'!$A$10:$A$5000=$B$4)*('Libro Diario'!$E$10:$E$5000=A75)*(YEAR('Libro Diario'!$C$10:$C$5000)=$E$4)*('Libro Diario'!$I$10:$I$5000)) -> 0 | G75: =IF(E75>F75,E75-F75,"") | H75: =IF(F75>E75,F75-E75,"") | I75: =IF(OR(C75="ACTIVO",C75="PERDIDA"),E75-F75,F75-E75) -> 0
A76: 3101002 | B76: =IFERROR(INDEX(Cuentas!$C$8:$C$500,MATCH($B$4&"|"&A76,Cuentas!$A$8:$A$500&"|"&Cuentas!$B$8:$B$500,0)),"Gastos Administracion") -> Gastos Administracion | C76: =IFERROR(INDEX(Cuentas!$D$8:$D$500,MATCH($B$4&"|"&A76,Cuentas!$A$8:$A$500&"|"&Cuentas!$B$8:$B$500,0)),"PERDIDA") -> PERDIDA | D76: =IF(OR(C76="ACTIVO",C76="PERDIDA"),"Deudor","Acreedor") -> Deudor | E76: =SUMPRODUCT(('Libro Diario'!$A$10:$A$5000=$B$4)*('Libro Diario'!$E$10:$E$5000=A76)*(YEAR('Libro Diario'!$C$10:$C$5000)=$E$4)*('Libro Diario'!$H$10:$H$5000)) -> 0 | F76: =SUMPRODUCT(('Libro Diario'!$A$10:$A$5000=$B$4)*('Libro Diario'!$E$10:$E$5000=A76)*(YEAR('Libro Diario'!$C$10:$C$5000)=$E$4)*('Libro Diario'!$I$10:$I$5000)) -> 0 | G76: =IF(E76>F76,E76-F76,"") | H76: =IF(F76>E76,F76-E76,"") | I76: =IF(OR(C76="ACTIVO",C76="PERDIDA"),E76-F76,F76-E76) -> 0
A77: 3101003 | B77: =IFERROR(INDEX(Cuentas!$C$8:$C$500,MATCH($B$4&"|"&A77,Cuentas!$A$8:$A$500&"|"&Cuentas!$B$8:$B$500,0)),"Combustibles y Mant. Vehiculos") -> Combustibles y Mant. Vehiculos | C77: =IFERROR(INDEX(Cuentas!$D$8:$D$500,MATCH($B$4&"|"&A77,Cuentas!$A$8:$A$500&"|"&Cuentas!$B$8:$B$500,0)),"PERDIDA") -> PERDIDA | D77: =IF(OR(C77="ACTIVO",C77="PERDIDA"),"Deudor","Acreedor") -> Deudor | E77: =SUMPRODUCT(('Libro Diario'!$A$10:$A$5000=$B$4)*('Libro Diario'!$E$10:$E$5000=A77)*(YEAR('Libro Diario'!$C$10:$C$5000)=$E$4)*('Libro Diario'!$H$10:$H$5000)) -> 0 | F77: =SUMPRODUCT(('Libro Diario'!$A$10:$A$5000=$B$4)*('Libro Diario'!$E$10:$E$5000=A77)*(YEAR('Libro Diario'!$C$10:$C$5000)=$E$4)*('Libro Diario'!$I$10:$I$5000)) -> 0 | G77: =IF(E77>F77,E77-F77,"") | H77: =IF(F77>E77,F77-E77,"") | I77: =IF(OR(C77="ACTIVO",C77="PERDIDA"),E77-F77,F77-E77) -> 0
A78: 3102002 | B78: =IFERROR(INDEX(Cuentas!$C$8:$C$500,MATCH($B$4&"|"&A78,Cuentas!$A$8:$A$500&"|"&Cuentas!$B$8:$B$500,0)),"Capacitación y Perfeccionamiento") -> Capacitación y Perfeccionamiento | C78: =IFERROR(INDEX(Cuentas!$D$8:$D$500,MATCH($B$4&"|"&A78,Cuentas!$A$8:$A$500&"|"&Cuentas!$B$8:$B$500,0)),"PERDIDA") -> PERDIDA | D78: =IF(OR(C78="ACTIVO",C78="PERDIDA"),"Deudor","Acreedor") -> Deudor | E78: =SUMPRODUCT(('Libro Diario'!$A$10:$A$5000=$B$4)*('Libro Diario'!$E$10:$E$5000=A78)*(YEAR('Libro Diario'!$C$10:$C$5000)=$E$4)*('Libro Diario'!$H$10:$H$5000)) -> 0 | F78: =SUMPRODUCT(('Libro Diario'!$A$10:$A$5000=$B$4)*('Libro Diario'!$E$10:$E$5000=A78)*(YEAR('Libro Diario'!$C$10:$C$5000)=$E$4)*('Libro Diario'!$I$10:$I$5000)) -> 0 | G78: =IF(E78>F78,E78-F78,"") | H78: =IF(F78>E78,F78-E78,"") | I78: =IF(OR(C78="ACTIVO",C78="PERDIDA"),E78-F78,F78-E78) -> 0
A79: 3103001 | B79: =IFERROR(INDEX(Cuentas!$C$8:$C$500,MATCH($B$4&"|"&A79,Cuentas!$A$8:$A$500&"|"&Cuentas!$B$8:$B$500,0)),"Remuneraciones") -> Remuneraciones | C79: =IFERROR(INDEX(Cuentas!$D$8:$D$500,MATCH($B$4&"|"&A79,Cuentas!$A$8:$A$500&"|"&Cuentas!$B$8:$B$500,0)),"PERDIDA") -> PERDIDA | D79: =IF(OR(C79="ACTIVO",C79="PERDIDA"),"Deudor","Acreedor") -> Deudor | E79: =SUMPRODUCT(('Libro Diario'!$A$10:$A$5000=$B$4)*('Libro Diario'!$E$10:$E$5000=A79)*(YEAR('Libro Diario'!$C$10:$C$5000)=$E$4)*('Libro Diario'!$H$10:$H$5000)) -> 0 | F79: =SUMPRODUCT(('Libro Diario'!$A$10:$A$5000=$B$4)*('Libro Diario'!$E$10:$E$5000=A79)*(YEAR('Libro Diario'!$C$10:$C$5000)=$E$4)*('Libro Diario'!$I$10:$I$5000)) -> 0 | G79: =IF(E79>F79,E79-F79,"") | H79: =IF(F79>E79,F79-E79,"") | I79: =IF(OR(C79="ACTIVO",C79="PERDIDA"),E79-F79,F79-E79) -> 0
A80: 3103002 | B80: =IFERROR(INDEX(Cuentas!$C$8:$C$500,MATCH($B$4&"|"&A80,Cuentas!$A$8:$A$500&"|"&Cuentas!$B$8:$B$500,0)),"Asesorias y Honorarios Profesionales") -> Asesorias y Honorarios Profesionales | C80: =IFERROR(INDEX(Cuentas!$D$8:$D$500,MATCH($B$4&"|"&A80,Cuentas!$A$8:$A$500&"|"&Cuentas!$B$8:$B$500,0)),"PERDIDA") -> PERDIDA | D80: =IF(OR(C80="ACTIVO",C80="PERDIDA"),"Deudor","Acreedor") -> Deudor | E80: =SUMPRODUCT(('Libro Diario'!$A$10:$A$5000=$B$4)*('Libro Diario'!$E$10:$E$5000=A80)*(YEAR('Libro Diario'!$C$10:$C$5000)=$E$4)*('Libro Diario'!$H$10:$H$5000)) -> 0 | F80: =SUMPRODUCT(('Libro Diario'!$A$10:$A$5000=$B$4)*('Libro Diario'!$E$10:$E$5000=A80)*(YEAR('Libro Diario'!$C$10:$C$5000)=$E$4)*('Libro Diario'!$I$10:$I$5000)) -> 0 | G80: =IF(E80>F80,E80-F80,"") | H80: =IF(F80>E80,F80-E80,"") | I80: =IF(OR(C80="ACTIVO",C80="PERDIDA"),E80-F80,F80-E80) -> 0
A81: 3103003 | B81: =IFERROR(INDEX(Cuentas!$C$8:$C$500,MATCH($B$4&"|"&A81,Cuentas!$A$8:$A$500&"|"&Cuentas!$B$8:$B$500,0)),"Gastos Varios") -> Gastos Varios | C81: =IFERROR(INDEX(Cuentas!$D$8:$D$500,MATCH($B$4&"|"&A81,Cuentas!$A$8:$A$500&"|"&Cuentas!$B$8:$B$500,0)),"PERDIDA") -> PERDIDA | D81: =IF(OR(C81="ACTIVO",C81="PERDIDA"),"Deudor","Acreedor") -> Deudor | E81: =SUMPRODUCT(('Libro Diario'!$A$10:$A$5000=$B$4)*('Libro Diario'!$E$10:$E$5000=A81)*(YEAR('Libro Diario'!$C$10:$C$5000)=$E$4)*('Libro Diario'!$H$10:$H$5000)) -> 0 | F81: =SUMPRODUCT(('Libro Diario'!$A$10:$A$5000=$B$4)*('Libro Diario'!$E$10:$E$5000=A81)*(YEAR('Libro Diario'!$C$10:$C$5000)=$E$4)*('Libro Diario'!$I$10:$I$5000)) -> 0 | G81: =IF(E81>F81,E81-F81,"") | H81: =IF(F81>E81,F81-E81,"") | I81: =IF(OR(C81="ACTIVO",C81="PERDIDA"),E81-F81,F81-E81) -> 0
A82: 3103004 | B82: =IFERROR(INDEX(Cuentas!$C$8:$C$500,MATCH($B$4&"|"&A82,Cuentas!$A$8:$A$500&"|"&Cuentas!$B$8:$B$500,0)),"Fletes y Combustibles") -> Fletes y Combustibles | C82: =IFERROR(INDEX(Cuentas!$D$8:$D$500,MATCH($B$4&"|"&A82,Cuentas!$A$8:$A$500&"|"&Cuentas!$B$8:$B$500,0)),"PERDIDA") -> PERDIDA | D82: =IF(OR(C82="ACTIVO",C82="PERDIDA"),"Deudor","Acreedor") -> Deudor | E82: =SUMPRODUCT(('Libro Diario'!$A$10:$A$5000=$B$4)*('Libro Diario'!$E$10:$E$5000=A82)*(YEAR('Libro Diario'!$C$10:$C$5000)=$E$4)*('Libro Diario'!$H$10:$H$5000)) -> 0 | F82: =SUMPRODUCT(('Libro Diario'!$A$10:$A$5000=$B$4)*('Libro Diario'!$E$10:$E$5000=A82)*(YEAR('Libro Diario'!$C$10:$C$5000)=$E$4)*('Libro Diario'!$I$10:$I$5000)) -> 0 | G82: =IF(E82>F82,E82-F82,"") | H82: =IF(F82>E82,F82-E82,"") | I82: =IF(OR(C82="ACTIVO",C82="PERDIDA"),E82-F82,F82-E82) -> 0
A83: 3103005 | B83: =IFERROR(INDEX(Cuentas!$C$8:$C$500,MATCH($B$4&"|"&A83,Cuentas!$A$8:$A$500&"|"&Cuentas!$B$8:$B$500,0)),"Gastos Repuestos") -> Gastos Repuestos | C83: =IFERROR(INDEX(Cuentas!$D$8:$D$500,MATCH($B$4&"|"&A83,Cuentas!$A$8:$A$500&"|"&Cuentas!$B$8:$B$500,0)),"PERDIDA") -> PERDIDA | D83: =IF(OR(C83="ACTIVO",C83="PERDIDA"),"Deudor","Acreedor") -> Deudor | E83: =SUMPRODUCT(('Libro Diario'!$A$10:$A$5000=$B$4)*('Libro Diario'!$E$10:$E$5000=A83)*(YEAR('Libro Diario'!$C$10:$C$5000)=$E$4)*('Libro Diario'!$H$10:$H$5000)) -> 0 | F83: =SUMPRODUCT(('Libro Diario'!$A$10:$A$5000=$B$4)*('Libro Diario'!$E$10:$E$5000=A83)*(YEAR('Libro Diario'!$C$10:$C$5000)=$E$4)*('Libro Diario'!$I$10:$I$5000)) -> 0 | G83: =IF(E83>F83,E83-F83,"") | H83: =IF(F83>E83,F83-E83,"") | I83: =IF(OR(C83="ACTIVO",C83="PERDIDA"),E83-F83,F83-E83) -> 0
A84: 3103006 | B84: =IFERROR(INDEX(Cuentas!$C$8:$C$500,MATCH($B$4&"|"&A84,Cuentas!$A$8:$A$500&"|"&Cuentas!$B$8:$B$500,0)),"Gastos Basicos") -> Gastos Basicos | C84: =IFERROR(INDEX(Cuentas!$D$8:$D$500,MATCH($B$4&"|"&A84,Cuentas!$A$8:$A$500&"|"&Cuentas!$B$8:$B$500,0)),"PERDIDA") -> PERDIDA | D84: =IF(OR(C84="ACTIVO",C84="PERDIDA"),"Deudor","Acreedor") -> Deudor | E84: =SUMPRODUCT(('Libro Diario'!$A$10:$A$5000=$B$4)*('Libro Diario'!$E$10:$E$5000=A84)*(YEAR('Libro Diario'!$C$10:$C$5000)=$E$4)*('Libro Diario'!$H$10:$H$5000)) -> 0 | F84: =SUMPRODUCT(('Libro Diario'!$A$10:$A$5000=$B$4)*('Libro Diario'!$E$10:$E$5000=A84)*(YEAR('Libro Diario'!$C$10:$C$5000)=$E$4)*('Libro Diario'!$I$10:$I$5000)) -> 0 | G84: =IF(E84>F84,E84-F84,"") | H84: =IF(F84>E84,F84-E84,"") | I84: =IF(OR(C84="ACTIVO",C84="PERDIDA"),E84-F84,F84-E84) -> 0
A85: 3103007 | B85: =IFERROR(INDEX(Cuentas!$C$8:$C$500,MATCH($B$4&"|"&A85,Cuentas!$A$8:$A$500&"|"&Cuentas!$B$8:$B$500,0)),"Gastos de Administración") -> Gastos de Administración | C85: =IFERROR(INDEX(Cuentas!$D$8:$D$500,MATCH($B$4&"|"&A85,Cuentas!$A$8:$A$500&"|"&Cuentas!$B$8:$B$500,0)),"PERDIDA") -> PERDIDA | D85: =IF(OR(C85="ACTIVO",C85="PERDIDA"),"Deudor","Acreedor") -> Deudor | E85: =SUMPRODUCT(('Libro Diario'!$A$10:$A$5000=$B$4)*('Libro Diario'!$E$10:$E$5000=A85)*(YEAR('Libro Diario'!$C$10:$C$5000)=$E$4)*('Libro Diario'!$H$10:$H$5000)) -> 0 | F85: =SUMPRODUCT(('Libro Diario'!$A$10:$A$5000=$B$4)*('Libro Diario'!$E$10:$E$5000=A85)*(YEAR('Libro Diario'!$C$10:$C$5000)=$E$4)*('Libro Diario'!$I$10:$I$5000)) -> 0 | G85: =IF(E85>F85,E85-F85,"") | H85: =IF(F85>E85,F85-E85,"") | I85: =IF(OR(C85="ACTIVO",C85="PERDIDA"),E85-F85,F85-E85) -> 0
A86: 3103008 | B86: =IFERROR(INDEX(Cuentas!$C$8:$C$500,MATCH($B$4&"|"&A86,Cuentas!$A$8:$A$500&"|"&Cuentas!$B$8:$B$500,0)),"Publicidad") -> Publicidad | C86: =IFERROR(INDEX(Cuentas!$D$8:$D$500,MATCH($B$4&"|"&A86,Cuentas!$A$8:$A$500&"|"&Cuentas!$B$8:$B$500,0)),"PERDIDA") -> PERDIDA | D86: =IF(OR(C86="ACTIVO",C86="PERDIDA"),"Deudor","Acreedor") -> Deudor | E86: =SUMPRODUCT(('Libro Diario'!$A$10:$A$5000=$B$4)*('Libro Diario'!$E$10:$E$5000=A86)*(YEAR('Libro Diario'!$C$10:$C$5000)=$E$4)*('Libro Diario'!$H$10:$H$5000)) -> 0 | F86: =SUMPRODUCT(('Libro Diario'!$A$10:$A$5000=$B$4)*('Libro Diario'!$E$10:$E$5000=A86)*(YEAR('Libro Diario'!$C$10:$C$5000)=$E$4)*('Libro Diario'!$I$10:$I$5000)) -> 0 | G86: =IF(E86>F86,E86-F86,"") | H86: =IF(F86>E86,F86-E86,"") | I86: =IF(OR(C86="ACTIVO",C86="PERDIDA"),E86-F86,F86-E86) -> 0
A87: 3103009 | B87: =IFERROR(INDEX(Cuentas!$C$8:$C$500,MATCH($B$4&"|"&A87,Cuentas!$A$8:$A$500&"|"&Cuentas!$B$8:$B$500,0)),"Arriendos") -> Arriendos | C87: =IFERROR(INDEX(Cuentas!$D$8:$D$500,MATCH($B$4&"|"&A87,Cuentas!$A$8:$A$500&"|"&Cuentas!$B$8:$B$500,0)),"PERDIDA") -> PERDIDA | D87: =IF(OR(C87="ACTIVO",C87="PERDIDA"),"Deudor","Acreedor") -> Deudor | E87: =SUMPRODUCT(('Libro Diario'!$A$10:$A$5000=$B$4)*('Libro Diario'!$E$10:$E$5000=A87)*(YEAR('Libro Diario'!$C$10:$C$5000)=$E$4)*('Libro Diario'!$H$10:$H$5000)) -> 0 | F87: =SUMPRODUCT(('Libro Diario'!$A$10:$A$5000=$B$4)*('Libro Diario'!$E$10:$E$5000=A87)*(YEAR('Libro Diario'!$C$10:$C$5000)=$E$4)*('Libro Diario'!$I$10:$I$5000)) -> 0 | G87: =IF(E87>F87,E87-F87,"") | H87: =IF(F87>E87,F87-E87,"") | I87: =IF(OR(C87="ACTIVO",C87="PERDIDA"),E87-F87,F87-E87) -> 0
A88: 3103010 | B88: =IFERROR(INDEX(Cuentas!$C$8:$C$500,MATCH($B$4&"|"&A88,Cuentas!$A$8:$A$500&"|"&Cuentas!$B$8:$B$500,0)),"Seguros") -> Seguros | C88: =IFERROR(INDEX(Cuentas!$D$8:$D$500,MATCH($B$4&"|"&A88,Cuentas!$A$8:$A$500&"|"&Cuentas!$B$8:$B$500,0)),"PERDIDA") -> PERDIDA | D88: =IF(OR(C88="ACTIVO",C88="PERDIDA"),"Deudor","Acreedor") -> Deudor | E88: =SUMPRODUCT(('Libro Diario'!$A$10:$A$5000=$B$4)*('Libro Diario'!$E$10:$E$5000=A88)*(YEAR('Libro Diario'!$C$10:$C$5000)=$E$4)*('Libro Diario'!$H$10:$H$5000)) -> 0 | F88: =SUMPRODUCT(('Libro Diario'!$A$10:$A$5000=$B$4)*('Libro Diario'!$E$10:$E$5000=A88)*(YEAR('Libro Diario'!$C$10:$C$5000)=$E$4)*('Libro Diario'!$I$10:$I$5000)) -> 0 | G88: =IF(E88>F88,E88-F88,"") | H88: =IF(F88>E88,F88-E88,"") | I88: =IF(OR(C88="ACTIVO",C88="PERDIDA"),E88-F88,F88-E88) -> 0
A89: 3201001 | B89: =IFERROR(INDEX(Cuentas!$C$8:$C$500,MATCH($B$4&"|"&A89,Cuentas!$A$8:$A$500&"|"&Cuentas!$B$8:$B$500,0)),"Gastos Financieros") -> Gastos Financieros | C89: =IFERROR(INDEX(Cuentas!$D$8:$D$500,MATCH($B$4&"|"&A89,Cuentas!$A$8:$A$500&"|"&Cuentas!$B$8:$B$500,0)),"PERDIDA") -> PERDIDA | D89: =IF(OR(C89="ACTIVO",C89="PERDIDA"),"Deudor","Acreedor") -> Deudor | E89: =SUMPRODUCT(('Libro Diario'!$A$10:$A$5000=$B$4)*('Libro Diario'!$E$10:$E$5000=A89)*(YEAR('Libro Diario'!$C$10:$C$5000)=$E$4)*('Libro Diario'!$H$10:$H$5000)) -> 0 | F89: =SUMPRODUCT(('Libro Diario'!$A$10:$A$5000=$B$4)*('Libro Diario'!$E$10:$E$5000=A89)*(YEAR('Libro Diario'!$C$10:$C$5000)=$E$4)*('Libro Diario'!$I$10:$I$5000)) -> 0 | G89: =IF(E89>F89,E89-F89,"") | H89: =IF(F89>E89,F89-E89,"") | I89: =IF(OR(C89="ACTIVO",C89="PERDIDA"),E89-F89,F89-E89) -> 0
A90: 3201101 | B90: =IFERROR(INDEX(Cuentas!$C$8:$C$500,MATCH($B$4&"|"&A90,Cuentas!$A$8:$A$500&"|"&Cuentas!$B$8:$B$500,0)),"Impuesto 1a Categoria") -> Impuesto 1a Categoria | C90: =IFERROR(INDEX(Cuentas!$D$8:$D$500,MATCH($B$4&"|"&A90,Cuentas!$A$8:$A$500&"|"&Cuentas!$B$8:$B$500,0)),"PERDIDA") -> PERDIDA | D90: =IF(OR(C90="ACTIVO",C90="PERDIDA"),"Deudor","Acreedor") -> Deudor | E90: =SUMPRODUCT(('Libro Diario'!$A$10:$A$5000=$B$4)*('Libro Diario'!$E$10:$E$5000=A90)*(YEAR('Libro Diario'!$C$10:$C$5000)=$E$4)*('Libro Diario'!$H$10:$H$5000)) -> 0 | F90: =SUMPRODUCT(('Libro Diario'!$A$10:$A$5000=$B$4)*('Libro Diario'!$E$10:$E$5000=A90)*(YEAR('Libro Diario'!$C$10:$C$5000)=$E$4)*('Libro Diario'!$I$10:$I$5000)) -> 0 | G90: =IF(E90>F90,E90-F90,"") | H90: =IF(F90>E90,F90-E90,"") | I90: =IF(OR(C90="ACTIVO",C90="PERDIDA"),E90-F90,F90-E90) -> 0
A91: 3201102 | B91: =IFERROR(INDEX(Cuentas!$C$8:$C$500,MATCH($B$4&"|"&A91,Cuentas!$A$8:$A$500&"|"&Cuentas!$B$8:$B$500,0)),"Servicios incobrables") -> Servicios incobrables | C91: =IFERROR(INDEX(Cuentas!$D$8:$D$500,MATCH($B$4&"|"&A91,Cuentas!$A$8:$A$500&"|"&Cuentas!$B$8:$B$500,0)),"PERDIDA") -> PERDIDA | D91: =IF(OR(C91="ACTIVO",C91="PERDIDA"),"Deudor","Acreedor") -> Deudor | E91: =SUMPRODUCT(('Libro Diario'!$A$10:$A$5000=$B$4)*('Libro Diario'!$E$10:$E$5000=A91)*(YEAR('Libro Diario'!$C$10:$C$5000)=$E$4)*('Libro Diario'!$H$10:$H$5000)) -> 0 | F91: =SUMPRODUCT(('Libro Diario'!$A$10:$A$5000=$B$4)*('Libro Diario'!$E$10:$E$5000=A91)*(YEAR('Libro Diario'!$C$10:$C$5000)=$E$4)*('Libro Diario'!$I$10:$I$5000)) -> 0 | G91: =IF(E91>F91,E91-F91,"") | H91: =IF(F91>E91,F91-E91,"") | I91: =IF(OR(C91="ACTIVO",C91="PERDIDA"),E91-F91,F91-E91) -> 0
A92: 3201103 | B92: =IFERROR(INDEX(Cuentas!$C$8:$C$500,MATCH($B$4&"|"&A92,Cuentas!$A$8:$A$500&"|"&Cuentas!$B$8:$B$500,0)),"Patentes y Derechos Municipales") -> Patentes y Derechos Municipales | C92: =IFERROR(INDEX(Cuentas!$D$8:$D$500,MATCH($B$4&"|"&A92,Cuentas!$A$8:$A$500&"|"&Cuentas!$B$8:$B$500,0)),"PERDIDA") -> PERDIDA | D92: =IF(OR(C92="ACTIVO",C92="PERDIDA"),"Deudor","Acreedor") -> Deudor | E92: =SUMPRODUCT(('Libro Diario'!$A$10:$A$5000=$B$4)*('Libro Diario'!$E$10:$E$5000=A92)*(YEAR('Libro Diario'!$C$10:$C$5000)=$E$4)*('Libro Diario'!$H$10:$H$5000)) -> 0 | F92: =SUMPRODUCT(('Libro Diario'!$A$10:$A$5000=$B$4)*('Libro Diario'!$E$10:$E$5000=A92)*(YEAR('Libro Diario'!$C$10:$C$5000)=$E$4)*('Libro Diario'!$I$10:$I$5000)) -> 0 | G92: =IF(E92>F92,E92-F92,"") | H92: =IF(F92>E92,F92-E92,"") | I92: =IF(OR(C92="ACTIVO",C92="PERDIDA"),E92-F92,F92-E92) -> 0
A93: 3201104 | B93: =IFERROR(INDEX(Cuentas!$C$8:$C$500,MATCH($B$4&"|"&A93,Cuentas!$A$8:$A$500&"|"&Cuentas!$B$8:$B$500,0)),"Otros Impuestos") -> Otros Impuestos | C93: =IFERROR(INDEX(Cuentas!$D$8:$D$500,MATCH($B$4&"|"&A93,Cuentas!$A$8:$A$500&"|"&Cuentas!$B$8:$B$500,0)),"PERDIDA") -> PERDIDA | D93: =IF(OR(C93="ACTIVO",C93="PERDIDA"),"Deudor","Acreedor") -> Deudor | E93: =SUMPRODUCT(('Libro Diario'!$A$10:$A$5000=$B$4)*('Libro Diario'!$E$10:$E$5000=A93)*(YEAR('Libro Diario'!$C$10:$C$5000)=$E$4)*('Libro Diario'!$H$10:$H$5000)) -> 0 | F93: =SUMPRODUCT(('Libro Diario'!$A$10:$A$5000=$B$4)*('Libro Diario'!$E$10:$E$5000=A93)*(YEAR('Libro Diario'!$C$10:$C$5000)=$E$4)*('Libro Diario'!$I$10:$I$5000)) -> 0 | G93: =IF(E93>F93,E93-F93,"") | H93: =IF(F93>E93,F93-E93,"") | I93: =IF(OR(C93="ACTIVO",C93="PERDIDA"),E93-F93,F93-E93) -> 0
A94: 3201401 | B94: =IFERROR(INDEX(Cuentas!$C$8:$C$500,MATCH($B$4&"|"&A94,Cuentas!$A$8:$A$500&"|"&Cuentas!$B$8:$B$500,0)),"Depreciacion Vehiculos") -> Depreciacion Vehiculos | C94: =IFERROR(INDEX(Cuentas!$D$8:$D$500,MATCH($B$4&"|"&A94,Cuentas!$A$8:$A$500&"|"&Cuentas!$B$8:$B$500,0)),"PERDIDA") -> PERDIDA | D94: =IF(OR(C94="ACTIVO",C94="PERDIDA"),"Deudor","Acreedor") -> Deudor | E94: =SUMPRODUCT(('Libro Diario'!$A$10:$A$5000=$B$4)*('Libro Diario'!$E$10:$E$5000=A94)*(YEAR('Libro Diario'!$C$10:$C$5000)=$E$4)*('Libro Diario'!$H$10:$H$5000)) -> 0 | F94: =SUMPRODUCT(('Libro Diario'!$A$10:$A$5000=$B$4)*('Libro Diario'!$E$10:$E$5000=A94)*(YEAR('Libro Diario'!$C$10:$C$5000)=$E$4)*('Libro Diario'!$I$10:$I$5000)) -> 0 | G94: =IF(E94>F94,E94-F94,"") | H94: =IF(F94>E94,F94-E94,"") | I94: =IF(OR(C94="ACTIVO",C94="PERDIDA"),E94-F94,F94-E94) -> 0
A95: 3201402 | B95: =IFERROR(INDEX(Cuentas!$C$8:$C$500,MATCH($B$4&"|"&A95,Cuentas!$A$8:$A$500&"|"&Cuentas!$B$8:$B$500,0)),"Depreciacion") -> Depreciacion | C95: =IFERROR(INDEX(Cuentas!$D$8:$D$500,MATCH($B$4&"|"&A95,Cuentas!$A$8:$A$500&"|"&Cuentas!$B$8:$B$500,0)),"PERDIDA") -> PERDIDA | D95: =IF(OR(C95="ACTIVO",C95="PERDIDA"),"Deudor","Acreedor") -> Deudor | E95: =SUMPRODUCT(('Libro Diario'!$A$10:$A$5000=$B$4)*('Libro Diario'!$E$10:$E$5000=A95)*(YEAR('Libro Diario'!$C$10:$C$5000)=$E$4)*('Libro Diario'!$H$10:$H$5000)) -> 0 | F95: =SUMPRODUCT(('Libro Diario'!$A$10:$A$5000=$B$4)*('Libro Diario'!$E$10:$E$5000=A95)*(YEAR('Libro Diario'!$C$10:$C$5000)=$E$4)*('Libro Diario'!$I$10:$I$5000)) -> 0 | G95: =IF(E95>F95,E95-F95,"") | H95: =IF(F95>E95,F95-E95,"") | I95: =IF(OR(C95="ACTIVO",C95="PERDIDA"),E95-F95,F95-E95) -> 0
A96: 3201403 | B96: =IFERROR(INDEX(Cuentas!$C$8:$C$500,MATCH($B$4&"|"&A96,Cuentas!$A$8:$A$500&"|"&Cuentas!$B$8:$B$500,0)),"Depreciacion Carros y Remolques") -> Depreciacion Carros y Remolques | C96: =IFERROR(INDEX(Cuentas!$D$8:$D$500,MATCH($B$4&"|"&A96,Cuentas!$A$8:$A$500&"|"&Cuentas!$B$8:$B$500,0)),"PERDIDA") -> PERDIDA | D96: =IF(OR(C96="ACTIVO",C96="PERDIDA"),"Deudor","Acreedor") -> Deudor | E96: =SUMPRODUCT(('Libro Diario'!$A$10:$A$5000=$B$4)*('Libro Diario'!$E$10:$E$5000=A96)*(YEAR('Libro Diario'!$C$10:$C$5000)=$E$4)*('Libro Diario'!$H$10:$H$5000)) -> 0 | F96: =SUMPRODUCT(('Libro Diario'!$A$10:$A$5000=$B$4)*('Libro Diario'!$E$10:$E$5000=A96)*(YEAR('Libro Diario'!$C$10:$C$5000)=$E$4)*('Libro Diario'!$I$10:$I$5000)) -> 0 | G96: =IF(E96>F96,E96-F96,"") | H96: =IF(F96>E96,F96-E96,"") | I96: =IF(OR(C96="ACTIVO",C96="PERDIDA"),E96-F96,F96-E96) -> 0
A97: 3201404 | B97: =IFERROR(INDEX(Cuentas!$C$8:$C$500,MATCH($B$4&"|"&A97,Cuentas!$A$8:$A$500&"|"&Cuentas!$B$8:$B$500,0)),"Depreciacion Muebles, Utiles e Instalaciones") -> Depreciacion Muebles, Utiles e Instalaciones | C97: =IFERROR(INDEX(Cuentas!$D$8:$D$500,MATCH($B$4&"|"&A97,Cuentas!$A$8:$A$500&"|"&Cuentas!$B$8:$B$500,0)),"PERDIDA") -> PERDIDA | D97: =IF(OR(C97="ACTIVO",C97="PERDIDA"),"Deudor","Acreedor") -> Deudor | E97: =SUMPRODUCT(('Libro Diario'!$A$10:$A$5000=$B$4)*('Libro Diario'!$E$10:$E$5000=A97)*(YEAR('Libro Diario'!$C$10:$C$5000)=$E$4)*('Libro Diario'!$H$10:$H$5000)) -> 0 | F97: =SUMPRODUCT(('Libro Diario'!$A$10:$A$5000=$B$4)*('Libro Diario'!$E$10:$E$5000=A97)*(YEAR('Libro Diario'!$C$10:$C$5000)=$E$4)*('Libro Diario'!$I$10:$I$5000)) -> 0 | G97: =IF(E97>F97,E97-F97,"") | H97: =IF(F97>E97,F97-E97,"") | I97: =IF(OR(C97="ACTIVO",C97="PERDIDA"),E97-F97,F97-E97) -> 0
A98: 3201501 | B98: =IFERROR(INDEX(Cuentas!$C$8:$C$500,MATCH($B$4&"|"&A98,Cuentas!$A$8:$A$500&"|"&Cuentas!$B$8:$B$500,0)),"Correccion Monetaria") -> Correccion Monetaria | C98: =IFERROR(INDEX(Cuentas!$D$8:$D$500,MATCH($B$4&"|"&A98,Cuentas!$A$8:$A$500&"|"&Cuentas!$B$8:$B$500,0)),"PERDIDA") -> PERDIDA | D98: =IF(OR(C98="ACTIVO",C98="PERDIDA"),"Deudor","Acreedor") -> Deudor | E98: =SUMPRODUCT(('Libro Diario'!$A$10:$A$5000=$B$4)*('Libro Diario'!$E$10:$E$5000=A98)*(YEAR('Libro Diario'!$C$10:$C$5000)=$E$4)*('Libro Diario'!$H$10:$H$5000)) -> 0 | F98: =SUMPRODUCT(('Libro Diario'!$A$10:$A$5000=$B$4)*('Libro Diario'!$E$10:$E$5000=A98)*(YEAR('Libro Diario'!$C$10:$C$5000)=$E$4)*('Libro Diario'!$I$10:$I$5000)) -> 0 | G98: =IF(E98>F98,E98-F98,"") | H98: =IF(F98>E98,F98-E98,"") | I98: =IF(OR(C98="ACTIVO",C98="PERDIDA"),E98-F98,F98-E98) -> 0
A99: 4101001 | B99: =IFERROR(INDEX(Cuentas!$C$8:$C$500,MATCH($B$4&"|"&A99,Cuentas!$A$8:$A$500&"|"&Cuentas!$B$8:$B$500,0)),"Ventas") -> Ventas | C99: =IFERROR(INDEX(Cuentas!$D$8:$D$500,MATCH($B$4&"|"&A99,Cuentas!$A$8:$A$500&"|"&Cuentas!$B$8:$B$500,0)),"GANANCIA") -> GANANCIA | D99: =IF(OR(C99="ACTIVO",C99="PERDIDA"),"Deudor","Acreedor") -> Acreedor | E99: =SUMPRODUCT(('Libro Diario'!$A$10:$A$5000=$B$4)*('Libro Diario'!$E$10:$E$5000=A99)*(YEAR('Libro Diario'!$C$10:$C$5000)=$E$4)*('Libro Diario'!$H$10:$H$5000)) -> 0 | F99: =SUMPRODUCT(('Libro Diario'!$A$10:$A$5000=$B$4)*('Libro Diario'!$E$10:$E$5000=A99)*(YEAR('Libro Diario'!$C$10:$C$5000)=$E$4)*('Libro Diario'!$I$10:$I$5000)) -> 0 | G99: =IF(E99>F99,E99-F99,"") | H99: =IF(F99>E99,F99-E99,"") | I99: =IF(OR(C99="ACTIVO",C99="PERDIDA"),E99-F99,F99-E99) -> 0
A100: 4101002 | B100: =IFERROR(INDEX(Cuentas!$C$8:$C$500,MATCH($B$4&"|"&A100,Cuentas!$A$8:$A$500&"|"&Cuentas!$B$8:$B$500,0)),"Descuentos ganados") -> Descuentos ganados | C100: =IFERROR(INDEX(Cuentas!$D$8:$D$500,MATCH($B$4&"|"&A100,Cuentas!$A$8:$A$500&"|"&Cuentas!$B$8:$B$500,0)),"GANANCIA") -> GANANCIA | D100: =IF(OR(C100="ACTIVO",C100="PERDIDA"),"Deudor","Acreedor") -> Acreedor | E100: =SUMPRODUCT(('Libro Diario'!$A$10:$A$5000=$B$4)*('Libro Diario'!$E$10:$E$5000=A100)*(YEAR('Libro Diario'!$C$10:$C$5000)=$E$4)*('Libro Diario'!$H$10:$H$5000)) -> 0 | F100: =SUMPRODUCT(('Libro Diario'!$A$10:$A$5000=$B$4)*('Libro Diario'!$E$10:$E$5000=A100)*(YEAR('Libro Diario'!$C$10:$C$5000)=$E$4)*('Libro Diario'!$I$10:$I$5000)) -> 0 | G100: =IF(E100>F100,E100-F100,"") | H100: =IF(F100>E100,F100-E100,"") | I100: =IF(OR(C100="ACTIVO",C100="PERDIDA"),E100-F100,F100-E100) -> 0
A101: 4201101 | B101: =IFERROR(INDEX(Cuentas!$C$8:$C$500,MATCH($B$4&"|"&A101,Cuentas!$A$8:$A$500&"|"&Cuentas!$B$8:$B$500,0)),"Otros IngresosResultado Venta Avtivo Fijo") -> Otros IngresosResultado Venta Avtivo Fijo | C101: =IFERROR(INDEX(Cuentas!$D$8:$D$500,MATCH($B$4&"|"&A101,Cuentas!$A$8:$A$500&"|"&Cuentas!$B$8:$B$500,0)),"GANANCIA") -> GANANCIA | D101: =IF(OR(C101="ACTIVO",C101="PERDIDA"),"Deudor","Acreedor") -> Acreedor | E101: =SUMPRODUCT(('Libro Diario'!$A$10:$A$5000=$B$4)*('Libro Diario'!$E$10:$E$5000=A101)*(YEAR('Libro Diario'!$C$10:$C$5000)=$E$4)*('Libro Diario'!$H$10:$H$5000)) -> 0 | F101: =SUMPRODUCT(('Libro Diario'!$A$10:$A$5000=$B$4)*('Libro Diario'!$E$10:$E$5000=A101)*(YEAR('Libro Diario'!$C$10:$C$5000)=$E$4)*('Libro Diario'!$I$10:$I$5000)) -> 0 | G101: =IF(E101>F101,E101-F101,"") | H101: =IF(F101>E101,F101-E101,"") | I101: =IF(OR(C101="ACTIVO",C101="PERDIDA"),E101-F101,F101-E101) -> 0
...

Sheet Balance General
A1: BALANCE GENERAL — ESTADO DE SITUACIÓN FINANCIERA
A3: ⚖ NORMATIVA: NIIF para Pymes — obligatoria en Chile desde 2013 (Boletín Técnico N°82, Colegio de Contadores A.G.). Empresas con ingresos > 100.000 UF aplican NIIF Completas bajo supervisión CMF. Estructura clasificada Corriente/No Corriente según Sección 4 NIIF Pymes. Tercera edición NIIF Pymes aplicable desde el 1 de enero de 2027. Para fines tributarios: Balance de 8 Columnas — Formulario I001 (Grandes/Medianas) o I002 (Micro/Pequeñas), presentado con F-22 antes del 30 de junio.
A5: Cliente: | B5: CLI001 | C5: Período (Año): | D5: 2025
A7: =IFERROR(INDEX(Clientes!$C$4:$C$200,MATCH(B5,Clientes!$A$4:$A$200,0)),"[Seleccione un cliente]")&" — Balance General al 31 de Diciembre de "&TEXT(D5,"0") -> ← Ingrese aquí su primer cliente — Balance General al 31 de Diciembre de 2025
A8: RUBRO / CUENTA | D8: MONTO ($)
A9: A C T I V O S
A10: ACTIVO CORRIENTE
A11: Sec. 4.5 NIIF Pymes: Activos cuya realización se espera dentro de 12 meses o del ciclo normal de operación.
A12: Efectivo y Equivalentes — Caja | C12: Sec. 7 NIIF Pymes | Activo más líquido | D12: =SUMPRODUCT(('Libro Diario'!$A$10:$A$5000=$B$5)*('Libro Diario'!$E$10:$E$5000=1101001)*(YEAR('Libro Diario'!$C$10:$C$5000)=$D$5)*('Libro Diario'!$H$10:$H$5000))-SUMPRODUCT(('Libro Diario'!$A$10:$A$5000=$B$5)*('Libro Diario'!$E$10:$E$5000=1101001)*(YEAR('Libro Diario'!$C$10:$C$5000)=$D$5)*('Libro Diario'!$I$10:$I$5000)) -> 0
A13: Efectivo y Equivalentes — Bancos | C13: Sec. 7 NIIF Pymes | Incluye depósitos vista | D13: =SUMPRODUCT(('Libro Diario'!$A$10:$A$5000=$B$5)*('Libro Diario'!$E$10:$E$5000=1101002)*(YEAR('Libro Diario'!$C$10:$C$5000)=$D$5)*('Libro Diario'!$H$10:$H$5000))-SUMPRODUCT(('Libro Diario'!$A$10:$A$5000=$B$5)*('Libro Diario'!$E$10:$E$5000=1101002)*(YEAR('Libro Diario'!$C$10:$C$5000)=$D$5)*('Libro Diario'!$I$10:$I$5000)) -> 0
A14: Cuentas por Cobrar Comerciales | C14: Sec. 11 NIIF Pymes | Valor neto de recuperación | D14: =SUMPRODUCT(('Libro Diario'!$A$10:$A$5000=$B$5)*('Libro Diario'!$E$10:$E$5000=1104001)*(YEAR('Libro Diario'!$C$10:$C$5000)=$D$5)*('Libro Diario'!$H$10:$H$5000))-SUMPRODUCT(('Libro Diario'!$A$10:$A$5000=$B$5)*('Libro Diario'!$E$10:$E$5000=1104001)*(YEAR('Libro Diario'!$C$10:$C$5000)=$D$5)*('Libro Diario'!$I$10:$I$5000)) -> 0
A15: Retiros Acumulados Ej. Anteriores | C15: PCGA Chile | Cuenta socios | D15: =SUMPRODUCT(('Libro Diario'!$A$10:$A$5000=$B$5)*('Libro Diario'!$E$10:$E$5000=1106001)*(YEAR('Libro Diario'!$C$10:$C$5000)=$D$5)*('Libro Diario'!$H$10:$H$5000))-SUMPRODUCT(('Libro Diario'!$A$10:$A$5000=$B$5)*('Libro Diario'!$E$10:$E$5000=1106001)*(YEAR('Libro Diario'!$C$10:$C$5000)=$D$5)*('Libro Diario'!$I$10:$I$5000)) -> 0
A16: Cta. Cte. Socio (1) | C16: Sec. 22 NIIF Pymes | Partes relacionadas | D16: =SUMPRODUCT(('Libro Diario'!$A$10:$A$5000=$B$5)*('Libro Diario'!$E$10:$E$5000=1106002)*(YEAR('Libro Diario'!$C$10:$C$5000)=$D$5)*('Libro Diario'!$H$10:$H$5000))-SUMPRODUCT(('Libro Diario'!$A$10:$A$5000=$B$5)*('Libro Diario'!$E$10:$E$5000=1106002)*(YEAR('Libro Diario'!$C$10:$C$5000)=$D$5)*('Libro Diario'!$I$10:$I$5000)) -> 0
A17: Cta. Cte. Socio (2) | C17: Sec. 22 NIIF Pymes | Partes relacionadas | D17: =SUMPRODUCT(('Libro Diario'!$A$10:$A$5000=$B$5)*('Libro Diario'!$E$10:$E$5000=1106003)*(YEAR('Libro Diario'!$C$10:$C$5000)=$D$5)*('Libro Diario'!$H$10:$H$5000))-SUMPRODUCT(('Libro Diario'!$A$10:$A$5000=$B$5)*('Libro Diario'!$E$10:$E$5000=1106003)*(YEAR('Libro Diario'!$C$10:$C$5000)=$D$5)*('Libro Diario'!$I$10:$I$5000)) -> 0
A18: IVA Crédito Fiscal 19% | C18: Art. 23 D.L. 825 | Recuperable F-29 | D18: =SUMPRODUCT(('Libro Diario'!$A$10:$A$5000=$B$5)*('Libro Diario'!$E$10:$E$5000=1107101)*(YEAR('Libro Diario'!$C$10:$C$5000)=$D$5)*('Libro Diario'!$H$10:$H$5000))-SUMPRODUCT(('Libro Diario'!$A$10:$A$5000=$B$5)*('Libro Diario'!$E$10:$E$5000=1107101)*(YEAR('Libro Diario'!$C$10:$C$5000)=$D$5)*('Libro Diario'!$I$10:$I$5000)) -> 0
A19: IVA CF No Retenido 11% | C19: Art. 11 D.L. 825 | Retención parcial | D19: =SUMPRODUCT(('Libro Diario'!$A$10:$A$5000=$B$5)*('Libro Diario'!$E$10:$E$5000=1107103)*(YEAR('Libro Diario'!$C$10:$C$5000)=$D$5)*('Libro Diario'!$H$10:$H$5000))-SUMPRODUCT(('Libro Diario'!$A$10:$A$5000=$B$5)*('Libro Diario'!$E$10:$E$5000=1107103)*(YEAR('Libro Diario'!$C$10:$C$5000)=$D$5)*('Libro Diario'!$I$10:$I$5000)) -> 0
A20: PPM (Pagos Prov. Mensuales) | C20: Art. 84 LIR | Crédito Impuesto 1ª Cat. | D20: =SUMPRODUCT(('Libro Diario'!$A$10:$A$5000=$B$5)*('Libro Diario'!$E$10:$E$5000=1107201)*(YEAR('Libro Diario'!$C$10:$C$5000)=$D$5)*('Libro Diario'!$H$10:$H$5000))-SUMPRODUCT(('Libro Diario'!$A$10:$A$5000=$B$5)*('Libro Diario'!$E$10:$E$5000=1107201)*(YEAR('Libro Diario'!$C$10:$C$5000)=$D$5)*('Libro Diario'!$I$10:$I$5000)) -> 0
A21: Crédito Diesel Transporte Carga | C21: Art. 7° Ley 18.502 | D21: =SUMPRODUCT(('Libro Diario'!$A$10:$A$5000=$B$5)*('Libro Diario'!$E$10:$E$5000=1107301)*(YEAR('Libro Diario'!$C$10:$C$5000)=$D$5)*('Libro Diario'!$H$10:$H$5000))-SUMPRODUCT(('Libro Diario'!$A$10:$A$5000=$B$5)*('Libro Diario'!$E$10:$E$5000=1107301)*(YEAR('Libro Diario'!$C$10:$C$5000)=$D$5)*('Libro Diario'!$I$10:$I$5000)) -> 0
A22: Art. 33 bis (4%) Activo Fijo | C22: Art. 33 bis LIR | Crédito inversión AF | D22: =SUMPRODUCT(('Libro Diario'!$A$10:$A$5000=$B$5)*('Libro Diario'!$E$10:$E$5000=1107302)*(YEAR('Libro Diario'!$C$10:$C$5000)=$D$5)*('Libro Diario'!$H$10:$H$5000))-SUMPRODUCT(('Libro Diario'!$A$10:$A$5000=$B$5)*('Libro Diario'!$E$10:$E$5000=1107302)*(YEAR('Libro Diario'!$C$10:$C$5000)=$D$5)*('Libro Diario'!$I$10:$I$5000)) -> 0
A23: Contrib. Bienes Raíces — Crédito | C23: Art. 33 bis LIR | D23: =SUMPRODUCT(('Libro Diario'!$A$10:$A$5000=$B$5)*('Libro Diario'!$E$10:$E$5000=1107401)*(YEAR('Libro Diario'!$C$10:$C$5000)=$D$5)*('Libro Diario'!$H$10:$H$5000))-SUMPRODUCT(('Libro Diario'!$A$10:$A$5000=$B$5)*('Libro Diario'!$E$10:$E$5000=1107401)*(YEAR('Libro Diario'!$C$10:$C$5000)=$D$5)*('Libro Diario'!$I$10:$I$5000)) -> 0
A24: PPUA | C24: Art. 31 N°3 LIR | Pérdidas tributarias | D24: =SUMPRODUCT(('Libro Diario'!$A$10:$A$5000=$B$5)*('Libro Diario'!$E$10:$E$5000=1107402)*(YEAR('Libro Diario'!$C$10:$C$5000)=$D$5)*('Libro Diario'!$H$10:$H$5000))-SUMPRODUCT(('Libro Diario'!$A$10:$A$5000=$B$5)*('Libro Diario'!$E$10:$E$5000=1107402)*(YEAR('Libro Diario'!$C$10:$C$5000)=$D$5)*('Libro Diario'!$I$10:$I$5000)) -> 0
A25: Crédito SENCE | C25: Ley 19.518 | Recuperable F-29 | D25: =SUMPRODUCT(('Libro Diario'!$A$10:$A$5000=$B$5)*('Libro Diario'!$E$10:$E$5000=1107404)*(YEAR('Libro Diario'!$C$10:$C$5000)=$D$5)*('Libro Diario'!$H$10:$H$5000))-SUMPRODUCT(('Libro Diario'!$A$10:$A$5000=$B$5)*('Libro Diario'!$E$10:$E$5000=1107404)*(YEAR('Libro Diario'!$C$10:$C$5000)=$D$5)*('Libro Diario'!$I$10:$I$5000)) -> 0
A26: Mercaderías | C26: Sec. 13 NIIF Pymes | Min(costo, VNR) | D26: =SUMPRODUCT(('Libro Diario'!$A$10:$A$5000=$B$5)*('Libro Diario'!$E$10:$E$5000=1108001)*(YEAR('Libro Diario'!$C$10:$C$5000)=$D$5)*('Libro Diario'!$H$10:$H$5000))-SUMPRODUCT(('Libro Diario'!$A$10:$A$5000=$B$5)*('Libro Diario'!$E$10:$E$5000=1108001)*(YEAR('Libro Diario'!$C$10:$C$5000)=$D$5)*('Libro Diario'!$I$10:$I$5000)) -> 0
A27: Materia Prima e Insumos | C27: Sec. 13 NIIF Pymes | FIFO o CMP | D27: =SUMPRODUCT(('Libro Diario'!$A$10:$A$5000=$B$5)*('Libro Diario'!$E$10:$E$5000=1108002)*(YEAR('Libro Diario'!$C$10:$C$5000)=$D$5)*('Libro Diario'!$H$10:$H$5000))-SUMPRODUCT(('Libro Diario'!$A$10:$A$5000=$B$5)*('Libro Diario'!$E$10:$E$5000=1108002)*(YEAR('Libro Diario'!$C$10:$C$5000)=$D$5)*('Libro Diario'!$I$10:$I$5000)) -> 0
A28: Intereses Diferidos CP | C28: Sec. 11 NIIF Pymes | Costo amortizado | D28: =SUMPRODUCT(('Libro Diario'!$A$10:$A$5000=$B$5)*('Libro Diario'!$E$10:$E$5000=1110001)*(YEAR('Libro Diario'!$C$10:$C$5000)=$D$5)*('Libro Diario'!$H$10:$H$5000))-SUMPRODUCT(('Libro Diario'!$A$10:$A$5000=$B$5)*('Libro Diario'!$E$10:$E$5000=1110001)*(YEAR('Libro Diario'!$C$10:$C$5000)=$D$5)*('Libro Diario'!$I$10:$I$5000)) -> 0
A29: TOTAL ACTIVO CORRIENTE | D29: =SUM(D12:D28) -> 0
A31: ACTIVO NO CORRIENTE
A32: Sec. 4.5 NIIF Pymes: Activos no corrientes. Se presentan netos de depreciación acumulada. Terrenos no se deprecian (Sec. 17.15). Leasing financiero se activa (Sec. 20.9).
A33: Vehículos de Carga (Bruto) | C33: Sec. 17 NIIF Pymes | Modelo del Costo | D33: =SUMPRODUCT(('Libro Diario'!$A$10:$A$5000=$B$5)*('Libro Diario'!$E$10:$E$5000=1201001)*(YEAR('Libro Diario'!$C$10:$C$5000)=$D$5)*('Libro Diario'!$H$10:$H$5000))-SUMPRODUCT(('Libro Diario'!$A$10:$A$5000=$B$5)*('Libro Diario'!$E$10:$E$5000=1201001)*(YEAR('Libro Diario'!$C$10:$C$5000)=$D$5)*('Libro Diario'!$I$10:$I$5000)) -> 0
A34: (-) Dep. Acum. Vehículos de Carga | C34: SII: vida útil 7 años (Res. Ex. 43/2002) | D34: =SUMPRODUCT(('Libro Diario'!$A$10:$A$5000=$B$5)*('Libro Diario'!$E$10:$E$5000=1201002)*(YEAR('Libro Diario'!$C$10:$C$5000)=$D$5)*('Libro Diario'!$H$10:$H$5000))-SUMPRODUCT(('Libro Diario'!$A$10:$A$5000=$B$5)*('Libro Diario'!$E$10:$E$5000=1201002)*(YEAR('Libro Diario'!$C$10:$C$5000)=$D$5)*('Libro Diario'!$I$10:$I$5000)) -> 0
A35: Otros Vehículos (Bruto) | C35: Sec. 17 NIIF Pymes | D35: =SUMPRODUCT(('Libro Diario'!$A$10:$A$5000=$B$5)*('Libro Diario'!$E$10:$E$5000=1201003)*(YEAR('Libro Diario'!$C$10:$C$5000)=$D$5)*('Libro Diario'!$H$10:$H$5000))-SUMPRODUCT(('Libro Diario'!$A$10:$A$5000=$B$5)*('Libro Diario'!$E$10:$E$5000=1201003)*(YEAR('Libro Diario'!$C$10:$C$5000)=$D$5)*('Libro Diario'!$I$10:$I$5000)) -> 0
A36: (-) Dep. Acum. Otros Vehículos | C36: SII: tabla vida útil Res. Ex. 43/2002 | D36: =SUMPRODUCT(('Libro Diario'!$A$10:$A$5000=$B$5)*('Libro Diario'!$E$10:$E$5000=1201004)*(YEAR('Libro Diario'!$C$10:$C$5000)=$D$5)*('Libro Diario'!$H$10:$H$5000))-SUMPRODUCT(('Libro Diario'!$A$10:$A$5000=$B$5)*('Libro Diario'!$E$10:$E$5000=1201004)*(YEAR('Libro Diario'!$C$10:$C$5000)=$D$5)*('Libro Diario'!$I$10:$I$5000)) -> 0
A37: Remolques y Carros (Bruto) | C37: Sec. 17 NIIF Pymes | D37: =SUMPRODUCT(('Libro Diario'!$A$10:$A$5000=$B$5)*('Libro Diario'!$E$10:$E$5000=1201005)*(YEAR('Libro Diario'!$C$10:$C$5000)=$D$5)*('Libro Diario'!$H$10:$H$5000))-SUMPRODUCT(('Libro Diario'!$A$10:$A$5000=$B$5)*('Libro Diario'!$E$10:$E$5000=1201005)*(YEAR('Libro Diario'!$C$10:$C$5000)=$D$5)*('Libro Diario'!$I$10:$I$5000)) -> 0
A38: (-) Dep. Acum. Remolques | C38: SII: según tabla de vida útil | D38: =SUMPRODUCT(('Libro Diario'!$A$10:$A$5000=$B$5)*('Libro Diario'!$E$10:$E$5000=1201006)*(YEAR('Libro Diario'!$C$10:$C$5000)=$D$5)*('Libro Diario'!$H$10:$H$5000))-SUMPRODUCT(('Libro Diario'!$A$10:$A$5000=$B$5)*('Libro Diario'!$E$10:$E$5000=1201006)*(YEAR('Libro Diario'!$C$10:$C$5000)=$D$5)*('Libro Diario'!$I$10:$I$5000)) -> 0
A39: Vehículos (Bruto) | C39: Sec. 17 NIIF Pymes | D39: =SUMPRODUCT(('Libro Diario'!$A$10:$A$5000=$B$5)*('Libro Diario'!$E$10:$E$5000=1201007)*(YEAR('Libro Diario'!$C$10:$C$5000)=$D$5)*('Libro Diario'!$H$10:$H$5000))-SUMPRODUCT(('Libro Diario'!$A$10:$A$5000=$B$5)*('Libro Diario'!$E$10:$E$5000=1201007)*(YEAR('Libro Diario'!$C$10:$C$5000)=$D$5)*('Libro Diario'!$I$10:$I$5000)) -> 0
A40: Vehículos en Leasing | C40: Sec. 20 NIIF Pymes | Activo arrendado | D40: =SUMPRODUCT(('Libro Diario'!$A$10:$A$5000=$B$5)*('Libro Diario'!$E$10:$E$5000=1201008)*(YEAR('Libro Diario'!$C$10:$C$5000)=$D$5)*('Libro Diario'!$H$10:$H$5000))-SUMPRODUCT(('Libro Diario'!$A$10:$A$5000=$B$5)*('Libro Diario'!$E$10:$E$5000=1201008)*(YEAR('Libro Diario'!$C$10:$C$5000)=$D$5)*('Libro Diario'!$I$10:$I$5000)) -> 0
A41: Dif. Valor Comercial Vehículos | C41: Ajuste valor libro vs. comercial | D41: =SUMPRODUCT(('Libro Diario'!$A$10:$A$5000=$B$5)*('Libro Diario'!$E$10:$E$5000=1201010)*(YEAR('Libro Diario'!$C$10:$C$5000)=$D$5)*('Libro Diario'!$H$10:$H$5000))-SUMPRODUCT(('Libro Diario'!$A$10:$A$5000=$B$5)*('Libro Diario'!$E$10:$E$5000=1201010)*(YEAR('Libro Diario'!$C$10:$C$5000)=$D$5)*('Libro Diario'!$I$10:$I$5000)) -> 0
A42: Grúas (Bruto) | C42: Sec. 17 NIIF Pymes | D42: =SUMPRODUCT(('Libro Diario'!$A$10:$A$5000=$B$5)*('Libro Diario'!$E$10:$E$5000=1202001)*(YEAR('Libro Diario'!$C$10:$C$5000)=$D$5)*('Libro Diario'!$H$10:$H$5000))-SUMPRODUCT(('Libro Diario'!$A$10:$A$5000=$B$5)*('Libro Diario'!$E$10:$E$5000=1202001)*(YEAR('Libro Diario'!$C$10:$C$5000)=$D$5)*('Libro Diario'!$I$10:$I$5000)) -> 0
A43: Tractores (Bruto) | C43: Sec. 17 NIIF Pymes | D43: =SUMPRODUCT(('Libro Diario'!$A$10:$A$5000=$B$5)*('Libro Diario'!$E$10:$E$5000=1202003)*(YEAR('Libro Diario'!$C$10:$C$5000)=$D$5)*('Libro Diario'!$H$10:$H$5000))-SUMPRODUCT(('Libro Diario'!$A$10:$A$5000=$B$5)*('Libro Diario'!$E$10:$E$5000=1202003)*(YEAR('Libro Diario'!$C$10:$C$5000)=$D$5)*('Libro Diario'!$I$10:$I$5000)) -> 0
A44: Máquinas y Equipos (Bruto) | C44: Sec. 17 NIIF Pymes | D44: =SUMPRODUCT(('Libro Diario'!$A$10:$A$5000=$B$5)*('Libro Diario'!$E$10:$E$5000=1202004)*(YEAR('Libro Diario'!$C$10:$C$5000)=$D$5)*('Libro Diario'!$H$10:$H$5000))-SUMPRODUCT(('Libro Diario'!$A$10:$A$5000=$B$5)*('Libro Diario'!$E$10:$E$5000=1202004)*(YEAR('Libro Diario'!$C$10:$C$5000)=$D$5)*('Libro Diario'!$I$10:$I$5000)) -> 0
A45: Equipos Computacionales (Bruto) | C45: SII: vida útil 6 años (Res. Ex. 43/2002) | D45: =SUMPRODUCT(('Libro Diario'!$A$10:$A$5000=$B$5)*('Libro Diario'!$E$10:$E$5000=1202005)*(YEAR('Libro Diario'!$C$10:$C$5000)=$D$5)*('Libro Diario'!$H$10:$H$5000))-SUMPRODUCT(('Libro Diario'!$A$10:$A$5000=$B$5)*('Libro Diario'!$E$10:$E$5000=1202005)*(YEAR('Libro Diario'!$C$10:$C$5000)=$D$5)*('Libro Diario'!$I$10:$I$5000)) -> 0
A46: (-) Dep. Acum. Máquinas/Equipos | C46: Sec. 17.18 NIIF Pymes | D46: =SUMPRODUCT(('Libro Diario'!$A$10:$A$5000=$B$5)*('Libro Diario'!$E$10:$E$5000=1202006)*(YEAR('Libro Diario'!$C$10:$C$5000)=$D$5)*('Libro Diario'!$H$10:$H$5000))-SUMPRODUCT(('Libro Diario'!$A$10:$A$5000=$B$5)*('Libro Diario'!$E$10:$E$5000=1202006)*(YEAR('Libro Diario'!$C$10:$C$5000)=$D$5)*('Libro Diario'!$I$10:$I$5000)) -> 0
A47: Maquinarias en Leasing (Bruto) | C47: Sec. 20 NIIF Pymes | D47: =SUMPRODUCT(('Libro Diario'!$A$10:$A$5000=$B$5)*('Libro Diario'!$E$10:$E$5000=1202007)*(YEAR('Libro Diario'!$C$10:$C$5000)=$D$5)*('Libro Diario'!$H$10:$H$5000))-SUMPRODUCT(('Libro Diario'!$A$10:$A$5000=$B$5)*('Libro Diario'!$E$10:$E$5000=1202007)*(YEAR('Libro Diario'!$C$10:$C$5000)=$D$5)*('Libro Diario'!$I$10:$I$5000)) -> 0
A48: Terrenos | C48: Sec. 17.15 NIIF Pymes | NO se deprecian | D48: =SUMPRODUCT(('Libro Diario'!$A$10:$A$5000=$B$5)*('Libro Diario'!$E$10:$E$5000=1203001)*(YEAR('Libro Diario'!$C$10:$C$5000)=$D$5)*('Libro Diario'!$H$10:$H$5000))-SUMPRODUCT(('Libro Diario'!$A$10:$A$5000=$B$5)*('Libro Diario'!$E$10:$E$5000=1203001)*(YEAR('Libro Diario'!$C$10:$C$5000)=$D$5)*('Libro Diario'!$I$10:$I$5000)) -> 0
A49: Construcciones (Bruto) | C49: Sec. 17 NIIF Pymes | D49: =SUMPRODUCT(('Libro Diario'!$A$10:$A$5000=$B$5)*('Libro Diario'!$E$10:$E$5000=1203002)*(YEAR('Libro Diario'!$C$10:$C$5000)=$D$5)*('Libro Diario'!$H$10:$H$5000))-SUMPRODUCT(('Libro Diario'!$A$10:$A$5000=$B$5)*('Libro Diario'!$E$10:$E$5000=1203002)*(YEAR('Libro Diario'!$C$10:$C$5000)=$D$5)*('Libro Diario'!$I$10:$I$5000)) -> 0
A50: (-) Dep. Acum. Construcciones | C50: SII: 40-100 años según material | D50: =SUMPRODUCT(('Libro Diario'!$A$10:$A$5000=$B$5)*('Libro Diario'!$E$10:$E$5000=1203003)*(YEAR('Libro Diario'!$C$10:$C$5000)=$D$5)*('Libro Diario'!$H$10:$H$5000))-SUMPRODUCT(('Libro Diario'!$A$10:$A$5000=$B$5)*('Libro Diario'!$E$10:$E$5000=1203003)*(YEAR('Libro Diario'!$C$10:$C$5000)=$D$5)*('Libro Diario'!$I$10:$I$5000)) -> 0
A51: Muebles, Útiles e Instalaciones | C51: Sec. 17 NIIF Pymes | D51: =SUMPRODUCT(('Libro Diario'!$A$10:$A$5000=$B$5)*('Libro Diario'!$E$10:$E$5000=1204001)*(YEAR('Libro Diario'!$C$10:$C$5000)=$D$5)*('Libro Diario'!$H$10:$H$5000))-SUMPRODUCT(('Libro Diario'!$A$10:$A$5000=$B$5)*('Libro Diario'!$E$10:$E$5000=1204001)*(YEAR('Libro Diario'!$C$10:$C$5000)=$D$5)*('Libro Diario'!$I$10:$I$5000)) -> 0
A52: (-) Dep. Acum. Muebles/Útiles | C52: Sec. 17.18 NIIF Pymes | D52: =SUMPRODUCT(('Libro Diario'!$A$10:$A$5000=$B$5)*('Libro Diario'!$E$10:$E$5000=1204009)*(YEAR('Libro Diario'!$C$10:$C$5000)=$D$5)*('Libro Diario'!$H$10:$H$5000))-SUMPRODUCT(('Libro Diario'!$A$10:$A$5000=$B$5)*('Libro Diario'!$E$10:$E$5000=1204009)*(YEAR('Libro Diario'!$C$10:$C$5000)=$D$5)*('Libro Diario'!$I$10:$I$5000)) -> 0
A53: Repuestos e Insumos (LP) | C53: Sec. 17 NIIF Pymes | Repuestos mayores | D53: =SUMPRODUCT(('Libro Diario'!$A$10:$A$5000=$B$5)*('Libro Diario'!$E$10:$E$5000=1205001)*(YEAR('Libro Diario'!$C$10:$C$5000)=$D$5)*('Libro Diario'!$H$10:$H$5000))-SUMPRODUCT(('Libro Diario'!$A$10:$A$5000=$B$5)*('Libro Diario'!$E$10:$E$5000=1205001)*(YEAR('Libro Diario'!$C$10:$C$5000)=$D$5)*('Libro Diario'!$I$10:$I$5000)) -> 0
A54: Intereses Diferidos LP | C54: Sec. 11 NIIF Pymes | D54: =SUMPRODUCT(('Libro Diario'!$A$10:$A$5000=$B$5)*('Libro Diario'!$E$10:$E$5000=1301001)*(YEAR('Libro Diario'!$C$10:$C$5000)=$D$5)*('Libro Diario'!$H$10:$H$5000))-SUMPRODUCT(('Libro Diario'!$A$10:$A$5000=$B$5)*('Libro Diario'!$E$10:$E$5000=1301001)*(YEAR('Libro Diario'!$C$10:$C$5000)=$D$5)*('Libro Diario'!$I$10:$I$5000)) -> 0
A55: Derechos Sociales Relacionadas | C55: Sec. 14-15 NIIF Pymes | Inversiones LP | D55: =SUMPRODUCT(('Libro Diario'!$A$10:$A$5000=$B$5)*('Libro Diario'!$E$10:$E$5000=1303001)*(YEAR('Libro Diario'!$C$10:$C$5000)=$D$5)*('Libro Diario'!$H$10:$H$5000))-SUMPRODUCT(('Libro Diario'!$A$10:$A$5000=$B$5)*('Libro Diario'!$E$10:$E$5000=1303001)*(YEAR('Libro Diario'!$C$10:$C$5000)=$D$5)*('Libro Diario'!$I$10:$I$5000)) -> 0
A56: TOTAL ACTIVO NO CORRIENTE | D56: =SUM(D33:D55) -> 0
A58: TOTAL ACTIVOS | D58: =D29+D56 -> 0
A60: P A S I V O S
A61: PASIVO CORRIENTE
A62: Sec. 4.7 NIIF Pymes: Pasivos a liquidar en ≤12 meses. Incluye IVA débito, retenciones, remuneraciones y cuotas corrientes de préstamos LP.
A63: Proveedores | C63: Sec. 11 NIIF Pymes | Cuentas por pagar | D63: =SUMPRODUCT(('Libro Diario'!$A$10:$A$5000=$B$5)*('Libro Diario'!$E$10:$E$5000=2102001)*(YEAR('Libro Diario'!$C$10:$C$5000)=$D$5)*('Libro Diario'!$H$10:$H$5000))-SUMPRODUCT(('Libro Diario'!$A$10:$A$5000=$B$5)*('Libro Diario'!$E$10:$E$5000=2102001)*(YEAR('Libro Diario'!$C$10:$C$5000)=$D$5)*('Libro Diario'!$I$10:$I$5000)) -> 0
A64: Documentos por Pagar — Vehículos | C64: Letras/pagarés CP | D64: =SUMPRODUCT(('Libro Diario'!$A$10:$A$5000=$B$5)*('Libro Diario'!$E$10:$E$5000=2103001)*(YEAR('Libro Diario'!$C$10:$C$5000)=$D$5)*('Libro Diario'!$H$10:$H$5000))-SUMPRODUCT(('Libro Diario'!$A$10:$A$5000=$B$5)*('Libro Diario'!$E$10:$E$5000=2103001)*(YEAR('Libro Diario'!$C$10:$C$5000)=$D$5)*('Libro Diario'!$I$10:$I$5000)) -> 0
A65: Acreedores Varios | C65: Deudas con terceros | D65: =SUMPRODUCT(('Libro Diario'!$A$10:$A$5000=$B$5)*('Libro Diario'!$E$10:$E$5000=2104001)*(YEAR('Libro Diario'!$C$10:$C$5000)=$D$5)*('Libro Diario'!$H$10:$H$5000))-SUMPRODUCT(('Libro Diario'!$A$10:$A$5000=$B$5)*('Libro Diario'!$E$10:$E$5000=2104001)*(YEAR('Libro Diario'!$C$10:$C$5000)=$D$5)*('Libro Diario'!$I$10:$I$5000)) -> 0
A66: IVA Débito Fiscal 19% | C66: Art. 15 D.L. 825 | Por pagar F-29 | D66: =SUMPRODUCT(('Libro Diario'!$A$10:$A$5000=$B$5)*('Libro Diario'!$E$10:$E$5000=2105101)*(YEAR('Libro Diario'!$C$10:$C$5000)=$D$5)*('Libro Diario'!$H$10:$H$5000))-SUMPRODUCT(('Libro Diario'!$A$10:$A$5000=$B$5)*('Libro Diario'!$E$10:$E$5000=2105101)*(YEAR('Libro Diario'!$C$10:$C$5000)=$D$5)*('Libro Diario'!$I$10:$I$5000)) -> 0
A67: IVA Débito No Retenido 11% | C67: Régimen retención parcial | D67: =SUMPRODUCT(('Libro Diario'!$A$10:$A$5000=$B$5)*('Libro Diario'!$E$10:$E$5000=2105102)*(YEAR('Libro Diario'!$C$10:$C$5000)=$D$5)*('Libro Diario'!$H$10:$H$5000))-SUMPRODUCT(('Libro Diario'!$A$10:$A$5000=$B$5)*('Libro Diario'!$E$10:$E$5000=2105102)*(YEAR('Libro Diario'!$C$10:$C$5000)=$D$5)*('Libro Diario'!$I$10:$I$5000)) -> 0
A68: IVA Retenido a Terceros | C68: Art. 3° D.L. 825 | Retención total | D68: =SUMPRODUCT(('Libro Diario'!$A$10:$A$5000=$B$5)*('Libro Diario'!$E$10:$E$5000=2105401)*(YEAR('Libro Diario'!$C$10:$C$5000)=$D$5)*('Libro Diario'!$H$10:$H$5000))-SUMPRODUCT(('Libro Diario'!$A$10:$A$5000=$B$5)*('Libro Diario'!$E$10:$E$5000=2105401)*(YEAR('Libro Diario'!$C$10:$C$5000)=$D$5)*('Libro Diario'!$I$10:$I$5000)) -> 0
A69: PPM por Pagar | C69: Art. 84 LIR | Pagos prov. mensuales | D69: =SUMPRODUCT(('Libro Diario'!$A$10:$A$5000=$B$5)*('Libro Diario'!$E$10:$E$5000=2105004)*(YEAR('Libro Diario'!$C$10:$C$5000)=$D$5)*('Libro Diario'!$H$10:$H$5000))-SUMPRODUCT(('Libro Diario'!$A$10:$A$5000=$B$5)*('Libro Diario'!$E$10:$E$5000=2105004)*(YEAR('Libro Diario'!$C$10:$C$5000)=$D$5)*('Libro Diario'!$I$10:$I$5000)) -> 0
A70: Provisión Impuesto Renta | C70: Art. 24 LIR | Impuesto 1ª Cat. estimado | D70: =SUMPRODUCT(('Libro Diario'!$A$10:$A$5000=$B$5)*('Libro Diario'!$E$10:$E$5000=2105005)*(YEAR('Libro Diario'!$C$10:$C$5000)=$D$5)*('Libro Diario'!$H$10:$H$5000))-SUMPRODUCT(('Libro Diario'!$A$10:$A$5000=$B$5)*('Libro Diario'!$E$10:$E$5000=2105005)*(YEAR('Libro Diario'!$C$10:$C$5000)=$D$5)*('Libro Diario'!$I$10:$I$5000)) -> 0
A71: Contribuciones por Pagar | C71: Art. 3° Ley 17.235 | D71: =SUMPRODUCT(('Libro Diario'!$A$10:$A$5000=$B$5)*('Libro Diario'!$E$10:$E$5000=2105006)*(YEAR('Libro Diario'!$C$10:$C$5000)=$D$5)*('Libro Diario'!$H$10:$H$5000))-SUMPRODUCT(('Libro Diario'!$A$10:$A$5000=$B$5)*('Libro Diario'!$E$10:$E$5000=2105006)*(YEAR('Libro Diario'!$C$10:$C$5000)=$D$5)*('Libro Diario'!$I$10:$I$5000)) -> 0
A72: Retención 2ª Categoría (10%) | C72: Art. 74 N°1 LIR | Honorarios | D72: =SUMPRODUCT(('Libro Diario'!$A$10:$A$5000=$B$5)*('Libro Diario'!$E$10:$E$5000=2105201)*(YEAR('Libro Diario'!$C$10:$C$5000)=$D$5)*('Libro Diario'!$H$10:$H$5000))-SUMPRODUCT(('Libro Diario'!$A$10:$A$5000=$B$5)*('Libro Diario'!$E$10:$E$5000=2105201)*(YEAR('Libro Diario'!$C$10:$C$5000)=$D$5)*('Libro Diario'!$I$10:$I$5000)) -> 0
A73: Sueldos por Pagar | C73: Art. 54 Cód. Trabajo | Devengo mensual | D73: =SUMPRODUCT(('Libro Diario'!$A$10:$A$5000=$B$5)*('Libro Diario'!$E$10:$E$5000=2106001)*(YEAR('Libro Diario'!$C$10:$C$5000)=$D$5)*('Libro Diario'!$H$10:$H$5000))-SUMPRODUCT(('Libro Diario'!$A$10:$A$5000=$B$5)*('Libro Diario'!$E$10:$E$5000=2106001)*(YEAR('Libro Diario'!$C$10:$C$5000)=$D$5)*('Libro Diario'!$I$10:$I$5000)) -> 0
A74: Honorarios por Pagar | C74: Art. 42 N°2 LIR | Ret. 14,5% (2025) / 15,25% (2026) — Ley 21.133 | D74: =SUMPRODUCT(('Libro Diario'!$A$10:$A$5000=$B$5)*('Libro Diario'!$E$10:$E$5000=2106002)*(YEAR('Libro Diario'!$C$10:$C$5000)=$D$5)*('Libro Diario'!$H$10:$H$5000))-SUMPRODUCT(('Libro Diario'!$A$10:$A$5000=$B$5)*('Libro Diario'!$E$10:$E$5000=2106002)*(YEAR('Libro Diario'!$C$10:$C$5000)=$D$5)*('Libro Diario'!$I$10:$I$5000)) -> 0
A75: Instituciones de Previsión | C75: Ley 17.322 | AFP/ISAPRE/AFC vence día 10 | D75: =SUMPRODUCT(('Libro Diario'!$A$10:$A$5000=$B$5)*('Libro Diario'!$E$10:$E$5000=2107001)*(YEAR('Libro Diario'!$C$10:$C$5000)=$D$5)*('Libro Diario'!$H$10:$H$5000))-SUMPRODUCT(('Libro Diario'!$A$10:$A$5000=$B$5)*('Libro Diario'!$E$10:$E$5000=2107001)*(YEAR('Libro Diario'!$C$10:$C$5000)=$D$5)*('Libro Diario'!$I$10:$I$5000)) -> 0
A76: Préstamos de Socios | C76: Sec. 22 NIIF Pymes | Partes relacionadas | D76: =SUMPRODUCT(('Libro Diario'!$A$10:$A$5000=$B$5)*('Libro Diario'!$E$10:$E$5000=2108001)*(YEAR('Libro Diario'!$C$10:$C$5000)=$D$5)*('Libro Diario'!$H$10:$H$5000))-SUMPRODUCT(('Libro Diario'!$A$10:$A$5000=$B$5)*('Libro Diario'!$E$10:$E$5000=2108001)*(YEAR('Libro Diario'!$C$10:$C$5000)=$D$5)*('Libro Diario'!$I$10:$I$5000)) -> 0
A77: Acreedores Varios (porción CP) | C77: Porción CP de deuda LP | D77: =SUMPRODUCT(('Libro Diario'!$A$10:$A$5000=$B$5)*('Libro Diario'!$E$10:$E$5000=2108003)*(YEAR('Libro Diario'!$C$10:$C$5000)=$D$5)*('Libro Diario'!$H$10:$H$5000))-SUMPRODUCT(('Libro Diario'!$A$10:$A$5000=$B$5)*('Libro Diario'!$E$10:$E$5000=2108003)*(YEAR('Libro Diario'!$C$10:$C$5000)=$D$5)*('Libro Diario'!$I$10:$I$5000)) -> 0
A78: TOTAL PASIVO CORRIENTE | D78: =SUM(D63:D77) -> 0
A80: PASIVO NO CORRIENTE
A81: Sec. 4.7 NIIF Pymes: Pasivos con vencimiento > 12 meses. Incluye préstamos bancarios LP, obligaciones leasing LP e impuestos diferidos.
A82: Préstamos Banco Largo Plazo | C82: Sec. 11 NIIF Pymes | Costo amortizado; TIE | D82: =SUMPRODUCT(('Libro Diario'!$A$10:$A$5000=$B$5)*('Libro Diario'!$E$10:$E$5000=2201001)*(YEAR('Libro Diario'!$C$10:$C$5000)=$D$5)*('Libro Diario'!$H$10:$H$5000))-SUMPRODUCT(('Libro Diario'!$A$10:$A$5000=$B$5)*('Libro Diario'!$E$10:$E$5000=2201001)*(YEAR('Libro Diario'!$C$10:$C$5000)=$D$5)*('Libro Diario'!$I$10:$I$5000)) -> 0
A83: Acreedores Leasing Largo Plazo | C83: Sec. 20 NIIF Pymes | Obligación arrend. financiero | D83: =SUMPRODUCT(('Libro Diario'!$A$10:$A$5000=$B$5)*('Libro Diario'!$E$10:$E$5000=2201002)*(YEAR('Libro Diario'!$C$10:$C$5000)=$D$5)*('Libro Diario'!$H$10:$H$5000))-SUMPRODUCT(('Libro Diario'!$A$10:$A$5000=$B$5)*('Libro Diario'!$E$10:$E$5000=2201002)*(YEAR('Libro Diario'!$C$10:$C$5000)=$D$5)*('Libro Diario'!$I$10:$I$5000)) -> 0
A84: TOTAL PASIVO NO CORRIENTE | D84: =SUM(D82:D83) -> 0
A86: TOTAL PASIVOS | D86: =D78+D84 -> 0
A88: P A T R I M O N I O
A89: Sec. 22 NIIF Pymes: Participación residual en activos deducidos pasivos. Art. 41 LIR: corrección monetaria capital por variación IPC. Para SpA y SRL: Capital, Reservas, Utilidades Retenidas y Resultado Ejercicio.
A90: Capital Pagado / Aportado | C90: Sec. 22.7 NIIF Pymes | Capital suscrito pagado | D90: =SUMPRODUCT(('Libro Diario'!$A$10:$A$5000=$B$5)*('Libro Diario'!$E$10:$E$5000=2301001)*(YEAR('Libro Diario'!$C$10:$C$5000)=$D$5)*('Libro Diario'!$H$10:$H$5000))-SUMPRODUCT(('Libro Diario'!$A$10:$A$5000=$B$5)*('Libro Diario'!$E$10:$E$5000=2301001)*(YEAR('Libro Diario'!$C$10:$C$5000)=$D$5)*('Libro Diario'!$I$10:$I$5000)) -> 0
A91: Revalorización Capital Propio | C91: Art. 41 N°1 LIR | Corrección monetaria IPC | D91: =SUMPRODUCT(('Libro Diario'!$A$10:$A$5000=$B$5)*('Libro Diario'!$E$10:$E$5000=2302001)*(YEAR('Libro Diario'!$C$10:$C$5000)=$D$5)*('Libro Diario'!$H$10:$H$5000))-SUMPRODUCT(('Libro Diario'!$A$10:$A$5000=$B$5)*('Libro Diario'!$E$10:$E$5000=2302001)*(YEAR('Libro Diario'!$C$10:$C$5000)=$D$5)*('Libro Diario'!$I$10:$I$5000)) -> 0
A92: Resultado Ejercicios Anteriores | C92: Sec. 3.23 NIIF Pymes | Utilidades retenidas | D92: =SUMPRODUCT(('Libro Diario'!$A$10:$A$5000=$B$5)*('Libro Diario'!$E$10:$E$5000=2302101)*(YEAR('Libro Diario'!$C$10:$C$5000)=$D$5)*('Libro Diario'!$H$10:$H$5000))-SUMPRODUCT(('Libro Diario'!$A$10:$A$5000=$B$5)*('Libro Diario'!$E$10:$E$5000=2302101)*(YEAR('Libro Diario'!$C$10:$C$5000)=$D$5)*('Libro Diario'!$I$10:$I$5000)) -> 0
A93: Resultado del Ejercicio | C93: Calculado desde Estado de Resultados del mismo período | D93: =IFERROR(INDEX('Estado Resultados'!$D:$D,MATCH("Resultado Neto del Ejercicio",'Estado Resultados'!$A:$A,0)),0) -> 0
A94: TOTAL PATRIMONIO | D94: =SUM(D90:D93) -> 0
A96: TOTAL PASIVOS + PATRIMONIO | D96: =D86+D94 -> 0
A98: VERIFICACIÓN: Activos = Pasivos + Patrimonio → | D98: =IF(ABS(D58-D96)<1,"✓ BALANCE CUADRADO","✗ DIFERENCIA: $"&TEXT(ABS(D58-D96),"#,##0")) -> ✓ BALANCE CUADRADO
A100: 📋 NOTA TRIBUTARIA SII: Impuesto 1ª Categoría 2024: 27% régimen general (SA/SpA) | 12,5% Pro-Pyme 2025-2027 (Ley 21.755, art. 14D LIR). Sube a 15% en 2028. Corrección Monetaria (Art. 41 LIR): activos monetarios se ajustan por variación del IPC del ejercicio. Depreciación Acelerada: 1/3 vida útil (Art. 31 N°5 LIR). Depreciación Instantánea Pro-Pyme: 100% en 1 ejercicio para bienes nuevos (Art. 31 N°5 bis LIR, Ley 21.210). Todas las empresas deben presentar el Balance de 8 Columnas como Anexo al F-22. Plazo: 30 de junio.

Sheet Estado Resultados
A1: ESTADO DE RESULTADOS — ESTADO DE RESULTADO INTEGRAL
A3: ⚖ NORMATIVA: Sección 5 NIIF para Pymes — Estado del Resultado Integral. Puede presentarse como un único estado o dividido en Estado de Resultados + Estado de Otro Resultado Integral (ORI). Para Pymes chilenas se acepta el formato de función del gasto (por naturaleza o por función). SII exige presentar el Resultado del Ejercicio antes y después de impuesto en la Declaración de Renta F-22. Tasa Impuesto 1ª Categoría 2024: 27% (régimen general) | 12,5% Pro-Pyme 2025-2027 (Ley 21.755, Art. 14D LIR). Los gastos no aceptados tributariamente deben agregarse al resultado tributario (Art. 33 LIR).
A5: Cliente: | B5: CLI001 | C5: Período (Año): | D5: 2025
A7: =IFERROR(INDEX(Clientes!$C$4:$C$200,MATCH(B5,Clientes!$A$4:$A$200,0)),"[Seleccione un cliente]")&" — Estado de Resultados Enero a Diciembre "&TEXT(D5,"0") -> ← Ingrese aquí su primer cliente — Estado de Resultados Enero a Diciembre 2025
A8: CONCEPTO | D8: MONTO ($)
A9: I. INGRESOS DE ACTIVIDADES ORDINARIAS
A10: Sec. 23 NIIF Pymes: Se reconocen cuando es probable que fluyan beneficios económicos y el ingreso puede medirse confiablemente. Incluir solo ingresos devengados (no recaudados). Neto de devoluciones y descuentos.
A11: Ventas de Bienes / Productos | C11: Sec. 23.10 NIIF Pymes | Neto de devoluciones | D11: =SUMPRODUCT(('Libro Diario'!$A$10:$A$5000=$B$5)*('Libro Diario'!$E$10:$E$5000=4101001)*(YEAR('Libro Diario'!$C$10:$C$5000)=$D$5)*('Libro Diario'!$I$10:$I$5000))-SUMPRODUCT(('Libro Diario'!$A$10:$A$5000=$B$5)*('Libro Diario'!$E$10:$E$5000=4101001)*(YEAR('Libro Diario'!$C$10:$C$5000)=$D$5)*('Libro Diario'!$H$10:$H$5000)) -> 0
A12: Ingresos por Servicios | C12: Sec. 23.14 NIIF Pymes | % de terminación | D12: =SUMPRODUCT(('Libro Diario'!$A$10:$A$5000=$B$5)*('Libro Diario'!$E$10:$E$5000=4101002)*(YEAR('Libro Diario'!$C$10:$C$5000)=$D$5)*('Libro Diario'!$I$10:$I$5000))-SUMPRODUCT(('Libro Diario'!$A$10:$A$5000=$B$5)*('Libro Diario'!$E$10:$E$5000=4101002)*(YEAR('Libro Diario'!$C$10:$C$5000)=$D$5)*('Libro Diario'!$H$10:$H$5000)) -> 0
A13: Ingresos por Comisiones | C13: Sec. 23.29 NIIF Pymes | D13: =SUMPRODUCT(('Libro Diario'!$A$10:$A$5000=$B$5)*('Libro Diario'!$E$10:$E$5000=4101003)*(YEAR('Libro Diario'!$C$10:$C$5000)=$D$5)*('Libro Diario'!$I$10:$I$5000))-SUMPRODUCT(('Libro Diario'!$A$10:$A$5000=$B$5)*('Libro Diario'!$E$10:$E$5000=4101003)*(YEAR('Libro Diario'!$C$10:$C$5000)=$D$5)*('Libro Diario'!$H$10:$H$5000)) -> 0
A14: Otros Ingresos Operacionales | C14: Ingresos accesorios a la actividad principal | D14: =SUMPRODUCT(('Libro Diario'!$A$10:$A$5000=$B$5)*('Libro Diario'!$E$10:$E$5000=4201001)*(YEAR('Libro Diario'!$C$10:$C$5000)=$D$5)*('Libro Diario'!$I$10:$I$5000))-SUMPRODUCT(('Libro Diario'!$A$10:$A$5000=$B$5)*('Libro Diario'!$E$10:$E$5000=4201001)*(YEAR('Libro Diario'!$C$10:$C$5000)=$D$5)*('Libro Diario'!$H$10:$H$5000)) -> 0
A15: Ingresos Financieros | C15: Sec. 11 NIIF Pymes | Intereses devengados | D15: =SUMPRODUCT(('Libro Diario'!$A$10:$A$5000=$B$5)*('Libro Diario'!$E$10:$E$5000=4201101)*(YEAR('Libro Diario'!$C$10:$C$5000)=$D$5)*('Libro Diario'!$I$10:$I$5000))-SUMPRODUCT(('Libro Diario'!$A$10:$A$5000=$B$5)*('Libro Diario'!$E$10:$E$5000=4201101)*(YEAR('Libro Diario'!$C$10:$C$5000)=$D$5)*('Libro Diario'!$H$10:$H$5000)) -> 0
A16: Otros Ingresos | C16: Art. 17 LIR: verificar si constituye renta | D16: =SUMPRODUCT(('Libro Diario'!$A$10:$A$5000=$B$5)*('Libro Diario'!$E$10:$E$5000=4201102)*(YEAR('Libro Diario'!$C$10:$C$5000)=$D$5)*('Libro Diario'!$I$10:$I$5000))-SUMPRODUCT(('Libro Diario'!$A$10:$A$5000=$B$5)*('Libro Diario'!$E$10:$E$5000=4201102)*(YEAR('Libro Diario'!$C$10:$C$5000)=$D$5)*('Libro Diario'!$H$10:$H$5000)) -> 0
A17: TOTAL INGRESOS | D17: =SUM(D11:D16) -> 0
A19: II. COSTO DE VENTAS / COSTO DE SERVICIOS
A20: Sec. 13 NIIF Pymes: Los inventarios se valorizan al costo o VNR (el menor). Métodos permitidos: FIFO o Costo Promedio Ponderado (LIFO no permitido). El costo incluye todos los costos directos de adquisición/transformación.
A21: Costo de Ventas / Mercaderías | C21: Sec. 13.19 NIIF Pymes | Costo promedio o FIFO | D21: =SUMPRODUCT(('Libro Diario'!$A$10:$A$5000=$B$5)*('Libro Diario'!$E$10:$E$5000=3101001)*(YEAR('Libro Diario'!$C$10:$C$5000)=$D$5)*('Libro Diario'!$H$10:$H$5000))-SUMPRODUCT(('Libro Diario'!$A$10:$A$5000=$B$5)*('Libro Diario'!$E$10:$E$5000=3101001)*(YEAR('Libro Diario'!$C$10:$C$5000)=$D$5)*('Libro Diario'!$I$10:$I$5000)) -> 0
A22: Gastos de Administración | C22: Sec. 5.5 NIIF Pymes | Por función o naturaleza | D22: =SUMPRODUCT(('Libro Diario'!$A$10:$A$5000=$B$5)*('Libro Diario'!$E$10:$E$5000=3101002)*(YEAR('Libro Diario'!$C$10:$C$5000)=$D$5)*('Libro Diario'!$H$10:$H$5000))-SUMPRODUCT(('Libro Diario'!$A$10:$A$5000=$B$5)*('Libro Diario'!$E$10:$E$5000=3101002)*(YEAR('Libro Diario'!$C$10:$C$5000)=$D$5)*('Libro Diario'!$I$10:$I$5000)) -> 0
A23: Combustibles y Mant. Vehículos | C23: Deducible Art. 31 LIR si relacionado al giro | D23: =SUMPRODUCT(('Libro Diario'!$A$10:$A$5000=$B$5)*('Libro Diario'!$E$10:$E$5000=3101003)*(YEAR('Libro Diario'!$C$10:$C$5000)=$D$5)*('Libro Diario'!$H$10:$H$5000))-SUMPRODUCT(('Libro Diario'!$A$10:$A$5000=$B$5)*('Libro Diario'!$E$10:$E$5000=3101003)*(YEAR('Libro Diario'!$C$10:$C$5000)=$D$5)*('Libro Diario'!$I$10:$I$5000)) -> 0
A24: TOTAL COSTO DE VENTAS | D24: =SUM(D21:D23) -> 0
A26: GANANCIA BRUTA (Ingresos − Costo de Ventas) | D26: =D17-D24 -> 0
A27: Ganancia Bruta = Ingresos Ordinarios − Costo de Ventas. Indicador clave de la eficiencia del proceso productivo o comercial (Margen Bruto = Ganancia Bruta / Ingresos).
A29: III. GASTOS DE OPERACIÓN
A30: Art. 31 LIR: Son deducibles los gastos necesarios para producir la renta, siempre que no hayan sido rebajados como costo. Deben estar devengados en el ejercicio, ser de giro y acreditarse documentalmente. Gastos rechazados quedan afectos al Art. 21 LIR (impuesto único 40%).
A31: Remuneraciones del Personal | C31: Art. 31 N°6 LIR | Deducibles; Cód. Trabajo | D31: =SUMPRODUCT(('Libro Diario'!$A$10:$A$5000=$B$5)*('Libro Diario'!$E$10:$E$5000=3103001)*(YEAR('Libro Diario'!$C$10:$C$5000)=$D$5)*('Libro Diario'!$H$10:$H$5000))-SUMPRODUCT(('Libro Diario'!$A$10:$A$5000=$B$5)*('Libro Diario'!$E$10:$E$5000=3103001)*(YEAR('Libro Diario'!$C$10:$C$5000)=$D$5)*('Libro Diario'!$I$10:$I$5000)) -> 0
A32: Asesorías y Honorarios Prof. | C32: Art. 42 N°2 LIR | Retención 14,5% (2025), 15,25% (2026) — Ley 21.133 | D32: =SUMPRODUCT(('Libro Diario'!$A$10:$A$5000=$B$5)*('Libro Diario'!$E$10:$E$5000=3103002)*(YEAR('Libro Diario'!$C$10:$C$5000)=$D$5)*('Libro Diario'!$H$10:$H$5000))-SUMPRODUCT(('Libro Diario'!$A$10:$A$5000=$B$5)*('Libro Diario'!$E$10:$E$5000=3103002)*(YEAR('Libro Diario'!$C$10:$C$5000)=$D$5)*('Libro Diario'!$I$10:$I$5000)) -> 0
A33: Gastos Varios | C33: Art. 31 LIR | Deben ser necesarios para el giro | D33: =SUMPRODUCT(('Libro Diario'!$A$10:$A$5000=$B$5)*('Libro Diario'!$E$10:$E$5000=3103003)*(YEAR('Libro Diario'!$C$10:$C$5000)=$D$5)*('Libro Diario'!$H$10:$H$5000))-SUMPRODUCT(('Libro Diario'!$A$10:$A$5000=$B$5)*('Libro Diario'!$E$10:$E$5000=3103003)*(YEAR('Libro Diario'!$C$10:$C$5000)=$D$5)*('Libro Diario'!$I$10:$I$5000)) -> 0
A34: Fletes y Combustibles | C34: Art. 31 LIR | Relacionados al giro | D34: =SUMPRODUCT(('Libro Diario'!$A$10:$A$5000=$B$5)*('Libro Diario'!$E$10:$E$5000=3103004)*(YEAR('Libro Diario'!$C$10:$C$5000)=$D$5)*('Libro Diario'!$H$10:$H$5000))-SUMPRODUCT(('Libro Diario'!$A$10:$A$5000=$B$5)*('Libro Diario'!$E$10:$E$5000=3103004)*(YEAR('Libro Diario'!$C$10:$C$5000)=$D$5)*('Libro Diario'!$I$10:$I$5000)) -> 0
A35: Gastos en Repuestos | C35: Art. 31 LIR | Mantenimiento activo fijo | D35: =SUMPRODUCT(('Libro Diario'!$A$10:$A$5000=$B$5)*('Libro Diario'!$E$10:$E$5000=3103005)*(YEAR('Libro Diario'!$C$10:$C$5000)=$D$5)*('Libro Diario'!$H$10:$H$5000))-SUMPRODUCT(('Libro Diario'!$A$10:$A$5000=$B$5)*('Libro Diario'!$E$10:$E$5000=3103005)*(YEAR('Libro Diario'!$C$10:$C$5000)=$D$5)*('Libro Diario'!$I$10:$I$5000)) -> 0
A36: Gastos Básicos | C36: Art. 31 LIR | Electricidad, agua, internet | D36: =SUMPRODUCT(('Libro Diario'!$A$10:$A$5000=$B$5)*('Libro Diario'!$E$10:$E$5000=3103006)*(YEAR('Libro Diario'!$C$10:$C$5000)=$D$5)*('Libro Diario'!$H$10:$H$5000))-SUMPRODUCT(('Libro Diario'!$A$10:$A$5000=$B$5)*('Libro Diario'!$E$10:$E$5000=3103006)*(YEAR('Libro Diario'!$C$10:$C$5000)=$D$5)*('Libro Diario'!$I$10:$I$5000)) -> 0
A37: Gastos de Administración | C37: Art. 31 LIR | Arriendo oficina, útiles | D37: =SUMPRODUCT(('Libro Diario'!$A$10:$A$5000=$B$5)*('Libro Diario'!$E$10:$E$5000=3103007)*(YEAR('Libro Diario'!$C$10:$C$5000)=$D$5)*('Libro Diario'!$H$10:$H$5000))-SUMPRODUCT(('Libro Diario'!$A$10:$A$5000=$B$5)*('Libro Diario'!$E$10:$E$5000=3103007)*(YEAR('Libro Diario'!$C$10:$C$5000)=$D$5)*('Libro Diario'!$I$10:$I$5000)) -> 0
A38: Publicidad | C38: Art. 31 LIR | Vinculada al giro | D38: =SUMPRODUCT(('Libro Diario'!$A$10:$A$5000=$B$5)*('Libro Diario'!$E$10:$E$5000=3103008)*(YEAR('Libro Diario'!$C$10:$C$5000)=$D$5)*('Libro Diario'!$H$10:$H$5000))-SUMPRODUCT(('Libro Diario'!$A$10:$A$5000=$B$5)*('Libro Diario'!$E$10:$E$5000=3103008)*(YEAR('Libro Diario'!$C$10:$C$5000)=$D$5)*('Libro Diario'!$I$10:$I$5000)) -> 0
A39: Arriendos | C39: Art. 31 N°1 LIR | Arriendo bienes del giro | D39: =SUMPRODUCT(('Libro Diario'!$A$10:$A$5000=$B$5)*('Libro Diario'!$E$10:$E$5000=3103009)*(YEAR('Libro Diario'!$C$10:$C$5000)=$D$5)*('Libro Diario'!$H$10:$H$5000))-SUMPRODUCT(('Libro Diario'!$A$10:$A$5000=$B$5)*('Libro Diario'!$E$10:$E$5000=3103009)*(YEAR('Libro Diario'!$C$10:$C$5000)=$D$5)*('Libro Diario'!$I$10:$I$5000)) -> 0
A40: Seguros | C40: Art. 31 N°3 LIR | Seguros relacionados al giro | D40: =SUMPRODUCT(('Libro Diario'!$A$10:$A$5000=$B$5)*('Libro Diario'!$E$10:$E$5000=3103010)*(YEAR('Libro Diario'!$C$10:$C$5000)=$D$5)*('Libro Diario'!$H$10:$H$5000))-SUMPRODUCT(('Libro Diario'!$A$10:$A$5000=$B$5)*('Libro Diario'!$E$10:$E$5000=3103010)*(YEAR('Libro Diario'!$C$10:$C$5000)=$D$5)*('Libro Diario'!$I$10:$I$5000)) -> 0
A41: Capacitación y Perfeccionamiento | C41: Ley 19.518 SENCE | Hasta 1% planilla remuneraciones | D41: =SUMPRODUCT(('Libro Diario'!$A$10:$A$5000=$B$5)*('Libro Diario'!$E$10:$E$5000=3102002)*(YEAR('Libro Diario'!$C$10:$C$5000)=$D$5)*('Libro Diario'!$H$10:$H$5000))-SUMPRODUCT(('Libro Diario'!$A$10:$A$5000=$B$5)*('Libro Diario'!$E$10:$E$5000=3102002)*(YEAR('Libro Diario'!$C$10:$C$5000)=$D$5)*('Libro Diario'!$I$10:$I$5000)) -> 0
A42: Gastos Financieros (Intereses) | C42: Art. 31 N°1 LIR | Intereses devengados | D42: =SUMPRODUCT(('Libro Diario'!$A$10:$A$5000=$B$5)*('Libro Diario'!$E$10:$E$5000=3201001)*(YEAR('Libro Diario'!$C$10:$C$5000)=$D$5)*('Libro Diario'!$H$10:$H$5000))-SUMPRODUCT(('Libro Diario'!$A$10:$A$5000=$B$5)*('Libro Diario'!$E$10:$E$5000=3201001)*(YEAR('Libro Diario'!$C$10:$C$5000)=$D$5)*('Libro Diario'!$I$10:$I$5000)) -> 0
A43: TOTAL GASTOS OPERACIONALES | D43: =SUM(D31:D42) -> 0
A45: RESULTADO OPERACIONAL (EBIT) | D45: =D26-D43 -> 0
A47: IV. DEPRECIACIÓN Y AMORTIZACIÓN
A48: Sec. 17.18 NIIF Pymes: Depreciar durante la vida útil económica del activo. SII permite Depreciación Acelerada (1/3 vida útil) para Pymes — Art. 31 N°5 bis LIR. La depreciación financiera y tributaria pueden diferir, generando impuestos diferidos.
A49: Depreciación Vehículos | C49: Art. 31 N°5 LIR | 7 años vida útil normal | D49: =SUMPRODUCT(('Libro Diario'!$A$10:$A$5000=$B$5)*('Libro Diario'!$E$10:$E$5000=3201401)*(YEAR('Libro Diario'!$C$10:$C$5000)=$D$5)*('Libro Diario'!$H$10:$H$5000))-SUMPRODUCT(('Libro Diario'!$A$10:$A$5000=$B$5)*('Libro Diario'!$E$10:$E$5000=3201401)*(YEAR('Libro Diario'!$C$10:$C$5000)=$D$5)*('Libro Diario'!$I$10:$I$5000)) -> 0
A50: Depreciación (General) | C50: Art. 31 N°5 bis LIR | Acelerada Pymes | D50: =SUMPRODUCT(('Libro Diario'!$A$10:$A$5000=$B$5)*('Libro Diario'!$E$10:$E$5000=3201402)*(YEAR('Libro Diario'!$C$10:$C$5000)=$D$5)*('Libro Diario'!$H$10:$H$5000))-SUMPRODUCT(('Libro Diario'!$A$10:$A$5000=$B$5)*('Libro Diario'!$E$10:$E$5000=3201402)*(YEAR('Libro Diario'!$C$10:$C$5000)=$D$5)*('Libro Diario'!$I$10:$I$5000)) -> 0
A51: Depreciación Carros y Remolques | C51: Sec. 17.18 NIIF Pymes | Componente a componente | D51: =SUMPRODUCT(('Libro Diario'!$A$10:$A$5000=$B$5)*('Libro Diario'!$E$10:$E$5000=3201403)*(YEAR('Libro Diario'!$C$10:$C$5000)=$D$5)*('Libro Diario'!$H$10:$H$5000))-SUMPRODUCT(('Libro Diario'!$A$10:$A$5000=$B$5)*('Libro Diario'!$E$10:$E$5000=3201403)*(YEAR('Libro Diario'!$C$10:$C$5000)=$D$5)*('Libro Diario'!$I$10:$I$5000)) -> 0
A52: Depreciación Muebles/Instalaciones | C52: SII: según Res. Ex. 43/2002 | D52: =SUMPRODUCT(('Libro Diario'!$A$10:$A$5000=$B$5)*('Libro Diario'!$E$10:$E$5000=3201404)*(YEAR('Libro Diario'!$C$10:$C$5000)=$D$5)*('Libro Diario'!$H$10:$H$5000))-SUMPRODUCT(('Libro Diario'!$A$10:$A$5000=$B$5)*('Libro Diario'!$E$10:$E$5000=3201404)*(YEAR('Libro Diario'!$C$10:$C$5000)=$D$5)*('Libro Diario'!$I$10:$I$5000)) -> 0
A53: TOTAL DEPRECIACIÓN Y AMORTIZACIÓN | D53: =SUM(D49:D52) -> 0
A55: V. OTROS INGRESOS / GASTOS NO OPERACIONALES
A56: Sec. 5.5 NIIF Pymes: Ingresos y gastos no relacionados con la actividad principal. Incluye utilidad/pérdida en venta de activos fijos, corrección monetaria y diferencias de cambio. Art. 41 LIR: Corrección Monetaria ajusta activos y pasivos por variación IPC.
A57: Corrección Monetaria (Pérdida) | C57: Art. 41 LIR | Ajuste por variación IPC | D57: =SUMPRODUCT(('Libro Diario'!$A$10:$A$5000=$B$5)*('Libro Diario'!$E$10:$E$5000=3201501)*(YEAR('Libro Diario'!$C$10:$C$5000)=$D$5)*('Libro Diario'!$H$10:$H$5000))-SUMPRODUCT(('Libro Diario'!$A$10:$A$5000=$B$5)*('Libro Diario'!$E$10:$E$5000=3201501)*(YEAR('Libro Diario'!$C$10:$C$5000)=$D$5)*('Libro Diario'!$I$10:$I$5000)) -> 0
A58: Impuesto Municipal (Patentes) | C58: Art. 31 N°2 LIR | Patentes municipales | D58: =SUMPRODUCT(('Libro Diario'!$A$10:$A$5000=$B$5)*('Libro Diario'!$E$10:$E$5000=3201101)*(YEAR('Libro Diario'!$C$10:$C$5000)=$D$5)*('Libro Diario'!$H$10:$H$5000))-SUMPRODUCT(('Libro Diario'!$A$10:$A$5000=$B$5)*('Libro Diario'!$E$10:$E$5000=3201101)*(YEAR('Libro Diario'!$C$10:$C$5000)=$D$5)*('Libro Diario'!$I$10:$I$5000)) -> 0
A59: Patentes y Derechos Municipales | C59: Ley 18.695 | Deducibles como gasto | D59: =SUMPRODUCT(('Libro Diario'!$A$10:$A$5000=$B$5)*('Libro Diario'!$E$10:$E$5000=3201103)*(YEAR('Libro Diario'!$C$10:$C$5000)=$D$5)*('Libro Diario'!$H$10:$H$5000))-SUMPRODUCT(('Libro Diario'!$A$10:$A$5000=$B$5)*('Libro Diario'!$E$10:$E$5000=3201103)*(YEAR('Libro Diario'!$C$10:$C$5000)=$D$5)*('Libro Diario'!$I$10:$I$5000)) -> 0
A60: TOTAL OTROS EGRESOS NO OPERACIONALES | D60: =SUM(D57:D59) -> 0
A62: RESULTADO ANTES DE IMPUESTO A LA RENTA | D62: =D45-D53-D60 -> 0
A63: Resultado Financiero antes de aplicar el Impuesto de Primera Categoría. Base para calcular la RLI tributaria (con ajustes Arts. 29-33 LIR).
A65: VI. IMPUESTO A LA RENTA (1ª CATEGORÍA)
A66: Art. 20 LIR: Impuesto de 1ª Categoría. Tasa 2024: 27% régimen general (SA/SpA) | 12,5% Pro-Pyme 2025-2027 (Ley 21.755, Art. 14D). Sube a 15% en 2028, 25% desde 2029. Sobre la Renta Líquida Imponible (RLI) que puede diferir del resultado financiero. Créditos: PPM, Art. 33 bis, Diesel, SENCE.
A67: Impuesto de 1ª Categoría Estimado | C67: Tasa 27% régimen general | 12,5% Pro-Pyme 2025-2027 (Ley 21.755, Art. 14D LIR) | D67: =IF(D62>0,D62*0.27,0) -> 0
A68: TOTAL IMPUESTO A LA RENTA | D68: =D67 -> 0
A70: Resultado Neto del Ejercicio | D70: =D62-D68 -> 0
A71: El Resultado Neto del Ejercicio se traspasa al Balance General como componente del Patrimonio. Si es positivo: Utilidad del Ejercicio. Si es negativo: Pérdida del Ejercicio (Art. 31 N°3 LIR: arrastre de pérdidas). Margen Neto = Resultado Neto / Ingresos. EBITDA = EBIT + Depreciación + Amortización.
A73: INDICADORES FINANCIEROS CLAVE
A74: Margen Bruto (%) | B74: Ganancia Bruta / Ingresos × 100 | D74: =IFERROR(D26/D17*100,0) -> 0
A75: Margen Operacional (%) | B75: EBIT / Ingresos × 100 | D75: =IFERROR(D45/D17*100,0) -> 0
A76: Margen Neto (%) | B76: Resultado Neto / Ingresos × 100 | D76: =IFERROR(D70/D17*100,0) -> 0
A77: EBITDA ($) | B77: EBIT + Depreciación y Amortización | D77: =D45+D53 -> 0
A78: Carga Tributaria Efectiva (%) | B78: Impuesto / RAI × 100 | D78: =IFERROR(D68/D62*100,0) -> 0
A80: 📋 NOTAS TRIBUTARIAS ADICIONALES (Chile 2024): (1) Gastos Rechazados Art. 21 LIR: afectos a impuesto único 40% si son de SA/SpA o global complementario si son empresas individuales. (2) Corrección Monetaria Art. 41 LIR: ajusta activos y pasivos no monetarios por variación del IPC del ejercicio (acumulado anual). (3) RAI (Registro de Rentas Afectas a Impuesto): las utilidades generadas quedan en el Registro de Rentas Afectas a Impuesto (RAI). (4) Pérdidas tributarias: se arrastra indefinidamente según Art. 31 N°3 LIR (reforma Ley 21.210). (5) Pro-Pyme (Art. 14D): empresas con ingresos ≤ 75.000 UF pueden acogerse a régimen simplificado con tasa 25%.

Sheet Indicadores
A1: REPORTE DE GESTIÓN — INDICADORES FINANCIEROS CLAVE
A3: ⚖ NORMATIVA: Indicadores calculados conforme a NIIF para Pymes (Colegio de Contadores de Chile, BT N°82) y estándares de análisis financiero CORFO/SERCOTEC para MYPE. Los umbrales referenciales son orientativos — varían según sector e industria. Fuente benchmarks: SBIF/CMF, Banco Central Chile, SERCOTEC.
A5: Cliente: | B5: CLI001 | D5: Año: | E5: 2025 | F5: ← Cambie cliente y año para actualizar todos los indicadores
A7: INDICADOR | B7: VALOR | C7: 🚦 | D7: INTERPRETACIÓN | E7: REFERENCIA NORMATIVA | F7: ✅ BUENO | G7: ⚠ PRECAUCIÓN
A8: 💧 INDICADORES DE LIQUIDEZ — ¿Puede pagar sus deudas a corto plazo?
A9: Miden la capacidad de la empresa para cubrir sus obligaciones de corto plazo con sus activos líquidos. Críticos para la sobrevivencia de una MYPE.
A10: Razón Corriente (Liquidez General) | B10: =IFERROR($J$100/$J$101,0) -> 0 | C10: =IF(B10>=1.5,"🟢",IF(B10>=1,"🟡","🔴")) -> 🔴 | D10: Activo Cte / Pasivo Cte. Mide cuántos $ de activo cte. respaldan cada $ de deuda cte. | E10: SERCOTEC: ≥1.5 saludable | Banco Central Chile ref. | F10: ≥ 1.5 | G10: 1.0 – 1.4
A11: Razón Ácida (Prueba Ácida) | B11: =IFERROR(($J$100-$J$107)/$J$101,0) -> 0 | C11: =IF(B11>=1,"🟢",IF(B11>=0.7,"🟡","🔴")) -> 🔴 | D11: (Activo Cte − Inventarios) / Pasivo Cte. Excluye inventarios por ser menos líquidos. | E11: Ref. NIIF Pymes Sec. 7 | Estándar MYPE Chile | F11: ≥ 1.0 | G11: 0.7 – 0.9
A12: Razón de Efectivo (Tesorería Inmediata) | B12: =IFERROR($J$106/$J$101,0) -> 0 | C12: =IF(B12>=0.3,"🟢",IF(B12>=0.1,"🟡","🔴")) -> 🔴 | D12: Caja y Bancos / Pasivo Cte. Capacidad de pago con dinero disponible hoy. | E12: Umbral mínimo recomendado SERCOTEC Pymes | F12: ≥ 0.3 | G12: 0.1 – 0.29
A14: 🏦 INDICADORES DE DEUDA Y APALANCAMIENTO — ¿Qué tanto debe la empresa?
A15: Prioridad máxima para MYPE: el sobre-endeudamiento es la principal causa de quiebra en pequeñas empresas chilenas (fuente: SBIF/CMF). Art. 2° Ley 20.720 de Insolvencia.
A16: Razón de Endeudamiento (Leverage) | B16: =IFERROR($J$102/($J$102+$J$103),0) -> 0 | C16: =IF(B16<=0.5,"🟢",IF(B16<=0.7,"🟡","🔴")) -> 🟢 | D16: Pasivo Total / (Pasivo + Patrimonio). Proporción de activos financiados con deuda. >70% es zona de riesgo. | E16: CMF Chile | Ley 20.720 Insolvencia | Ref. SBIF | F16: ≤ 0.50 | G16: 0.51 – 0.70
A17: Razón Deuda / Patrimonio (D/E Ratio) | B17: =IFERROR($J$102/$J$103,0) -> 0 | C17: =IF(B17<=1,"🟢",IF(B17<=2,"🟡","🔴")) -> 🟢 | D17: Pasivo Total / Patrimonio. Por cada $1 de capital propio, cuánto se debe. >2x es señal de alerta MYPE. | E17: Estándar internacional | CORFO criterio crédito | F17: ≤ 1.0 | G17: 1.01 – 2.0
A18: Cobertura de Intereses (ICR) | B18: =IFERROR(($J$104-$J$105)/$J$108,0) -> 0 | C18: =IF(B18>=3,"🟢",IF(B18>=1.5,"🟡","🔴")) -> 🔴 | D18: EBIT / Gastos Financieros. Veces que la utilidad operacional cubre los intereses. <1.5x: riesgo de insolvencia. | E18: Ref. Bancos en Chile | Covenants financieros CORFO | F18: ≥ 3.0 | G18: 1.5 – 2.9
A19: Endeudamiento Corriente | B19: =IFERROR($J$101/$J$102,0) -> 0 | C19: =IF(B19<=0.5,"🟢",IF(B19<=0.7,"🟡","🔴")) -> 🟢 | D19: Pasivo Cte / Pasivo Total. Proporción de deuda que vence en <12 meses. Alta concentración = riesgo de liquidez. | E19: Ref. análisis crédito bancario Chile | F19: ≤ 0.50 | G19: 0.51 – 0.70
A21: 📈 INDICADORES DE RENTABILIDAD — ¿Es rentable el negocio?
A22: Miden la eficiencia del negocio para generar utilidades. Un ROE > costo de capital indica creación de valor. SERCOTEC exige rentabilidad positiva para créditos MYPE.
A23: ROE (Retorno sobre Patrimonio) | B23: =IFERROR(($J$104-$J$105)/$J$103,0) -> 0 | C23: =IF(B23>=0.15,"🟢",IF(B23>=0.05,"🟡","🔴")) -> 🔴 | D23: Utilidad Neta / Patrimonio. Por cada $1 de capital propio, cuánta ganancia genera. Mínimo 15% recomendado. | E23: Ref. SERCOTEC | Benchmark MYPE sector comercio | F23: ≥ 15% | G23: 5% – 14%
A24: ROA (Retorno sobre Activos) | B24: =IFERROR(($J$104-$J$105)/($J$102+$J$103),0) -> 0 | C24: =IF(B24>=0.08,"🟢",IF(B24>=0.03,"🟡","🔴")) -> 🔴 | D24: Utilidad Neta / Activo Total. Eficiencia para generar utilidades con todos los activos disponibles. | E24: Ref. análisis sectorial Banco Central Chile | F24: ≥ 8% | G24: 3% – 7%
A25: Margen Bruto | B25: =IFERROR(($J$104-SUMPRODUCT(('Libro Diario'!$A$10:$A$5000=B5)*('Libro Diario'!$E$10:$E$5000=3101001)*(YEAR('Libro Diario'!$C$10:$C$5000)=E5)*('Libro Diario'!$H$10:$H$5000)))/$J$104,0) -> 0 | C25: =IF(B25>=0.3,"🟢",IF(B25>=0.15,"🟡","🔴")) -> 🔴 | D25: (Ingresos − Costo Ventas) / Ingresos. Porcentaje que queda para cubrir gastos operacionales. | E25: Ref. sectorial CORFO | Comercio MYPE Chile ≥30% | F25: ≥ 30% | G25: 15% – 29%
A26: Margen Operacional (EBIT%) | B26: =IFERROR(($J$104-$J$105)/$J$104,0) -> 0 | C26: =IF(B26>=0.1,"🟢",IF(B26>=0.03,"🟡","🔴")) -> 🔴 | D26: (Ingresos − Gastos Oper.) / Ingresos. Eficiencia operacional antes de financiamiento e impuestos. | E26: Ref. CMF Chile | MYPE objetivo ≥10% | F26: ≥ 10% | G26: 3% – 9%
A28: ⚙️ INDICADORES DE ACTIVIDAD Y EFICIENCIA — ¿Qué tan bien usa sus recursos?
A29: Miden la velocidad con que la empresa convierte sus activos en ventas o efectivo. Relevantes para gestionar el capital de trabajo de la MYPE.
A30: Rotación de Inventarios (veces/año) | B30: =IFERROR(SUMPRODUCT(('Libro Diario'!$A$10:$A$5000=B5)*('Libro Diario'!$E$10:$E$5000=3101001)*(YEAR('Libro Diario'!$C$10:$C$5000)=E5)*('Libro Diario'!$H$10:$H$5000))/$J$107,0) -> 0 | C30: =IF(B30>=6,"🟢",IF(B30>=3,"🟡","🔴")) -> 🔴 | D30: Costo Ventas / Inventario Promedio. Veces que el inventario se renueva en el año. Baja rotación = mercadería estancada. | E30: Ref. SERCOTEC | Comercio minorista Chile ≥6x | F30: ≥ 6 veces | G30: 3 – 5 veces
A31: Días de Cobro (PMC) | B31: =IFERROR(SUMPRODUCT(('Libro Diario'!$A$10:$A$5000=B5)*('Libro Diario'!$E$10:$E$5000=1104001)*(YEAR('Libro Diario'!$C$10:$C$5000)=E5)*('Libro Diario'!$H$10:$H$5000))/($J$104/365),0) -> 0 | C31: =IF(B31<=30,"🟢",IF(B31<=60,"🟡","🔴")) -> 🟢 | D31: CxC / (Ingresos/365). Días promedio que tarda en cobrar. >60 días compromete el flujo de caja. | E31: Ref. análisis MYPE BancoEstado | SERCOTEC | F31: ≤ 30 días | G31: 31 – 60 días
A32: Días de Pago (PMP) | B32: =IFERROR(SUMPRODUCT(('Libro Diario'!$A$10:$A$5000=B5)*('Libro Diario'!$E$10:$E$5000=2102001)*(YEAR('Libro Diario'!$C$10:$C$5000)=E5)*('Libro Diario'!$I$10:$I$5000))/(SUMPRODUCT(('Libro Diario'!$A$10:$A$5000=B5)*('Libro Diario'!$E$10:$E$5000=3101001)*(YEAR('Libro Diario'!$C$10:$C$5000)=E5)*('Libro Diario'!$H$10:$H$5000))/365),0) -> 0 | C32: =IF(B32>=30,"🟢",IF(B32>=45,"🟡","🔴")) -> 🔴 | D32: CxP / (Costo Ventas/365). Días que la empresa tarda en pagar a proveedores. Negociar >30 días mejora liquidez. | E32: Ref. comercio Chile | Ley 20.416 Pymes | F32: ≥ 30 días | G32: 15 – 29 días
A34: 🏁 DIAGNÓSTICO GENERAL
A35: =IFERROR("Estado general del cliente " & B5 & " (" & E5 & "): " & TEXT(COUNTIF(C8:C33,"🟢"),"0") & " indicadores SANOS | " & TEXT(COUNTIF(C8:C33,"🟡"),"0") & " en PRECAUCIÓN | " & TEXT(COUNTIF(C8:C33,"🔴"),"0") & " en RIESGO","Sin datos") -> Estado general del cliente CLI001 (2025): 4 indicadores SANOS | 0 en PRECAUCIÓN | 10 en RIESGO
J100: =((SUMPRODUCT(('Libro Diario'!$A$10:$A$5000=B5)*('Libro Diario'!$E$10:$E$5000=1101001)*(YEAR('Libro Diario'!$C$10:$C$5000)=E5)*('Libro Diario'!$H$10:$H$5000))-SUMPRODUCT(('Libro Diario'!$A$10:$A$5000=B5)*('Libro Diario'!$E$10:$E$5000=1101001)*(YEAR('Libro Diario'!$C$10:$C$5000)=E5)*('Libro Diario'!$I$10:$I$5000)))+(SUMPRODUCT(('Libro Diario'!$A$10:$A$5000=B5)*('Libro Diario'!$E$10:$E$5000=1101002)*(YEAR('Libro Diario'!$C$10:$C$5000)=E5)*('Libro Diario'!$H$10:$H$5000))-SUMPRODUCT(('Libro Diario'!$A$10:$A$5000=B5)*('Libro Diario'!$E$10:$E$5000=1101002)*(YEAR('Libro Diario'!$C$10:$C$5000)=E5)*('Libro Diario'!$I$10:$I$5000)))+(SUMPRODUCT(('Libro Diario'!$A$10:$A$5000=B5)*('Libro Diario'!$E$10:$E$5000=1104001)*(YEAR('Libro Diario'!$C$10:$C$5000)=E5)*('Libro Diario'!$H$10:$H$5000))-SUMPRODUCT(('Libro Diario'!$A$10:$A$5000=B5)*('Libro Diario'!$E$10:$E$5000=1104001)*(YEAR('Libro Diario'!$C$10:$C$5000)=E5)*('Libro Diario'!$I$10:$I$5000)))+(SUMPRODUCT(('Libro Diario'!$A$10:$A$5000=B5)*('Libro Diario'!$E$10:$E$5000=1107101)*(YEAR('Libro Diario'!$C$10:$C$5000)=E5)*('Libro Diario'!$H$10:$H$5000))-SUMPRODUCT(('Libro Diario'!$A$10:$A$5000=B5)*('Libro Diario'!$E$10:$E$5000=1107101)*(YEAR('Libro Diario'!$C$10:$C$5000)=E5)*('Libro Diario'!$I$10:$I$5000)))+(SUMPRODUCT(('Libro Diario'!$A$10:$A$5000=B5)*('Libro Diario'!$E$10:$E$5000=1107201)*(YEAR('Libro Diario'!$C$10:$C$5000)=E5)*('Libro Diario'!$H$10:$H$5000))-SUMPRODUCT(('Libro Diario'!$A$10:$A$5000=B5)*('Libro Diario'!$E$10:$E$5000=1107201)*(YEAR('Libro Diario'!$C$10:$C$5000)=E5)*('Libro Diario'!$I$10:$I$5000)))+(SUMPRODUCT(('Libro Diario'!$A$10:$A$5000=B5)*('Libro Diario'!$E$10:$E$5000=1108001)*(YEAR('Libro Diario'!$C$10:$C$5000)=E5)*('Libro Diario'!$H$10:$H$5000))-SUMPRODUCT(('Libro Diario'!$A$10:$A$5000=B5)*('Libro Diario'!$E$10:$E$5000=1108001)*(YEAR('Libro Diario'!$C$10:$C$5000)=E5)*('Libro Diario'!$I$10:$I$5000)))+(SUMPRODUCT(('Libro Diario'!$A$10:$A$5000=B5)*('Libro Diario'!$E$10:$E$5000=1108002)*(YEAR('Libro Diario'!$C$10:$C$5000)=E5)*('Libro Diario'!$H$10:$H$5000))-SUMPRODUCT(('Libro Diario'!$A$10:$A$5000=B5)*('Libro Diario'!$E$10:$E$5000=1108002)*(YEAR('Libro Diario'!$C$10:$C$5000)=E5)*('Libro Diario'!$I$10:$I$5000)))) -> 0 | K100: =((SUMPRODUCT(('Libro Diario'!$A$10:$A$5000=B5)*('Libro Diario'!$E$10:$E$5000=2102001)*(YEAR('Libro Diario'!$C$10:$C$5000)=E5)*('Libro Diario'!$I$10:$I$5000))-SUMPRODUCT(('Libro Diario'!$A$10:$A$5000=B5)*('Libro Diario'!$E$10:$E$5000=2102001)*(YEAR('Libro Diario'!$C$10:$C$5000)=E5)*('Libro Diario'!$H$10:$H$5000)))+(SUMPRODUCT(('Libro Diario'!$A$10:$A$5000=B5)*('Libro Diario'!$E$10:$E$5000=2103001)*(YEAR('Libro Diario'!$C$10:$C$5000)=E5)*('Libro Diario'!$I$10:$I$5000))-SUMPRODUCT(('Libro Diario'!$A$10:$A$5000=B5)*('Libro Diario'!$E$10:$E$5000=2103001)*(YEAR('Libro Diario'!$C$10:$C$5000)=E5)*('Libro Diario'!$H$10:$H$5000)))+(SUMPRODUCT(('Libro Diario'!$A$10:$A$5000=B5)*('Libro Diario'!$E$10:$E$5000=2104001)*(YEAR('Libro Diario'!$C$10:$C$5000)=E5)*('Libro Diario'!$I$10:$I$5000))-SUMPRODUCT(('Libro Diario'!$A$10:$A$5000=B5)*('Libro Diario'!$E$10:$E$5000=2104001)*(YEAR('Libro Diario'!$C$10:$C$5000)=E5)*('Libro Diario'!$H$10:$H$5000)))+(SUMPRODUCT(('Libro Diario'!$A$10:$A$5000=B5)*('Libro Diario'!$E$10:$E$5000=2105101)*(YEAR('Libro Diario'!$C$10:$C$5000)=E5)*('Libro Diario'!$I$10:$I$5000))-SUMPRODUCT(('Libro Diario'!$A$10:$A$5000=B5)*('Libro Diario'!$E$10:$E$5000=2105101)*(YEAR('Libro Diario'!$C$10:$C$5000)=E5)*('Libro Diario'!$H$10:$H$5000)))+(SUMPRODUCT(('Libro Diario'!$A$10:$A$5000=B5)*('Libro Diario'!$E$10:$E$5000=2105005)*(YEAR('Libro Diario'!$C$10:$C$5000)=E5)*('Libro Diario'!$I$10:$I$5000))-SUMPRODUCT(('Libro Diario'!$A$10:$A$5000=B5)*('Libro Diario'!$E$10:$E$5000=2105005)*(YEAR('Libro Diario'!$C$10:$C$5000)=E5)*('Libro Diario'!$H$10:$H$5000)))+(SUMPRODUCT(('Libro Diario'!$A$10:$A$5000=B5)*('Libro Diario'!$E$10:$E$5000=2106001)*(YEAR('Libro Diario'!$C$10:$C$5000)=E5)*('Libro Diario'!$I$10:$I$5000))-SUMPRODUCT(('Libro Diario'!$A$10:$A$5000=B5)*('Libro Diario'!$E$10:$E$5000=2106001)*(YEAR('Libro Diario'!$C$10:$C$5000)=E5)*('Libro Diario'!$H$10:$H$5000)))+(SUMPRODUCT(('Libro Diario'!$A$10:$A$5000=B5)*('Libro Diario'!$E$10:$E$5000=2107001)*(YEAR('Libro Diario'!$C$10:$C$5000)=E5)*('Libro Diario'!$I$10:$I$5000))-SUMPRODUCT(('Libro Diario'!$A$10:$A$5000=B5)*('Libro Diario'!$E$10:$E$5000=2107001)*(YEAR('Libro Diario'!$C$10:$C$5000)=E5)*('Libro Diario'!$H$10:$H$5000)))+(SUMPRODUCT(('Libro Diario'!$A$10:$A$5000=B5)*('Libro Diario'!$E$10:$E$5000=2108001)*(YEAR('Libro Diario'!$C$10:$C$5000)=E5)*('Libro Diario'!$I$10:$I$5000))-SUMPRODUCT(('Libro Diario'!$A$10:$A$5000=B5)*('Libro Diario'!$E$10:$E$5000=2108001)*(YEAR('Libro Diario'!$C$10:$C$5000)=E5)*('Libro Diario'!$H$10:$H$5000)))) -> 0 | L100: =((SUMPRODUCT(('Libro Diario'!$A$10:$A$5000=B5)*('Libro Diario'!$E$10:$E$5000=2102001)*(YEAR('Libro Diario'!$C$10:$C$5000)=E5)*('Libro Diario'!$I$10:$I$5000))-SUMPRODUCT(('Libro Diario'!$A$10:$A$5000=B5)*('Libro Diario'!$E$10:$E$5000=2102001)*(YEAR('Libro Diario'!$C$10:$C$5000)=E5)*('Libro Diario'!$H$10:$H$5000)))+(SUMPRODUCT(('Libro Diario'!$A$10:$A$5000=B5)*('Libro Diario'!$E$10:$E$5000=2103001)*(YEAR('Libro Diario'!$C$10:$C$5000)=E5)*('Libro Diario'!$I$10:$I$5000))-SUMPRODUCT(('Libro Diario'!$A$10:$A$5000=B5)*('Libro Diario'!$E$10:$E$5000=2103001)*(YEAR('Libro Diario'!$C$10:$C$5000)=E5)*('Libro Diario'!$H$10:$H$5000)))+(SUMPRODUCT(('Libro Diario'!$A$10:$A$5000=B5)*('Libro Diario'!$E$10:$E$5000=2104001)*(YEAR('Libro Diario'!$C$10:$C$5000)=E5)*('Libro Diario'!$I$10:$I$5000))-SUMPRODUCT(('Libro Diario'!$A$10:$A$5000=B5)*('Libro Diario'!$E$10:$E$5000=2104001)*(YEAR('Libro Diario'!$C$10:$C$5000)=E5)*('Libro Diario'!$H$10:$H$5000)))+(SUMPRODUCT(('Libro Diario'!$A$10:$A$5000=B5)*('Libro Diario'!$E$10:$E$5000=2105101)*(YEAR('Libro Diario'!$C$10:$C$5000)=E5)*('Libro Diario'!$I$10:$I$5000))-SUMPRODUCT(('Libro Diario'!$A$10:$A$5000=B5)*('Libro Diario'!$E$10:$E$5000=2105101)*(YEAR('Libro Diario'!$C$10:$C$5000)=E5)*('Libro Diario'!$H$10:$H$5000)))+(SUMPRODUCT(('Libro Diario'!$A$10:$A$5000=B5)*('Libro Diario'!$E$10:$E$5000=2105005)*(YEAR('Libro Diario'!$C$10:$C$5000)=E5)*('Libro Diario'!$I$10:$I$5000))-SUMPRODUCT(('Libro Diario'!$A$10:$A$5000=B5)*('Libro Diario'!$E$10:$E$5000=2105005)*(YEAR('Libro Diario'!$C$10:$C$5000)=E5)*('Libro Diario'!$H$10:$H$5000)))+(SUMPRODUCT(('Libro Diario'!$A$10:$A$5000=B5)*('Libro Diario'!$E$10:$E$5000=2106001)*(YEAR('Libro Diario'!$C$10:$C$5000)=E5)*('Libro Diario'!$I$10:$I$5000))-SUMPRODUCT(('Libro Diario'!$A$10:$A$5000=B5)*('Libro Diario'!$E$10:$E$5000=2106001)*(YEAR('Libro Diario'!$C$10:$C$5000)=E5)*('Libro Diario'!$H$10:$H$5000)))+(SUMPRODUCT(('Libro Diario'!$A$10:$A$5000=B5)*('Libro Diario'!$E$10:$E$5000=2107001)*(YEAR('Libro Diario'!$C$10:$C$5000)=E5)*('Libro Diario'!$I$10:$I$5000))-SUMPRODUCT(('Libro Diario'!$A$10:$A$5000=B5)*('Libro Diario'!$E$10:$E$5000=2107001)*(YEAR('Libro Diario'!$C$10:$C$5000)=E5)*('Libro Diario'!$H$10:$H$5000)))+(SUMPRODUCT(('Libro Diario'!$A$10:$A$5000=B5)*('Libro Diario'!$E$10:$E$5000=2108001)*(YEAR('Libro Diario'!$C$10:$C$5000)=E5)*('Libro Diario'!$I$10:$I$5000))-SUMPRODUCT(('Libro Diario'!$A$10:$A$5000=B5)*('Libro Diario'!$E$10:$E$5000=2108001)*(YEAR('Libro Diario'!$C$10:$C$5000)=E5)*('Libro Diario'!$H$10:$H$5000)))+(SUMPRODUCT(('Libro Diario'!$A$10:$A$5000=B5)*('Libro Diario'!$E$10:$E$5000=2201001)*(YEAR('Libro Diario'!$C$10:$C$5000)=E5)*('Libro Diario'!$I$10:$I$5000))-SUMPRODUCT(('Libro Diario'!$A$10:$A$5000=B5)*('Libro Diario'!$E$10:$E$5000=2201001)*(YEAR('Libro Diario'!$C$10:$C$5000)=E5)*('Libro Diario'!$H$10:$H$5000)))+(SUMPRODUCT(('Libro Diario'!$A$10:$A$5000=B5)*('Libro Diario'!$E$10:$E$5000=2201002)*(YEAR('Libro Diario'!$C$10:$C$5000)=E5)*('Libro Diario'!$I$10:$I$5000))-SUMPRODUCT(('Libro Diario'!$A$10:$A$5000=B5)*('Libro Diario'!$E$10:$E$5000=2201002)*(YEAR('Libro Diario'!$C$10:$C$5000)=E5)*('Libro Diario'!$H$10:$H$5000)))) -> 0 | M100: =((SUMPRODUCT(('Libro Diario'!$A$10:$A$5000=B5)*('Libro Diario'!$E$10:$E$5000=2301001)*(YEAR('Libro Diario'!$C$10:$C$5000)=E5)*('Libro Diario'!$I$10:$I$5000))-SUMPRODUCT(('Libro Diario'!$A$10:$A$5000=B5)*('Libro Diario'!$E$10:$E$5000=2301001)*(YEAR('Libro Diario'!$C$10:$C$5000)=E5)*('Libro Diario'!$H$10:$H$5000)))+(SUMPRODUCT(('Libro Diario'!$A$10:$A$5000=B5)*('Libro Diario'!$E$10:$E$5000=2302001)*(YEAR('Libro Diario'!$C$10:$C$5000)=E5)*('Libro Diario'!$I$10:$I$5000))-SUMPRODUCT(('Libro Diario'!$A$10:$A$5000=B5)*('Libro Diario'!$E$10:$E$5000=2302001)*(YEAR('Libro Diario'!$C$10:$C$5000)=E5)*('Libro Diario'!$H$10:$H$5000)))+(SUMPRODUCT(('Libro Diario'!$A$10:$A$5000=B5)*('Libro Diario'!$E$10:$E$5000=2302101)*(YEAR('Libro Diario'!$C$10:$C$5000)=E5)*('Libro Diario'!$I$10:$I$5000))-SUMPRODUCT(('Libro Diario'!$A$10:$A$5000=B5)*('Libro Diario'!$E$10:$E$5000=2302101)*(YEAR('Libro Diario'!$C$10:$C$5000)=E5)*('Libro Diario'!$H$10:$H$5000)))) -> 0 | N100: =((SUMPRODUCT(('Libro Diario'!$A$10:$A$5000=B5)*('Libro Diario'!$E$10:$E$5000=4101001)*(YEAR('Libro Diario'!$C$10:$C$5000)=E5)*('Libro Diario'!$I$10:$I$5000))-SUMPRODUCT(('Libro Diario'!$A$10:$A$5000=B5)*('Libro Diario'!$E$10:$E$5000=4101001)*(YEAR('Libro Diario'!$C$10:$C$5000)=E5)*('Libro Diario'!$H$10:$H$5000)))+(SUMPRODUCT(('Libro Diario'!$A$10:$A$5000=B5)*('Libro Diario'!$E$10:$E$5000=4101002)*(YEAR('Libro Diario'!$C$10:$C$5000)=E5)*('Libro Diario'!$I$10:$I$5000))-SUMPRODUCT(('Libro Diario'!$A$10:$A$5000=B5)*('Libro Diario'!$E$10:$E$5000=4101002)*(YEAR('Libro Diario'!$C$10:$C$5000)=E5)*('Libro Diario'!$H$10:$H$5000)))+(SUMPRODUCT(('Libro Diario'!$A$10:$A$5000=B5)*('Libro Diario'!$E$10:$E$5000=4101003)*(YEAR('Libro Diario'!$C$10:$C$5000)=E5)*('Libro Diario'!$I$10:$I$5000))-SUMPRODUCT(('Libro Diario'!$A$10:$A$5000=B5)*('Libro Diario'!$E$10:$E$5000=4101003)*(YEAR('Libro Diario'!$C$10:$C$5000)=E5)*('Libro Diario'!$H$10:$H$5000)))+(SUMPRODUCT(('Libro Diario'!$A$10:$A$5000=B5)*('Libro Diario'!$E$10:$E$5000=4201001)*(YEAR('Libro Diario'!$C$10:$C$5000)=E5)*('Libro Diario'!$I$10:$I$5000))-SUMPRODUCT(('Libro Diario'!$A$10:$A$5000=B5)*('Libro Diario'!$E$10:$E$5000=4201001)*(YEAR('Libro Diario'!$C$10:$C$5000)=E5)*('Libro Diario'!$H$10:$H$5000)))+(SUMPRODUCT(('Libro Diario'!$A$10:$A$5000=B5)*('Libro Diario'!$E$10:$E$5000=4201101)*(YEAR('Libro Diario'!$C$10:$C$5000)=E5)*('Libro Diario'!$I$10:$I$5000))-SUMPRODUCT(('Libro Diario'!$A$10:$A$5000=B5)*('Libro Diario'!$E$10:$E$5000=4201101)*(YEAR('Libro Diario'!$C$10:$C$5000)=E5)*('Libro Diario'!$H$10:$H$5000)))+(SUMPRODUCT(('Libro Diario'!$A$10:$A$5000=B5)*('Libro Diario'!$E$10:$E$5000=4201102)*(YEAR('Libro Diario'!$C$10:$C$5000)=E5)*('Libro Diario'!$I$10:$I$5000))-SUMPRODUCT(('Libro Diario'!$A$10:$A$5000=B5)*('Libro Diario'!$E$10:$E$5000=4201102)*(YEAR('Libro Diario'!$C$10:$C$5000)=E5)*('Libro Diario'!$H$10:$H$5000)))) -> 0 | O100: =((SUMPRODUCT(('Libro Diario'!$A$10:$A$5000=B5)*('Libro Diario'!$E$10:$E$5000=3101001)*(YEAR('Libro Diario'!$C$10:$C$5000)=E5)*('Libro Diario'!$H$10:$H$5000))-SUMPRODUCT(('Libro Diario'!$A$10:$A$5000=B5)*('Libro Diario'!$E$10:$E$5000=3101001)*(YEAR('Libro Diario'!$C$10:$C$5000)=E5)*('Libro Diario'!$I$10:$I$5000)))+(SUMPRODUCT(('Libro Diario'!$A$10:$A$5000=B5)*('Libro Diario'!$E$10:$E$5000=3103001)*(YEAR('Libro Diario'!$C$10:$C$5000)=E5)*('Libro Diario'!$H$10:$H$5000))-SUMPRODUCT(('Libro Diario'!$A$10:$A$5000=B5)*('Libro Diario'!$E$10:$E$5000=3103001)*(YEAR('Libro Diario'!$C$10:$C$5000)=E5)*('Libro Diario'!$I$10:$I$5000)))+(SUMPRODUCT(('Libro Diario'!$A$10:$A$5000=B5)*('Libro Diario'!$E$10:$E$5000=3103002)*(YEAR('Libro Diario'!$C$10:$C$5000)=E5)*('Libro Diario'!$H$10:$H$5000))-SUMPRODUCT(('Libro Diario'!$A$10:$A$5000=B5)*('Libro Diario'!$E$10:$E$5000=3103002)*(YEAR('Libro Diario'!$C$10:$C$5000)=E5)*('Libro Diario'!$I$10:$I$5000)))+(SUMPRODUCT(('Libro Diario'!$A$10:$A$5000=B5)*('Libro Diario'!$E$10:$E$5000=3103003)*(YEAR('Libro Diario'!$C$10:$C$5000)=E5)*('Libro Diario'!$H$10:$H$5000))-SUMPRODUCT(('Libro Diario'!$A$10:$A$5000=B5)*('Libro Diario'!$E$10:$E$5000=3103003)*(YEAR('Libro Diario'!$C$10:$C$5000)=E5)*('Libro Diario'!$I$10:$I$5000)))+(SUMPRODUCT(('Libro Diario'!$A$10:$A$5000=B5)*('Libro Diario'!$E$10:$E$5000=3103007)*(YEAR('Libro Diario'!$C$10:$C$5000)=E5)*('Libro Diario'!$H$10:$H$5000))-SUMPRODUCT(('Libro Diario'!$A$10:$A$5000=B5)*('Libro Diario'!$E$10:$E$5000=3103007)*(YEAR('Libro Diario'!$C$10:$C$5000)=E5)*('Libro Diario'!$I$10:$I$5000)))+(SUMPRODUCT(('Libro Diario'!$A$10:$A$5000=B5)*('Libro Diario'!$E$10:$E$5000=3201001)*(YEAR('Libro Diario'!$C$10:$C$5000)=E5)*('Libro Diario'!$H$10:$H$5000))-SUMPRODUCT(('Libro Diario'!$A$10:$A$5000=B5)*('Libro Diario'!$E$10:$E$5000=3201001)*(YEAR('Libro Diario'!$C$10:$C$5000)=E5)*('Libro Diario'!$I$10:$I$5000)))+(SUMPRODUCT(('Libro Diario'!$A$10:$A$5000=B5)*('Libro Diario'!$E$10:$E$5000=3201401)*(YEAR('Libro Diario'!$C$10:$C$5000)=E5)*('Libro Diario'!$H$10:$H$5000))-SUMPRODUCT(('Libro Diario'!$A$10:$A$5000=B5)*('Libro Diario'!$E$10:$E$5000=3201401)*(YEAR('Libro Diario'!$C$10:$C$5000)=E5)*('Libro Diario'!$I$10:$I$5000)))+(SUMPRODUCT(('Libro Diario'!$A$10:$A$5000=B5)*('Libro Diario'!$E$10:$E$5000=3201402)*(YEAR('Libro Diario'!$C$10:$C$5000)=E5)*('Libro Diario'!$H$10:$H$5000))-SUMPRODUCT(('Libro Diario'!$A$10:$A$5000=B5)*('Libro Diario'!$E$10:$E$5000=3201402)*(YEAR('Libro Diario'!$C$10:$C$5000)=E5)*('Libro Diario'!$I$10:$I$5000)))) -> 0 | P100: =((SUMPRODUCT(('Libro Diario'!$A$10:$A$5000=B5)*('Libro Diario'!$E$10:$E$5000=1101001)*(YEAR('Libro Diario'!$C$10:$C$5000)=E5)*('Libro Diario'!$H$10:$H$5000))-SUMPRODUCT(('Libro Diario'!$A$10:$A$5000=B5)*('Libro Diario'!$E$10:$E$5000=1101001)*(YEAR('Libro Diario'!$C$10:$C$5000)=E5)*('Libro Diario'!$I$10:$I$5000)))+(SUMPRODUCT(('Libro Diario'!$A$10:$A$5000=B5)*('Libro Diario'!$E$10:$E$5000=1101002)*(YEAR('Libro Diario'!$C$10:$C$5000)=E5)*('Libro Diario'!$H$10:$H$5000))-SUMPRODUCT(('Libro Diario'!$A$10:$A$5000=B5)*('Libro Diario'!$E$10:$E$5000=1101002)*(YEAR('Libro Diario'!$C$10:$C$5000)=E5)*('Libro Diario'!$I$10:$I$5000)))) -> 0 | Q100: =((SUMPRODUCT(('Libro Diario'!$A$10:$A$5000=B5)*('Libro Diario'!$E$10:$E$5000=1108001)*(YEAR('Libro Diario'!$C$10:$C$5000)=E5)*('Libro Diario'!$H$10:$H$5000))-SUMPRODUCT(('Libro Diario'!$A$10:$A$5000=B5)*('Libro Diario'!$E$10:$E$5000=1108001)*(YEAR('Libro Diario'!$C$10:$C$5000)=E5)*('Libro Diario'!$I$10:$I$5000)))+(SUMPRODUCT(('Libro Diario'!$A$10:$A$5000=B5)*('Libro Diario'!$E$10:$E$5000=1108002)*(YEAR('Libro Diario'!$C$10:$C$5000)=E5)*('Libro Diario'!$H$10:$H$5000))-SUMPRODUCT(('Libro Diario'!$A$10:$A$5000=B5)*('Libro Diario'!$E$10:$E$5000=1108002)*(YEAR('Libro Diario'!$C$10:$C$5000)=E5)*('Libro Diario'!$I$10:$I$5000)))) -> 0 | R100: =SUMPRODUCT(('Libro Diario'!$A$10:$A$5000=B5)*('Libro Diario'!$E$10:$E$5000=3201001)*(YEAR('Libro Diario'!$C$10:$C$5000)=E5)*('Libro Diario'!$H$10:$H$5000)) -> 0

Sheet Flujo de Caja
B1: REPORTE DE FLUJO DE CAJA Y SOSTENIBILIDAD | MYPE Chile
B2: Ref.: NIC 7 (IAS 7) Flujo de Efectivo · NIIF PYMES Sección 7 · Ley 20.720 Insolvencia · SERCOTEC · Circular SII N°13/2021
B3: FILTROS DE CONSULTA
B4: Cliente: | C4: Seleccione el cliente del listado | F4: Año: | G4: Año anterior: | H4: Ingrese año en F5
B5: CLI001 | F5: 2025 | G5: =$F$5-1 -> 2024
B7: CONCEPTO | C7: AÑO ACTUAL ($) | D7: AÑO ANTERIOR ($) | F7: VAR. ($) | G7: VAR. % | H7: NOTA
B8: 1. FLUJO DE ACTIVIDADES OPERACIONALES (Método Indirecto — NIIF Pymes Sec. 7.7)
B9: Resultado Neto del Ejercicio | C9: =(SUMPRODUCT(('Libro Diario'!$A$10:$A$5000=$B$5)*('Libro Diario'!$E$10:$E$5000=4101001)*(YEAR('Libro Diario'!$C$10:$C$5000)=$F$5)*('Libro Diario'!$I$10:$I$5000))+SUMPRODUCT(('Libro Diario'!$A$10:$A$5000=$B$5)*('Libro Diario'!$E$10:$E$5000=4101002)*(YEAR('Libro Diario'!$C$10:$C$5000)=$F$5)*('Libro Diario'!$I$10:$I$5000))+SUMPRODUCT(('Libro Diario'!$A$10:$A$5000=$B$5)*('Libro Diario'!$E$10:$E$5000=4101003)*(YEAR('Libro Diario'!$C$10:$C$5000)=$F$5)*('Libro Diario'!$I$10:$I$5000))+SUMPRODUCT(('Libro Diario'!$A$10:$A$5000=$B$5)*('Libro Diario'!$E$10:$E$5000=4201001)*(YEAR('Libro Diario'!$C$10:$C$5000)=$F$5)*('Libro Diario'!$I$10:$I$5000)))-(SUMPRODUCT(('Libro Diario'!$A$10:$A$5000=$B$5)*('Libro Diario'!$E$10:$E$5000=3101001)*(YEAR('Libro Diario'!$C$10:$C$5000)=$F$5)*('Libro Diario'!$H$10:$H$5000))+SUMPRODUCT(('Libro Diario'!$A$10:$A$5000=$B$5)*('Libro Diario'!$E$10:$E$5000=3103001)*(YEAR('Libro Diario'!$C$10:$C$5000)=$F$5)*('Libro Diario'!$H$10:$H$5000))+SUMPRODUCT(('Libro Diario'!$A$10:$A$5000=$B$5)*('Libro Diario'!$E$10:$E$5000=3103002)*(YEAR('Libro Diario'!$C$10:$C$5000)=$F$5)*('Libro Diario'!$H$10:$H$5000))+SUMPRODUCT(('Libro Diario'!$A$10:$A$5000=$B$5)*('Libro Diario'!$E$10:$E$5000=3103003)*(YEAR('Libro Diario'!$C$10:$C$5000)=$F$5)*('Libro Diario'!$H$10:$H$5000))+SUMPRODUCT(('Libro Diario'!$A$10:$A$5000=$B$5)*('Libro Diario'!$E$10:$E$5000=3103004)*(YEAR('Libro Diario'!$C$10:$C$5000)=$F$5)*('Libro Diario'!$H$10:$H$5000))+SUMPRODUCT(('Libro Diario'!$A$10:$A$5000=$B$5)*('Libro Diario'!$E$10:$E$5000=3103005)*(YEAR('Libro Diario'!$C$10:$C$5000)=$F$5)*('Libro Diario'!$H$10:$H$5000))+SUMPRODUCT(('Libro Diario'!$A$10:$A$5000=$B$5)*('Libro Diario'!$E$10:$E$5000=3103006)*(YEAR('Libro Diario'!$C$10:$C$5000)=$F$5)*('Libro Diario'!$H$10:$H$5000))+SUMPRODUCT(('Libro Diario'!$A$10:$A$5000=$B$5)*('Libro Diario'!$E$10:$E$5000=3103007)*(YEAR('Libro Diario'!$C$10:$C$5000)=$F$5)*('Libro Diario'!$H$10:$H$5000))+SUMPRODUCT(('Libro Diario'!$A$10:$A$5000=$B$5)*('Libro Diario'!$E$10:$E$5000=3103008)*(YEAR('Libro Diario'!$C$10:$C$5000)=$F$5)*('Libro Diario'!$H$10:$H$5000))+SUMPRODUCT(('Libro Diario'!$A$10:$A$5000=$B$5)*('Libro Diario'!$E$10:$E$5000=3103009)*(YEAR('Libro Diario'!$C$10:$C$5000)=$F$5)*('Libro Diario'!$H$10:$H$5000))+SUMPRODUCT(('Libro Diario'!$A$10:$A$5000=$B$5)*('Libro Diario'!$E$10:$E$5000=3103010)*(YEAR('Libro Diario'!$C$10:$C$5000)=$F$5)*('Libro Diario'!$H$10:$H$5000))+SUMPRODUCT(('Libro Diario'!$A$10:$A$5000=$B$5)*('Libro Diario'!$E$10:$E$5000=3201001)*(YEAR('Libro Diario'!$C$10:$C$5000)=$F$5)*('Libro Diario'!$H$10:$H$5000))) -> 0 | D9: =(SUMPRODUCT(('Libro Diario'!$A$10:$A$5000=$B$5)*('Libro Diario'!$E$10:$E$5000=4101001)*(YEAR('Libro Diario'!$C$10:$C$5000)=$G$5)*('Libro Diario'!$I$10:$I$5000))+SUMPRODUCT(('Libro Diario'!$A$10:$A$5000=$B$5)*('Libro Diario'!$E$10:$E$5000=4101002)*(YEAR('Libro Diario'!$C$10:$C$5000)=$G$5)*('Libro Diario'!$I$10:$I$5000))+SUMPRODUCT(('Libro Diario'!$A$10:$A$5000=$B$5)*('Libro Diario'!$E$10:$E$5000=4101003)*(YEAR('Libro Diario'!$C$10:$C$5000)=$G$5)*('Libro Diario'!$I$10:$I$5000))+SUMPRODUCT(('Libro Diario'!$A$10:$A$5000=$B$5)*('Libro Diario'!$E$10:$E$5000=4201001)*(YEAR('Libro Diario'!$C$10:$C$5000)=$G$5)*('Libro Diario'!$I$10:$I$5000)))-(SUMPRODUCT(('Libro Diario'!$A$10:$A$5000=$B$5)*('Libro Diario'!$E$10:$E$5000=3101001)*(YEAR('Libro Diario'!$C$10:$C$5000)=$G$5)*('Libro Diario'!$H$10:$H$5000))+SUMPRODUCT(('Libro Diario'!$A$10:$A$5000=$B$5)*('Libro Diario'!$E$10:$E$5000=3103001)*(YEAR('Libro Diario'!$C$10:$C$5000)=$G$5)*('Libro Diario'!$H$10:$H$5000))+SUMPRODUCT(('Libro Diario'!$A$10:$A$5000=$B$5)*('Libro Diario'!$E$10:$E$5000=3103002)*(YEAR('Libro Diario'!$C$10:$C$5000)=$G$5)*('Libro Diario'!$H$10:$H$5000))+SUMPRODUCT(('Libro Diario'!$A$10:$A$5000=$B$5)*('Libro Diario'!$E$10:$E$5000=3103003)*(YEAR('Libro Diario'!$C$10:$C$5000)=$G$5)*('Libro Diario'!$H$10:$H$5000))+SUMPRODUCT(('Libro Diario'!$A$10:$A$5000=$B$5)*('Libro Diario'!$E$10:$E$5000=3103004)*(YEAR('Libro Diario'!$C$10:$C$5000)=$G$5)*('Libro Diario'!$H$10:$H$5000))+SUMPRODUCT(('Libro Diario'!$A$10:$A$5000=$B$5)*('Libro Diario'!$E$10:$E$5000=3103005)*(YEAR('Libro Diario'!$C$10:$C$5000)=$G$5)*('Libro Diario'!$H$10:$H$5000))+SUMPRODUCT(('Libro Diario'!$A$10:$A$5000=$B$5)*('Libro Diario'!$E$10:$E$5000=3103006)*(YEAR('Libro Diario'!$C$10:$C$5000)=$G$5)*('Libro Diario'!$H$10:$H$5000))+SUMPRODUCT(('Libro Diario'!$A$10:$A$5000=$B$5)*('Libro Diario'!$E$10:$E$5000=3103007)*(YEAR('Libro Diario'!$C$10:$C$5000)=$G$5)*('Libro Diario'!$H$10:$H$5000))+SUMPRODUCT(('Libro Diario'!$A$10:$A$5000=$B$5)*('Libro Diario'!$E$10:$E$5000=3103008)*(YEAR('Libro Diario'!$C$10:$C$5000)=$G$5)*('Libro Diario'!$H$10:$H$5000))+SUMPRODUCT(('Libro Diario'!$A$10:$A$5000=$B$5)*('Libro Diario'!$E$10:$E$5000=3103009)*(YEAR('Libro Diario'!$C$10:$C$5000)=$G$5)*('Libro Diario'!$H$10:$H$5000))+SUMPRODUCT(('Libro Diario'!$A$10:$A$5000=$B$5)*('Libro Diario'!$E$10:$E$5000=3103010)*(YEAR('Libro Diario'!$C$10:$C$5000)=$G$5)*('Libro Diario'!$H$10:$H$5000))+SUMPRODUCT(('Libro Diario'!$A$10:$A$5000=$B$5)*('Libro Diario'!$E$10:$E$5000=3201001)*(YEAR('Libro Diario'!$C$10:$C$5000)=$G$5)*('Libro Diario'!$H$10:$H$5000))) -> 0 | F9: =C9-D9 -> 0 | G9: =IF(D9<>0,(C9-D9)/ABS(D9),"") | H9: Punto de partida método indirecto
B10: Ajustes por partidas no monetarias:
B11: (+) Depreciación del ejercicio | C11: =SUMPRODUCT(('Libro Diario'!$A$10:$A$5000=$B$5)*('Libro Diario'!$E$10:$E$5000=1201002)*(YEAR('Libro Diario'!$C$10:$C$5000)=$F$5)*('Libro Diario'!$I$10:$I$5000)) -> 0 | D11: =SUMPRODUCT(('Libro Diario'!$A$10:$A$5000=$B$5)*('Libro Diario'!$E$10:$E$5000=1201002)*(YEAR('Libro Diario'!$C$10:$C$5000)=$G$5)*('Libro Diario'!$I$10:$I$5000)) -> 0 | F11: =IF(ISNUMBER(C11),C11-D11,"") -> 0 | G11: =IF(AND(ISNUMBER(C11),ISNUMBER(D11),D11<>0),(C11-D11)/ABS(D11),"") | H11: Res. Ex. SII N°43/2002 – tablas depreciación
B12: (+/-) Variación CxC clientes | C12: =(SUMPRODUCT(('Libro Diario'!$A$10:$A$5000=$B$5)*('Libro Diario'!$E$10:$E$5000=1104001)*(YEAR('Libro Diario'!$C$10:$C$5000)=$F$5)*('Libro Diario'!$H$10:$H$5000)))-(SUMPRODUCT(('Libro Diario'!$A$10:$A$5000=$B$5)*('Libro Diario'!$E$10:$E$5000=1104001)*(YEAR('Libro Diario'!$C$10:$C$5000)=$F$5)*('Libro Diario'!$I$10:$I$5000)))-((SUMPRODUCT(('Libro Diario'!$A$10:$A$5000=$B$5)*('Libro Diario'!$E$10:$E$5000=1104001)*(YEAR('Libro Diario'!$C$10:$C$5000)=$G$5)*('Libro Diario'!$H$10:$H$5000)))-(SUMPRODUCT(('Libro Diario'!$A$10:$A$5000=$B$5)*('Libro Diario'!$E$10:$E$5000=1104001)*(YEAR('Libro Diario'!$C$10:$C$5000)=$G$5)*('Libro Diario'!$I$10:$I$5000)))) -> 0 | D12: =(SUMPRODUCT(('Libro Diario'!$A$10:$A$5000=$B$5)*('Libro Diario'!$E$10:$E$5000=1104001)*(YEAR('Libro Diario'!$C$10:$C$5000)=$G$5)*('Libro Diario'!$H$10:$H$5000)))-(SUMPRODUCT(('Libro Diario'!$A$10:$A$5000=$B$5)*('Libro Diario'!$E$10:$E$5000=1104001)*(YEAR('Libro Diario'!$C$10:$C$5000)=$G$5)*('Libro Diario'!$I$10:$I$5000))) -> 0 | F12: =IF(ISNUMBER(C12),C12-D12,"") -> 0 | G12: =IF(AND(ISNUMBER(C12),ISNUMBER(D12),D12<>0),(C12-D12)/ABS(D12),"") | H12: Δ CxC: positivo = cobros, negativo = mayor crédito
B13: (+/-) Variación inventarios | C13: =(SUMPRODUCT(('Libro Diario'!$A$10:$A$5000=$B$5)*('Libro Diario'!$E$10:$E$5000=1108001)*(YEAR('Libro Diario'!$C$10:$C$5000)=$F$5)*('Libro Diario'!$H$10:$H$5000))+SUMPRODUCT(('Libro Diario'!$A$10:$A$5000=$B$5)*('Libro Diario'!$E$10:$E$5000=1108002)*(YEAR('Libro Diario'!$C$10:$C$5000)=$F$5)*('Libro Diario'!$H$10:$H$5000)))-(SUMPRODUCT(('Libro Diario'!$A$10:$A$5000=$B$5)*('Libro Diario'!$E$10:$E$5000=1108001)*(YEAR('Libro Diario'!$C$10:$C$5000)=$F$5)*('Libro Diario'!$I$10:$I$5000))+SUMPRODUCT(('Libro Diario'!$A$10:$A$5000=$B$5)*('Libro Diario'!$E$10:$E$5000=1108002)*(YEAR('Libro Diario'!$C$10:$C$5000)=$F$5)*('Libro Diario'!$I$10:$I$5000)))-((SUMPRODUCT(('Libro Diario'!$A$10:$A$5000=$B$5)*('Libro Diario'!$E$10:$E$5000=1108001)*(YEAR('Libro Diario'!$C$10:$C$5000)=$G$5)*('Libro Diario'!$H$10:$H$5000))+SUMPRODUCT(('Libro Diario'!$A$10:$A$5000=$B$5)*('Libro Diario'!$E$10:$E$5000=1108002)*(YEAR('Libro Diario'!$C$10:$C$5000)=$G$5)*('Libro Diario'!$H$10:$H$5000)))-(SUMPRODUCT(('Libro Diario'!$A$10:$A$5000=$B$5)*('Libro Diario'!$E$10:$E$5000=1108001)*(YEAR('Libro Diario'!$C$10:$C$5000)=$G$5)*('Libro Diario'!$I$10:$I$5000))+SUMPRODUCT(('Libro Diario'!$A$10:$A$5000=$B$5)*('Libro Diario'!$E$10:$E$5000=1108002)*(YEAR('Libro Diario'!$C$10:$C$5000)=$G$5)*('Libro Diario'!$I$10:$I$5000)))) -> 0 | D13: 0 | F13: =IF(ISNUMBER(C13),C13-D13,"") -> 0 | G13: =IF(AND(ISNUMBER(C13),ISNUMBER(D13),D13<>0),(C13-D13)/ABS(D13),"") | H13: Δ Inventario: positivo = reducción stock
B14: (+/-) Variación CxP proveedores | C14: =(SUMPRODUCT(('Libro Diario'!$A$10:$A$5000=$B$5)*('Libro Diario'!$E$10:$E$5000=2102001)*(YEAR('Libro Diario'!$C$10:$C$5000)=$F$5)*('Libro Diario'!$I$10:$I$5000)))-(SUMPRODUCT(('Libro Diario'!$A$10:$A$5000=$B$5)*('Libro Diario'!$E$10:$E$5000=2102001)*(YEAR('Libro Diario'!$C$10:$C$5000)=$F$5)*('Libro Diario'!$H$10:$H$5000)))-((SUMPRODUCT(('Libro Diario'!$A$10:$A$5000=$B$5)*('Libro Diario'!$E$10:$E$5000=2102001)*(YEAR('Libro Diario'!$C$10:$C$5000)=$G$5)*('Libro Diario'!$I$10:$I$5000)))-(SUMPRODUCT(('Libro Diario'!$A$10:$A$5000=$B$5)*('Libro Diario'!$E$10:$E$5000=2102001)*(YEAR('Libro Diario'!$C$10:$C$5000)=$G$5)*('Libro Diario'!$H$10:$H$5000)))) -> 0 | D14: 0 | F14: =IF(ISNUMBER(C14),C14-D14,"") -> 0 | G14: =IF(AND(ISNUMBER(C14),ISNUMBER(D14),D14<>0),(C14-D14)/ABS(D14),"") | H14: Δ CxP: positivo = mayor plazo proveedores
B15: (+/-) Variación remuneraciones por pagar | C15: =(SUMPRODUCT(('Libro Diario'!$A$10:$A$5000=$B$5)*('Libro Diario'!$E$10:$E$5000=2103001)*(YEAR('Libro Diario'!$C$10:$C$5000)=$F$5)*('Libro Diario'!$I$10:$I$5000)))-(SUMPRODUCT(('Libro Diario'!$A$10:$A$5000=$B$5)*('Libro Diario'!$E$10:$E$5000=2103001)*(YEAR('Libro Diario'!$C$10:$C$5000)=$F$5)*('Libro Diario'!$H$10:$H$5000)))-((SUMPRODUCT(('Libro Diario'!$A$10:$A$5000=$B$5)*('Libro Diario'!$E$10:$E$5000=2103001)*(YEAR('Libro Diario'!$C$10:$C$5000)=$G$5)*('Libro Diario'!$I$10:$I$5000)))-(SUMPRODUCT(('Libro Diario'!$A$10:$A$5000=$B$5)*('Libro Diario'!$E$10:$E$5000=2103001)*(YEAR('Libro Diario'!$C$10:$C$5000)=$G$5)*('Libro Diario'!$H$10:$H$5000)))) -> 0 | D15: 0 | F15: =IF(ISNUMBER(C15),C15-D15,"") -> 0 | G15: =IF(AND(ISNUMBER(C15),ISNUMBER(D15),D15<>0),(C15-D15)/ABS(D15),"") | H15: Cód. del Trabajo Art. 54 bis – pago mensual
B16: (+/-) Variación IVA (CF-DF) | C16: =((SUMPRODUCT(('Libro Diario'!$A$10:$A$5000=$B$5)*('Libro Diario'!$E$10:$E$5000=1107101)*(YEAR('Libro Diario'!$C$10:$C$5000)=$F$5)*('Libro Diario'!$H$10:$H$5000)))-(SUMPRODUCT(('Libro Diario'!$A$10:$A$5000=$B$5)*('Libro Diario'!$E$10:$E$5000=1107101)*(YEAR('Libro Diario'!$C$10:$C$5000)=$F$5)*('Libro Diario'!$I$10:$I$5000))))-((SUMPRODUCT(('Libro Diario'!$A$10:$A$5000=$B$5)*('Libro Diario'!$E$10:$E$5000=2105101)*(YEAR('Libro Diario'!$C$10:$C$5000)=$F$5)*('Libro Diario'!$I$10:$I$5000)))-(SUMPRODUCT(('Libro Diario'!$A$10:$A$5000=$B$5)*('Libro Diario'!$E$10:$E$5000=2105101)*(YEAR('Libro Diario'!$C$10:$C$5000)=$F$5)*('Libro Diario'!$H$10:$H$5000)))) -> 0 | D16: 0 | F16: =IF(ISNUMBER(C16),C16-D16,"") -> 0 | G16: =IF(AND(ISNUMBER(C16),ISNUMBER(D16),D16<>0),(C16-D16)/ABS(D16),"") | H16: D.L. 825 IVA – saldo técnico
B17: FLUJO NETO OPERACIONAL | C17: =SUM(C9:C16) -> 0 | D17: =SUM(D9:D16) -> 0 | F17: =C17-D17 -> 0 | G17: =IF(D17<>0,(C17-D17)/ABS(D17),"")
B18: 2. FLUJO DE ACTIVIDADES DE INVERSIÓN (NIIF Pymes Sec. 7.10)
B19: (-) Compras de activo fijo / propiedades | C19: =SUMPRODUCT(('Libro Diario'!$A$10:$A$5000=$B$5)*('Libro Diario'!$E$10:$E$5000=1201001)*(YEAR('Libro Diario'!$C$10:$C$5000)=$F$5)*('Libro Diario'!$H$10:$H$5000)) -> 0 | D19: =SUMPRODUCT(('Libro Diario'!$A$10:$A$5000=$B$5)*('Libro Diario'!$E$10:$E$5000=1201001)*(YEAR('Libro Diario'!$C$10:$C$5000)=$G$5)*('Libro Diario'!$H$10:$H$5000)) -> 0 | F19: =IF(ISNUMBER(C19),C19-D19,"") -> 0 | G19: =IF(AND(ISNUMBER(C19),ISNUMBER(D19),D19<>0),(C19-D19)/ABS(D19),"") | H19: NIIF Sec. 17 PPE – costo histórico
B20: (+) Ventas de activos / recupero | C20: =SUMPRODUCT(('Libro Diario'!$A$10:$A$5000=$B$5)*('Libro Diario'!$E$10:$E$5000=1201001)*(YEAR('Libro Diario'!$C$10:$C$5000)=$F$5)*('Libro Diario'!$I$10:$I$5000)) -> 0 | D20: =SUMPRODUCT(('Libro Diario'!$A$10:$A$5000=$B$5)*('Libro Diario'!$E$10:$E$5000=1201001)*(YEAR('Libro Diario'!$C$10:$C$5000)=$G$5)*('Libro Diario'!$I$10:$I$5000)) -> 0 | F20: =IF(ISNUMBER(C20),C20-D20,"") -> 0 | G20: =IF(AND(ISNUMBER(C20),ISNUMBER(D20),D20<>0),(C20-D20)/ABS(D20),"")
B21: FLUJO NETO INVERSIÓN | C21: =SUM(C19:C20) -> 0 | D21: =SUM(D19:D20) -> 0 | F21: =C21-D21 -> 0 | G21: =IF(D21<>0,(C21-D21)/ABS(D21),"")
B22: 3. FLUJO DE ACTIVIDADES DE FINANCIAMIENTO (NIIF Pymes Sec. 7.14)
B23: (+) Préstamos / créditos obtenidos | C23: =SUMPRODUCT(('Libro Diario'!$A$10:$A$5000=$B$5)*('Libro Diario'!$E$10:$E$5000=2201001)*(YEAR('Libro Diario'!$C$10:$C$5000)=$F$5)*('Libro Diario'!$I$10:$I$5000))+SUMPRODUCT(('Libro Diario'!$A$10:$A$5000=$B$5)*('Libro Diario'!$E$10:$E$5000=2201002)*(YEAR('Libro Diario'!$C$10:$C$5000)=$F$5)*('Libro Diario'!$I$10:$I$5000)) -> 0 | D23: =SUMPRODUCT(('Libro Diario'!$A$10:$A$5000=$B$5)*('Libro Diario'!$E$10:$E$5000=2201001)*(YEAR('Libro Diario'!$C$10:$C$5000)=$G$5)*('Libro Diario'!$I$10:$I$5000))+SUMPRODUCT(('Libro Diario'!$A$10:$A$5000=$B$5)*('Libro Diario'!$E$10:$E$5000=2201002)*(YEAR('Libro Diario'!$C$10:$C$5000)=$G$5)*('Libro Diario'!$I$10:$I$5000)) -> 0 | F23: =IF(ISNUMBER(C23),C23-D23,"") -> 0 | G23: =IF(AND(ISNUMBER(C23),ISNUMBER(D23),D23<>0),(C23-D23)/ABS(D23),"") | H23: Incluye Banco BancoEstado MIPE, CORFO
B24: (-) Amortización / pago de deudas | C24: =SUMPRODUCT(('Libro Diario'!$A$10:$A$5000=$B$5)*('Libro Diario'!$E$10:$E$5000=2201001)*(YEAR('Libro Diario'!$C$10:$C$5000)=$F$5)*('Libro Diario'!$H$10:$H$5000))+SUMPRODUCT(('Libro Diario'!$A$10:$A$5000=$B$5)*('Libro Diario'!$E$10:$E$5000=2201002)*(YEAR('Libro Diario'!$C$10:$C$5000)=$F$5)*('Libro Diario'!$H$10:$H$5000)) -> 0 | D24: =SUMPRODUCT(('Libro Diario'!$A$10:$A$5000=$B$5)*('Libro Diario'!$E$10:$E$5000=2201001)*(YEAR('Libro Diario'!$C$10:$C$5000)=$G$5)*('Libro Diario'!$H$10:$H$5000))+SUMPRODUCT(('Libro Diario'!$A$10:$A$5000=$B$5)*('Libro Diario'!$E$10:$E$5000=2201002)*(YEAR('Libro Diario'!$C$10:$C$5000)=$G$5)*('Libro Diario'!$H$10:$H$5000)) -> 0 | F24: =IF(ISNUMBER(C24),C24-D24,"") -> 0 | G24: =IF(AND(ISNUMBER(C24),ISNUMBER(D24),D24<>0),(C24-D24)/ABS(D24),"") | H24: Pago capital — Art. 31 N°7 LIR
B25: (-) Pago de intereses / gastos financieros | C25: =SUMPRODUCT(('Libro Diario'!$A$10:$A$5000=$B$5)*('Libro Diario'!$E$10:$E$5000=3201001)*(YEAR('Libro Diario'!$C$10:$C$5000)=$F$5)*('Libro Diario'!$H$10:$H$5000)) -> 0 | D25: =SUMPRODUCT(('Libro Diario'!$A$10:$A$5000=$B$5)*('Libro Diario'!$E$10:$E$5000=3201001)*(YEAR('Libro Diario'!$C$10:$C$5000)=$G$5)*('Libro Diario'!$H$10:$H$5000)) -> 0 | F25: =IF(ISNUMBER(C25),C25-D25,"") -> 0 | G25: =IF(AND(ISNUMBER(C25),ISNUMBER(D25),D25<>0),(C25-D25)/ABS(D25),"") | H25: Art. 31 N°1 LIR – deducible si vinculado al giro
B26: (+/-) Aportes / retiros de capital | C26: =SUMPRODUCT(('Libro Diario'!$A$10:$A$5000=$B$5)*('Libro Diario'!$E$10:$E$5000=2301001)*(YEAR('Libro Diario'!$C$10:$C$5000)=$F$5)*('Libro Diario'!$I$10:$I$5000))-SUMPRODUCT(('Libro Diario'!$A$10:$A$5000=$B$5)*('Libro Diario'!$E$10:$E$5000=2301001)*(YEAR('Libro Diario'!$C$10:$C$5000)=$F$5)*('Libro Diario'!$H$10:$H$5000)) -> 0 | D26: =SUMPRODUCT(('Libro Diario'!$A$10:$A$5000=$B$5)*('Libro Diario'!$E$10:$E$5000=2301001)*(YEAR('Libro Diario'!$C$10:$C$5000)=$G$5)*('Libro Diario'!$I$10:$I$5000))-SUMPRODUCT(('Libro Diario'!$A$10:$A$5000=$B$5)*('Libro Diario'!$E$10:$E$5000=2301001)*(YEAR('Libro Diario'!$C$10:$C$5000)=$G$5)*('Libro Diario'!$H$10:$H$5000)) -> 0 | F26: =IF(ISNUMBER(C26),C26-D26,"") -> 0 | G26: =IF(AND(ISNUMBER(C26),ISNUMBER(D26),D26<>0),(C26-D26)/ABS(D26),"") | H26: Art. 17 N°5 LIR – aporte capital no tributa
B27: FLUJO NETO FINANCIAMIENTO | C27: =SUM(C23:C26) -> 0 | D27: =SUM(D23:D26) -> 0 | F27: =C27-D27 -> 0 | G27: =IF(D27<>0,(C27-D27)/ABS(D27),"")
B29: VARIACIÓN NETA DE CAJA (Σ 1+2+3) | C29: =C17+C21+C27 -> 0 | D29: =D17+D21+D27 -> 0 | F29: =C29-D29 -> 0 | G29: =IF(D29<>0,(C29-D29)/ABS(D29),"")
B30: Saldo inicial de Caja y Bancos (al 01/01) | C30: =SUMPRODUCT(('Libro Diario'!$A$10:$A$5000=$B$5)*('Libro Diario'!$E$10:$E$5000=1101001)*(YEAR('Libro Diario'!$C$10:$C$5000)=$G$5)*('Libro Diario'!$H$10:$H$5000))+SUMPRODUCT(('Libro Diario'!$A$10:$A$5000=$B$5)*('Libro Diario'!$E$10:$E$5000=1101002)*(YEAR('Libro Diario'!$C$10:$C$5000)=$G$5)*('Libro Diario'!$H$10:$H$5000)) -> 0 | D30: 0 | F30: =IF(ISNUMBER(C30),C30-D30,"") -> 0 | G30: =IF(AND(ISNUMBER(C30),ISNUMBER(D30),D30<>0),(C30-D30)/ABS(D30),"") | H30: Tomado del año anterior como saldo de apertura
B31: SALDO FINAL DE CAJA Y BANCOS | C31: =C29+C30 -> 0 | D31: =D30 -> 0
B33: 4. INDICADORES DE SOSTENIBILIDAD Y GESTIÓN DE CAJA (SERCOTEC · CMF · CORFO)
B34: INDICADOR | C34: VALOR | D34: 🚦 | F34: INTERPRETACIÓN | H34: UMBRAL 🟢 | I34: UMBRAL 🟡
B35: Liquidez y Runway de Caja
B36: Runway / Autonomía de Caja (meses) | C36: =IF($K$150<>0,$J$150/$K$150,0) -> 0 | D36: =IF(C36>=3,"🟢",IF(C36>=1,"🟡","🔴")) -> 🔴 | F36: Meses que puede operar sin ingresos. < 1 mes = riesgo crítico de insolvencia. | H36: SERCOTEC Cap. Trabajo · Ley 20.720 Art. 2
C37: ≥ 3 meses | D37: 1–3 meses
B38: Índice de Cobertura de Gastos Fijos | C38: =IF($K$150<>0,$L$150/($K$150*12),0) -> 0 | D38: =IF(C38>=1.2,"🟢",IF(C38>=1,"🟡","🔴")) -> 🔴 | F38: Ingresos totales / Gastos fijos anuales. < 1 = no cubre sus costos. | H38: CORFO benchmark MYPE · CMF análisis crédito
C39: ≥ 1.20 | D39: 1.00–1.20
B40: Burn Rate y Punto de Equilibrio
B41: Burn Rate mensual (gastos operac. mensuales, $) | C41: =$K$150 -> 0 | D41: =IF($K$150>0,IF($K$150/$L$150*12<=0.85,"🟢",IF($K$150/$L$150*12<=0.95,"🟡","🔴")),"🟢") -> 🟢 | F41: Gasto operacional promedio mensual. Si supera el 95% de ingresos mensuales, insostenible. | H41: SERCOTEC Gestión Financiera MYPE 2023
C42: < 85% ing. | D42: 85–95% ing.
B43: Punto de Equilibrio (ventas mínimas, $) | C43: =IF($L$150<>0,($M$150-(SUMPRODUCT(('Libro Diario'!$A$10:$A$5000=$B$5)*('Libro Diario'!$E$10:$E$5000=3101001)*(YEAR('Libro Diario'!$C$10:$C$5000)=$F$5)*('Libro Diario'!$H$10:$H$5000))))/(1-(SUMPRODUCT(('Libro Diario'!$A$10:$A$5000=$B$5)*('Libro Diario'!$E$10:$E$5000=3101001)*(YEAR('Libro Diario'!$C$10:$C$5000)=$F$5)*('Libro Diario'!$H$10:$H$5000)))/$L$150),0) -> 0 | D43: =IF($L$150<>0,IF($L$150>=($M$150-(SUMPRODUCT(('Libro Diario'!$A$10:$A$5000=$B$5)*('Libro Diario'!$E$10:$E$5000=3101001)*(YEAR('Libro Diario'!$C$10:$C$5000)=$F$5)*('Libro Diario'!$H$10:$H$5000))))/(1-(SUMPRODUCT(('Libro Diario'!$A$10:$A$5000=$B$5)*('Libro Diario'!$E$10:$E$5000=3101001)*(YEAR('Libro Diario'!$C$10:$C$5000)=$F$5)*('Libro Diario'!$H$10:$H$5000)))/$L$150),"🟢","🔴"),"🟡") -> 🟡 | F43: Ventas mínimas para cubrir todos los costos. Si ventas actuales < P.Eq., empresa en pérdida. | H43: Análisis CVU · SERCOTEC Herramientas Financieras
C44: Ingresos ≥ P.Eq. | D44: –
B45: Ciclo de Conversión de Efectivo (CCE)
B46: Período Medio de Cobro — PMC (días) | C46: =IF($L$150<>0,($Q$150/$L$150)*365,0) -> 0 | D46: =IF(C46<=30,"🟢",IF(C46<=60,"🟡","🔴")) -> 🟢 | F46: Días promedio que tarda en cobrar facturas. > 60 días deteriora el flujo de caja. | H46: CMF Análisis Crédito MYPE · Art. 12 Ley 19.983
C47: ≤ 30 días | D47: 30–60 días
B48: Días de Inventario (DI) | C48: =IF(SUMPRODUCT(('Libro Diario'!$A$10:$A$5000=$B$5)*('Libro Diario'!$E$10:$E$5000=3101001)*(YEAR('Libro Diario'!$C$10:$C$5000)=$F$5)*('Libro Diario'!$H$10:$H$5000))<>0,((SUMPRODUCT(('Libro Diario'!$A$10:$A$5000=$B$5)*('Libro Diario'!$E$10:$E$5000=1108001)*(YEAR('Libro Diario'!$C$10:$C$5000)=$F$5)*('Libro Diario'!$H$10:$H$5000))-SUMPRODUCT(('Libro Diario'!$A$10:$A$5000=$B$5)*('Libro Diario'!$E$10:$E$5000=1108001)*(YEAR('Libro Diario'!$C$10:$C$5000)=$F$5)*('Libro Diario'!$I$10:$I$5000))+SUMPRODUCT(('Libro Diario'!$A$10:$A$5000=$B$5)*('Libro Diario'!$E$10:$E$5000=1108002)*(YEAR('Libro Diario'!$C$10:$C$5000)=$F$5)*('Libro Diario'!$H$10:$H$5000))-SUMPRODUCT(('Libro Diario'!$A$10:$A$5000=$B$5)*('Libro Diario'!$E$10:$E$5000=1108002)*(YEAR('Libro Diario'!$C$10:$C$5000)=$F$5)*('Libro Diario'!$I$10:$I$5000)))/SUMPRODUCT(('Libro Diario'!$A$10:$A$5000=$B$5)*('Libro Diario'!$E$10:$E$5000=3101001)*(YEAR('Libro Diario'!$C$10:$C$5000)=$F$5)*('Libro Diario'!$H$10:$H$5000)))*365,0) -> 0 | D48: =IF(C48<=30,"🟢",IF(C48<=60,"🟡","🔴")) -> 🟢 | F48: Días que el inventario permanece en bodega. Alto = capital inmovilizado. | H48: SERCOTEC Gestión de Inventarios MYPE
C49: ≤ 30 días | D49: 30–60 días
B50: Ciclo de Conversión de Efectivo — CCE (días) | C50: =C46+C48-(IF(SUMPRODUCT(('Libro Diario'!$A$10:$A$5000=$B$5)*('Libro Diario'!$E$10:$E$5000=3101001)*(YEAR('Libro Diario'!$C$10:$C$5000)=$F$5)*('Libro Diario'!$H$10:$H$5000))<>0,((SUMPRODUCT(('Libro Diario'!$A$10:$A$5000=$B$5)*('Libro Diario'!$E$10:$E$5000=2102001)*(YEAR('Libro Diario'!$C$10:$C$5000)=$F$5)*('Libro Diario'!$I$10:$I$5000))-SUMPRODUCT(('Libro Diario'!$A$10:$A$5000=$B$5)*('Libro Diario'!$E$10:$E$5000=2102001)*(YEAR('Libro Diario'!$C$10:$C$5000)=$F$5)*('Libro Diario'!$H$10:$H$5000)))/SUMPRODUCT(('Libro Diario'!$A$10:$A$5000=$B$5)*('Libro Diario'!$E$10:$E$5000=3101001)*(YEAR('Libro Diario'!$C$10:$C$5000)=$F$5)*('Libro Diario'!$H$10:$H$5000)))*365,0)) -> 0 | D50: =IF(C50<=30,"🟢",IF(C50<=60,"🟡","🔴")) -> 🟢 | F50: PMC + DI - PMP. Días en que el capital queda sin liquidez. < 30 = excelente gestión. | H50: NIC 7 · SERCOTEC · CMF
C51: ≤ 30 días | D51: 30–60 días
B52: Sostenibilidad de la Deuda y Capacidad de Pago
B53: Flujo Operacional / Deuda Corriente | C53: =IF($O$150<>0,C17/$O$150,0) -> 0 | D53: =IF(C53>=1,"🟢",IF(C53>=0.5,"🟡","🔴")) -> 🔴 | F53: Flujo operacional vs deudas de corto plazo. < 0.5 = riesgo de cesación de pagos. | H53: Ley 20.720 Art. 2 · CMF Riesgo MYPE
C54: ≥ 1.0 | D54: 0.5–1.0
B55: Índice de Cobertura de Intereses (DSCR) | C55: =IF($N$150<>0,$P$150/$N$150,0) -> 0 | D55: =IF(C55>=1.5,"🟢",IF(C55>=1,"🟡","🔴")) -> 🔴 | F55: EBIT / Gastos financieros. < 1 = no genera suficiente para pagar intereses. | H55: Art. 31 N°1 LIR · BancoEstado MIPE scoring
C56: ≥ 1.50 | D56: 1.00–1.50
B57: Margen de Flujo Libre (Free Cash Flow %) | C57: =IF($L$150<>0,C17/$L$150,0) -> 0 | D57: =IF(C57>=0.1,"🟢",IF(C57>=0.05,"🟡","🔴")) -> 🔴 | F57: Flujo operacional / Ingresos. Mide qué % de ventas se convierte en caja libre. | H57: CORFO Evaluación Crédito · CMF Supervisión
C58: ≥ 10% | D58: 5–10%
B60: 5. DETALLE MENSUAL DE INGRESOS Y GASTOS (año seleccionado)
B61: Concepto | C61: ENE | D61: FEB | E61: MAR | F61: ABR | G61: MAY | H61: JUN | I61: JUL | J61: AGO | K61: SEP | L61: OCT | M61: NOV | N61: DIC | O61: TOTAL
